Workbook

Sheet Apple Consolidated Statements
A1: Apple Inc. Historical Financial Statements (FY1992–FY2025)
A2: Units: $ millions unless otherwise noted; EPS/dividends in $/share; share counts in thousands.
A4: Fiscal Year | B4: 1992 | C4: 1993 | D4: 1994 | E4: 1995 | F4: 1996 | G4: 1997 | H4: 1998 | I4: 1999 | J4: 2000 | K4: 2001 | L4: 2002 | M4: 2003 | N4: 2004 | O4: 2005 | P4: 2006 | Q4: 2007 | R4: 2008 | S4: 2009 | T4: 2010 | U4: 2011 | V4: 2012 | W4: 2013 | X4: 2014 | Y4: 2015 | Z4: 2016 | AA4: 2017 | AB4: 2018 | AC4: 2019 | AD4: 2020 | AE4: 2021 | AF4: 2022 | AG4: 2023 | AH4: 2024 | AI4: 2025
A6: INCOME STATEMENT | AL6: 5yr | AM6: Check | AO6: 3yr | AP6: Check
A7: Products Net Sales | B7: 0 | C7: 0 | D7: 0 | E7: 0 | F7: 0 | G7: 0 | H7: 0 | I7: 0 | J7: 0 | K7: 0 | L7: 0 | M7: 0 | N7: 0 | O7: 0 | P7: 0 | Q7: 0 | R7: 0 | S7: 0 | T7: 0 | U7: 0 | V7: 0 | W7: 0 | X7: 0 | Y7: 0 | Z7: 0 | AA7: 0 | AB7: 0 | AC7: 213883 | AD7: 220747 | AE7: 297392 | AF7: 316199 | AG7: 298085 | AH7: 294866 | AI7: 307003 | AL7: =IFERROR((AI7/AD7)^(1/5)-1,"") -> 0.068192592 | AM7: =IFERROR(PRODUCT(1+AE8,1+AF8,1+AG8,1+AH8,1+AI8)^(1/5)-1,"") -> 0.068192592 | AO7: =IFERROR((AI7/AF7)^(1/3)-1,"") -> -0.0097898453 | AP7: =IFERROR(PRODUCT(1+AG8,1+AH8,1+AI8)^(1/3)-1,"") -> -0.0097898453
A8: % Growth | AD8: =IFERROR(AD7/AC7-1,"") -> 0.032092312 | AE8: =IFERROR(AE7/AD7-1,"") -> 0.34720744 | AF8: =IFERROR(AF7/AE7-1,"") -> 0.063239764 | AG8: =IFERROR(AG7/AF7-1,"") -> -0.057286709 | AH8: =IFERROR(AH7/AG7-1,"") -> -0.010798933 | AI8: =IFERROR(AI7/AH7-1,"") -> 0.04116107 | AL8: =IFERROR((AI9/AD9)^(1/5)-1,"") -> 0.15214287 | AM8: =IFERROR(PRODUCT(1+AE10,1+AF10,1+AG10,1+AH10,1+AI10)^(1/5)-1,"") -> 0.15214287 | AO8: =IFERROR((AI9/AF9)^(1/3)-1,"") -> 0.11792955 | AP8: =IFERROR(PRODUCT(1+AG10,1+AH10,1+AI10)^(1/3)-1,"") -> 0.11792955
A9: Services Net Sales | B9: 0 | C9: 0 | D9: 0 | E9: 0 | F9: 0 | G9: 0 | H9: 0 | I9: 0 | J9: 0 | K9: 0 | L9: 0 | M9: 0 | N9: 0 | O9: 0 | P9: 0 | Q9: 0 | R9: 0 | S9: 0 | T9: 0 | U9: 0 | V9: 0 | W9: 0 | X9: 0 | Y9: 0 | Z9: 0 | AA9: 0 | AB9: 0 | AC9: 46291 | AD9: 53768 | AE9: 68425 | AF9: 78129 | AG9: 85200 | AH9: 96169 | AI9: 109158
A10: % Growth | AD10: =IFERROR(AD9/AC9-1,"") -> 0.16152168 | AE10: =IFERROR(AE9/AD9-1,"") -> 0.27259708 | AF10: =IFERROR(AF9/AE9-1,"") -> 0.14181951 | AG10: =IFERROR(AG9/AF9-1,"") -> 0.090504166 | AH10: =IFERROR(AH9/AG9-1,"") -> 0.12874413 | AI10: =IFERROR(AI9/AH9-1,"") -> 0.13506431 | AL10: 33yr | AM10: Check | AO10: 20yr | AP10: Check | AR10: 10yr | AS10: Check | AU10: 5yr | AV10: Check
A11: Net Sales / Revenue | B11: 7086.542 | C11: 7976.954 | D11: 9188.748 | E11: 11062 | F11: 9833 | G11: 7081 | H11: 5941 | I11: 6134 | J11: 7983 | K11: 5363 | L11: 5742 | M11: 6207 | N11: 8279 | O11: 13931 | P11: 19315 | Q11: 24578 | R11: 37491 | S11: 42905 | T11: 65225 | U11: 108249 | V11: 156508 | W11: 170910 | X11: 182795 | Y11: 233715 | Z11: 215639 | AA11: 229234 | AB11: 265595 | AC11: =AC9+AC7 -> 260174 | AD11: =AD9+AD7 -> 274515 | AE11: =AE9+AE7 -> 365817 | AF11: =AF9+AF7 -> 394328 | AG11: =AG9+AG7 -> 383285 | AH11: =AH9+AH7 -> 391035 | AI11: =AI9+AI7 -> 416161 | AL11: =IFERROR((AI11/B11)^(1/33)-1,"") -> 0.13136 | AM11: =IFERROR(PRODUCT(1+C12,1+D12,1+E12,1+F12,1+G12,1+H12,1+I12,1+J12,1+K12,1+L12,1+M12,1+N12,1+O12,1+P12,1+Q12,1+R12,1+S12,1+T12,1+U12,1+V12,1+W12,1+X12,1+Y12,1+Z12,1+AA12,1+AB12,1+AC12,1+AD12,1+AE12,1+AF12,1+AG12,1+AH12,1+AI12)^(1/33)-1,"") -> 0.13136 | AO11: =IFERROR((AI11/O11)^(1/20)-1, "") -> 0.18512444 | AP11: =IFERROR(PRODUCT(1+P12,1+Q12,1+R12,1+S12,1+T12,1+U12,1+V12,1+W12,1+X12,1+Y12,1+Z12,1+AA12,1+AB12,1+AC12,1+AD12,1+AE12,1+AF12,1+AG12,1+AH12,1+AI12)^(1/20)-1,"") -> 0.18512444 | AR11: =IFERROR((AI11/Y11)^(1/10)-1,"") -> 0.059393927 | AS11: =IFERROR(PRODUCT(1+Z12,1+AA12,1+AB12,1+AC12,1+AD12,1+AE12,1+AF12,1+AG12,1+AH12,1+AI12)^(1/10)-1,"") -> 0.059393927 | AU11: =IFERROR((AI11/AD11)^(1/5)-1,"") -> 0.086773549 | AV11: =IFERROR(PRODUCT(1+AE12,1+AF12,1+AG12,1+AH12,1+AI12)^(1/5)-1,"") -> 0.086773549
A12: % Growth | C12: =IFERROR(C11/B11-1,"") -> 0.12564831 | D12: =IFERROR(D11/C11-1,"") -> 0.15191187 | E12: =IFERROR(E11/D11-1,"") -> 0.20386368 | F12: =IFERROR(F11/E11-1,"") -> -0.11110107 | G12: =IFERROR(G11/F11-1,"") -> -0.27987389 | H12: =IFERROR(H11/G11-1,"") -> -0.16099421 | I12: =IFERROR(I11/H11-1,"") -> 0.032486113 | J12: =IFERROR(J11/I11-1,"") -> 0.30143463 | ... AI12: =IFERROR(AI11/AH11-1,"") -> 0.064255118
A14: Products Cost of Sales | B14: 0 | C14: 0 | D14: 0 | E14: 0 | F14: 0 | G14: 0 | H14: 0 | I14: 0 | J14: 0 | K14: 0 | L14: 0 | M14: 0 | N14: 0 | O14: 0 | P14: 0 | Q14: 0 | R14: 0 | S14: 0 | T14: 0 | U14: 0 | V14: 0 | W14: 0 | X14: 0 | Y14: 0 | Z14: 0 | AA14: 0 | AB14: 0 | AC14: 144996 | AD14: 151286 | AE14: 192266 | AF14: 201471 | AG14: 189282 | AH14: 185233 | AI14: 194116
A15: % Growth | AD15: =IFERROR(AD14/AC14-1,"") -> 0.043380507 | AE15: =IFERROR(AE14/AD14-1,"") -> 0.27087768 | AF15: =IFERROR(AF14/AE14-1,"") -> 0.04787638 | AG15: =IFERROR(AG14/AF14-1,"") -> -0.060500022 | AH15: =IFERROR(AH14/AG14-1,"") -> -0.021391363 | AI15: =IFERROR(AI14/AH14-1,"") -> 0.047955818
A16: Services Cost of Sales | B16: 0 | C16: 0 | D16: 0 | E16: 0 | F16: 0 | G16: 0 | H16: 0 | I16: 0 | J16: 0 | K16: 0 | L16: 0 | M16: 0 | N16: 0 | O16: 0 | P16: 0 | Q16: 0 | R16: 0 | S16: 0 | T16: 0 | U16: 0 | V16: 0 | W16: 0 | X16: 0 | Y16: 0 | Z16: 0 | AA16: 0 | AB16: 0 | AC16: 16786 | AD16: 18273 | AE16: 20715 | AF16: 22075 | AG16: 24855 | AH16: 25119 | AI16: 26844
A17: % Growth | AD17: =IFERROR(AD16/AC16-1,"") -> 0.088585726 | AE17: =IFERROR(AE16/AD16-1,"") -> 0.1336398 | AF17: =IFERROR(AF16/AE16-1,"") -> 0.065652909 | AG17: =IFERROR(AG16/AF16-1,"") -> 0.12593431 | AH17: =IFERROR(AH16/AG16-1,"") -> 0.010621605 | AI17: =IFERROR(AI16/AH16-1,"") -> 0.068673116
A18: Total COGS | B18: 3991.337 | C18: 5248.834 | D18: 6844.915 | E18: 8204 | F18: 8865 | G18: 5713 | H18: 4462 | I18: 4438 | J18: 5817 | K18: 4128 | L18: 4139 | M18: 4499 | N18: 6022 | O18: 9889 | P18: 13717 | Q18: 16426 | R18: 24294 | S18: 25683 | T18: 39541 | U18: 64431 | V18: 87846 | W18: 106606 | X18: 112258 | Y18: 140089 | Z18: 131376 | AA18: 141048 | AB18: 163756 | AC18: =AC16+AC14 -> 161782 | AD18: =AD16+AD14 -> 169559 | AE18: =AE16+AE14 -> 212981 | AF18: =AF16+AF14 -> 223546 | AG18: =AG16+AG14 -> 214137 | AH18: =AH16+AH14 -> 210352 | AI18: =AI16+AI14 -> 220960
A19: % Growth | C19: =IFERROR(C18/B18-1,"") -> 0.31505658 | D19: =IFERROR(D18/C18-1,"") -> 0.30408296 | E19: =IFERROR(E18/D18-1,"") -> 0.19855396 | F19: =IFERROR(F18/E18-1,"") -> 0.080570453 | G19: =IFERROR(G18/F18-1,"") -> -0.35555556 | H19: =IFERROR(H18/G18-1,"") -> -0.21897427 | I19: =IFERROR(I18/H18-1,"") -> -0.0053787539 | J19: =IFERROR(J18/I18-1,"") -> 0.31072555 | ... AI19: =IFERROR(AI18/AH18-1,"") -> 0.050429756 | AL19: 33yr | AM19: Check | AO19: 20yr | AP19: Check | AR19: 10yr | AS19: Check | AU19: 5yr | AV19: Check
A20: Products Gross Profit | B20: =B7-B14 -> 0 | C20: =C7-C14 -> 0 | D20: =D7-D14 -> 0 | E20: =E7-E14 -> 0 | F20: =F7-F14 -> 0 | G20: =G7-G14 -> 0 | H20: =H7-H14 -> 0 | I20: =I7-I14 -> 0 | ... AI20: =AI7-AI14 -> 112887
A21: % Growth | AD21: =IFERROR(AD20/AC20-1,"") -> 0.0083324865 | AE21: =IFERROR(AE20/AD20-1,"") -> 0.51345359 | AF21: =IFERROR(AF20/AE20-1,"") -> 0.091338013 | AG21: =IFERROR(AG20/AF20-1,"") -> -0.051643888 | AH21: =IFERROR(AH20/AG20-1,"") -> 0.0076284661 | AI21: =IFERROR(AI20/AH20-1,"") -> 0.029680844
A22: Services Gross Profit | B22: =B9-B16 -> 0 | C22: =C9-C16 -> 0 | D22: =D9-D16 -> 0 | E22: =E9-E16 -> 0 | F22: =F9-F16 -> 0 | G22: =G9-G16 -> 0 | H22: =H9-H16 -> 0 | I22: =I9-I16 -> 0 | ... AI22: =AI9-AI16 -> 82314
A23: % Growth | AD23: =IFERROR(AD22/AC22-1,"") -> 0.20301644 | AE23: =IFERROR(AE22/AD22-1,"") -> 0.34413298 | AF23: =IFERROR(AF22/AE22-1,"") -> 0.17488996 | AG23: =IFERROR(AG22/AF22-1,"") -> 0.076551183 | AH23: =IFERROR(AH22/AG22-1,"") -> 0.17739664 | AI23: =IFERROR(AI22/AH22-1,"") -> 0.15853624 | AL23: 33yr | AM23: Check | AO23: 20yr | AP23: Check | AR23: 10yr | AS23: Check | AU23: 5yr | AV23: Check
A24: Gross Profit | B24: =B11-B18 -> 3095.205 | C24: =C11-C18 -> 2728.12 | D24: =D11-D18 -> 2343.833 | E24: =E11-E18 -> 2858 | F24: =F11-F18 -> 968 | G24: =G11-G18 -> 1368 | H24: =H11-H18 -> 1479 | I24: =I11-I18 -> 1696 | ... AI24: =AI11-AI18 -> 195201 | AL24: =IFERROR((AI24/B24)^(1/33)-1,"") -> 0.13380709 | AM24: =IFERROR(PRODUCT(1+C25,1+D25,1+E25,1+F25,1+G25,1+H25,1+I25,1+J25,1+K25,1+L25,1+M25,1+N25,1+O25,1+P25,1+Q25,1+R25,1+S25,1+T25,1+U25,1+V25,1+W25,1+X25,1+Y25,1+Z25,1+AA25,1+AB25,1+AC25,1+AD25,1+AE25,1+AF25,1+AG25,1+AH25,1+AI25)^(1/33)-1,"") -> 0.13380709 | AO24: =IFERROR((AI24/O24)^(1/20)-1, "") -> 0.21393179 | AP24: =IFERROR(PRODUCT(1+P25,1+Q25,1+R25,1+S25,1+T25,1+U25,1+V25,1+W25,1+X25,1+Y25,1+Z25,1+AA25,1+AB25,1+AC25,1+AD25,1+AE25,1+AF25,1+AG25,1+AH25,1+AI25)^(1/20)-1,"") -> 0.21393179 | AR24: =IFERROR((AI24/Y24)^(1/10)-1,"") -> 0.076238582 | AS24: =IFERROR(PRODUCT(1+Z25,1+AA25,1+AB25,1+AC25,1+AD25,1+AE25,1+AF25,1+AG25,1+AH25,1+AI25)^(1/10)-1,"") -> 0.076238582 | AU24: =IFERROR((AI24/AD24)^(1/5)-1,"") -> 0.13212649 | AV24: =IFERROR(PRODUCT(1+AE25,1+AF25,1+AG25,1+AH25,1+AI25)^(1/5)-1,"") -> 0.13212649
A25: % Growth | C25: =IFERROR(C24/B24-1,"") -> -0.11859796 | D25: =IFERROR(D24/C24-1,"") -> -0.14086147 | E25: =IFERROR(E24/D24-1,"") -> 0.21937015 | F25: =IFERROR(F24/E24-1,"") -> -0.66130161 | G25: =IFERROR(G24/F24-1,"") -> 0.41322314 | H25: =IFERROR(H24/G24-1,"") -> 0.081140351 | I25: =IFERROR(I24/H24-1,"") -> 0.14672076 | J25: =IFERROR(J24/I24-1,"") -> 0.27712264 | ... AI25: =IFERROR(AI24/AH24-1,"") -> 0.080350669
AL26: 33yr | AM26: Check | AO26: 20yr | AP26: Check | AR26: 10yr | AS26: Check | AU26: 5yr | AV26: Check
A27: Research & Development | B27: 602.135 | C27: 664.564 | D27: 564.303 | E27: 614 | F27: 604 | G27: 485 | H27: 303 | I27: 314 | J27: 380 | K27: 430 | L27: 446 | M27: 471 | N27: 491 | O27: 535 | P27: 712 | Q27: 782 | R27: 1109 | S27: 1333 | T27: 1782 | U27: 2429 | V27: 3381 | W27: 4475 | X27: 6041 | Y27: 8067 | Z27: 10045 | AA27: 11581 | AB27: 14236 | AC27: 16217 | AD27: 18752 | AE27: 21914 | AF27: 26251 | AG27: 29915 | AH27: 31370 | AI27: 34550 | AL27: =IFERROR((AI27/B27)^(1/33)-1,"") -> 0.13056512 | AM27: =IFERROR(PRODUCT(1+C28,1+D28,1+E28,1+F28,1+G28,1+H28,1+I28,1+J28,1+K28,1+L28,1+M28,1+N28,1+O28,1+P28,1+Q28,1+R28,1+S28,1+T28,1+U28,1+V28,1+W28,1+X28,1+Y28,1+Z28,1+AA28,1+AB28,1+AC28,1+AD28,1+AE28,1+AF28,1+AG28,1+AH28,1+AI28)^(1/33)-1,"") -> 0.13056512 | AO27: =IFERROR((AI27/O27)^(1/20)-1, "") -> 0.23169935 | AP27: =IFERROR(PRODUCT(1+P28,1+Q28,1+R28,1+S28,1+T28,1+U28,1+V28,1+W28,1+X28,1+Y28,1+Z28,1+AA28,1+AB28,1+AC28,1+AD28,1+AE28,1+AF28,1+AG28,1+AH28,1+AI28)^(1/20)-1,"") -> 0.23169935 | AR27: =IFERROR((AI27/Y27)^(1/10)-1,"") -> 0.15657446 | AS27: =IFERROR(PRODUCT(1+Z28,1+AA28,1+AB28,1+AC28,1+AD28,1+AE28,1+AF28,1+AG28,1+AH28,1+AI28)^(1/10)-1,"") -> 0.15657446 | AU27: =IFERROR((AI27/AD27)^(1/5)-1,"") -> 0.13000429 | AV27: =IFERROR(PRODUCT(1+AE28,1+AF28,1+AG28,1+AH28,1+AI28)^(1/5)-1,"") -> 0.13000429
A28: % Growth | C28: =IFERROR(C27/B27-1,"") -> 0.10367941 | D28: =IFERROR(D27/C27-1,"") -> -0.15086734 | E28: =IFERROR(E27/D27-1,"") -> 0.088067935 | F28: =IFERROR(F27/E27-1,"") -> -0.016286645 | G28: =IFERROR(G27/F27-1,"") -> -0.19701987 | H28: =IFERROR(H27/G27-1,"") -> -0.37525773 | I28: =IFERROR(I27/H27-1,"") -> 0.03630363 | J28: =IFERROR(J27/I27-1,"") -> 0.21019108 | ... AI28: =IFERROR(AI27/AH27-1,"") -> 0.10137074
A29: Selling, General & Administrative | B29: 1687.262 | C29: 1632.362 | D29: 1384.111 | E29: 1583 | F29: 1568 | G29: 1286 | H29: 908 | I29: 996 | J29: 1166 | K29: 1138 | L29: 1111 | M29: 1212 | N29: 1430 | O29: 1864 | P29: 2433 | Q29: 2963 | R29: 3761 | S29: 4149 | T29: 5517 | U29: 7599 | V29: 10040 | W29: 10830 | X29: 11993 | Y29: 14329 | Z29: 14194 | AA29: 15261 | AB29: 16705 | AC29: 18245 | AD29: 19916 | AE29: 21973 | AF29: 25094 | AG29: 24932 | AH29: 26097 | AI29: 27601 | AL29: =IFERROR((AI29/B29)^(1/33)-1,"") -> 0.088378789 | AM29: =IFERROR(PRODUCT(1+C30,1+D30,1+E30,1+F30,1+G30,1+H30,1+I30,1+J30,1+K30,1+L30,1+M30,1+N30,1+O30,1+P30,1+Q30,1+R30,1+S30,1+T30,1+U30,1+V30,1+W30,1+X30,1+Y30,1+Z30,1+AA30,1+AB30,1+AC30,1+AD30,1+AE30,1+AF30,1+AG30,1+AH30,1+AI30)^(1/33)-1,"") -> 0.088378789 | AO29: =IFERROR((AI29/O29)^(1/20)-1, "") -> 0.14425797 | AP29: =IFERROR(PRODUCT(1+P30,1+Q30,1+R30,1+S30,1+T30,1+U30,1+V30,1+W30,1+X30,1+Y30,1+Z30,1+AA30,1+AB30,1+AC30,1+AD30,1+AE30,1+AF30,1+AG30,1+AH30,1+AI30)^(1/20)-1,"") -> 0.14425797 | AR29: =IFERROR((AI29/Y29)^(1/10)-1,"") -> 0.067753229 | AS29: =IFERROR(PRODUCT(1+Z30,1+AA30,1+AB30,1+AC30,1+AD30,1+AE30,1+AF30,1+AG30,1+AH30,1+AI30)^(1/10)-1,"") -> 0.067753229 | AU29: =IFERROR((AI29/AD29)^(1/5)-1,"") -> 0.067442622 | AV29: =IFERROR(PRODUCT(1+AE30,1+AF30,1+AG30,1+AH30,1+AI30)^(1/5)-1,"") -> 0.067442622
A30: % Growth | C30: =IFERROR(C29/B29-1,"") -> -0.032537922 | D30: =IFERROR(D29/C29-1,"") -> -0.15208085 | E30: =IFERROR(E29/D29-1,"") -> 0.1436944 | F30: =IFERROR(F29/E29-1,"") -> -0.0094756791 | G30: =IFERROR(G29/F29-1,"") -> -0.17984694 | H30: =IFERROR(H29/G29-1,"") -> -0.29393468 | I30: =IFERROR(I29/H29-1,"") -> 0.0969163 | J30: =IFERROR(J29/I29-1,"") -> 0.17068273 | ... AI30: =IFERROR(AI29/AH29-1,"") -> 0.057631145
A31: Restructuring Costs | B31: 0 | C31: 320.856 | D31: -126.855 | E31: -23 | F31: 179 | G31: 217 | H31: 0 | I31: 27 | J31: 8 | K31: 0 | L31: 30 | M31: 26 | N31: 23 | O31: 0 | P31: 0 | Q31: 0 | R31: 0 | S31: 0 | T31: 0 | U31: 0 | V31: 0 | W31: 0 | X31: 0 | Y31: 0 | Z31: 0 | AA31: 0 | AB31: 0 | AC31: 0 | AD31: 0 | AE31: 0 | AF31: 0 | AG31: 0 | AH31: 0 | AI31: 0
A32: % Growth | C32: =IFERROR(C31/B31-1,"") | D32: =IFERROR(D31/C31-1,"") -> -1.3953643 | E32: =IFERROR(E31/D31-1,"") -> -0.81869063 | F32: =IFERROR(F31/E31-1,"") -> -8.7826087 | G32: =IFERROR(G31/F31-1,"") -> 0.2122905 | H32: =IFERROR(H31/G31-1,"") -> -1 | I32: =IFERROR(I31/H31-1,"") | J32: =IFERROR(J31/I31-1,"") -> -0.7037037 | ... AI32: =IFERROR(AI31/AH31-1,"")
A33: In-Process R&D | B33: 0 | C33: 0 | D33: 0 | E33: 0 | F33: 0 | G33: 375 | H33: 7 | I33: 0 | J33: 0 | K33: 11 | L33: 1 | M33: 0 | N33: 0 | O33: 0 | P33: 0 | Q33: 0 | R33: 0 | S33: 0 | T33: 0 | U33: 0 | V33: 0 | W33: 0 | X33: 0 | Y33: 0 | Z33: 0 | AA33: 0 | AB33: 0 | AC33: 0 | AD33: 0 | AE33: 0 | AF33: 0 | AG33: 0 | AH33: 0 | AI33: 0
A34: % Growth | C34: =IFERROR(C33/B33-1,"") | D34: =IFERROR(D33/C33-1,"") | E34: =IFERROR(E33/D33-1,"") | F34: =IFERROR(F33/E33-1,"") | G34: =IFERROR(G33/F33-1,"") | H34: =IFERROR(H33/G33-1,"") -> -0.98133333 | I34: =IFERROR(I33/H33-1,"") -> -1 | J34: =IFERROR(J33/I33-1,"") | ... AI34: =IFERROR(AI33/AH33-1,"")
A35: Termination of License Agreement | B35: 0 | C35: 0 | D35: 0 | E35: 0 | F35: 0 | G35: 75 | H35: 0 | I35: 0 | J35: 0 | K35: 0 | L35: 0 | M35: 0 | N35: 0 | O35: 0 | P35: 0 | Q35: 0 | R35: 0 | S35: 0 | T35: 0 | U35: 0 | V35: 0 | W35: 0 | X35: 0 | Y35: 0 | Z35: 0 | AA35: 0 | AB35: 0 | AC35: 0 | AD35: 0 | AE35: 0 | AF35: 0 | AG35: 0 | AH35: 0 | AI35: 0
A36: % Growth | C36: =IFERROR(C35/B35-1,"") | D36: =IFERROR(D35/C35-1,"") | E36: =IFERROR(E35/D35-1,"") | F36: =IFERROR(F35/E35-1,"") | G36: =IFERROR(G35/F35-1,"") | H36: =IFERROR(H35/G35-1,"") -> -1 | I36: =IFERROR(I35/H35-1,"") | J36: =IFERROR(J35/I35-1,"") | ... AI36: =IFERROR(AI35/AH35-1,"")
A37: Executive Bonus / Special Compensation | B37: 0 | C37: 0 | D37: 0 | E37: 0 | F37: 0 | G37: 0 | H37: 0 | I37: 0 | J37: 90 | K37: 0 | L37: -2 | M37: 0 | N37: 0 | O37: 0 | P37: 0 | Q37: 0 | R37: 0 | S37: 0 | T37: 0 | U37: 0 | V37: 0 | W37: 0 | X37: 0 | Y37: 0 | Z37: 0 | AA37: 0 | AB37: 0 | AC37: 0 | AD37: 0 | AE37: 0 | AF37: 0 | AG37: 0 | AH37: 0 | AI37: 0
A38: % Growth | B38: =IFERROR(B37/A37-1,"") | C38: =IFERROR(C37/B37-1,"") | D38: =IFERROR(D37/C37-1,"") | E38: =IFERROR(E37/D37-1,"") | F38: =IFERROR(F37/E37-1,"") | G38: =IFERROR(G37/F37-1,"") | H38: =IFERROR(H37/G37-1,"") | I38: =IFERROR(I37/H37-1,"") | ... AI38: =IFERROR(AI37/AH37-1,"")
A39: Total Operating Expenses | B39: =B27+B29+B31+B33+B35+B37 -> 2289.397 | C39: =C27+C29+C31+C33+C35+C37 -> 2617.782 | D39: =D27+D29+D31+D33+D35+D37 -> 1821.559 | E39: =E27+E29+E31+E33+E35+E37 -> 2174 | F39: =F27+F29+F31+F33+F35+F37 -> 2351 | G39: =G27+G29+G31+G33+G35+G37 -> 2438 | H39: =H27+H29+H31+H33+H35+H37 -> 1218 | I39: =I27+I29+I31+I33+I35+I37 -> 1337 | ... AI39: =AI27+AI29+AI31+AI33+AI35+AI37 -> 62151
A40: % Growth | C40: =IFERROR(C39/B39-1,"") -> 0.14343733 | D40: =IFERROR(D39/C39-1,"") -> -0.3041594 | E40: =IFERROR(E39/D39-1,"") -> 0.19348316 | F40: =IFERROR(F39/E39-1,"") -> 0.081416743 | G40: =IFERROR(G39/F39-1,"") -> 0.03700553 | H40: =IFERROR(H39/G39-1,"") -> -0.50041017 | I40: =IFERROR(I39/H39-1,"") -> 0.097701149 | J40: =IFERROR(J39/I39-1,"") -> 0.22961855 | ... AI40: =IFERROR(AI39/AH39-1,"") -> 0.081507648 | AL40: 33yr | AM40: Check | AO40: 20yr | AP40: Check | AR40: 10yr | AS40: Check | AU40: 5yr | AV40: Check
A41: Operating Income (EBIT) | B41: =B24-B39 -> 805.808 | C41: =C24-C39 -> 110.338 | D41: =D24-D39 -> 522.274 | E41: =E24-E39 -> 684 | F41: =F24-F39 -> -1383 | G41: =G24-G39 -> -1070 | H41: =H24-H39 -> 261 | I41: =I24-I39 -> 359 | ... AI41: =AI24-AI39 -> 133050 | AL41: =IFERROR((AI41/B41)^(1/33)-1,"") -> 0.16736201 | AM41: =IFERROR(PRODUCT(1+C42,1+D42,1+E42,1+F42,1+G42,1+H42,1+I42,1+J42,1+K42,1+L42,1+M42,1+N42,1+O42,1+P42,1+Q42,1+R42,1+S42,1+T42,1+U42,1+V42,1+W42,1+X42,1+Y42,1+Z42,1+AA42,1+AB42,1+AC42,1+AD42,1+AE42,1+AF42,1+AG42,1+AH42,1+AI42)^(1/33)-1,"") -> 0.16736201 | AO41: =IFERROR((AI41/O41)^(1/20)-1, "") -> 0.24571549 | AP41: =IFERROR(PRODUCT(1+P42,1+Q42,1+R42,1+S42,1+T42,1+U42,1+V42,1+W42,1+X42,1+Y42,1+Z42,1+AA42,1+AB42,1+AC42,1+AD42,1+AE42,1+AF42,1+AG42,1+AH42,1+AI42)^(1/20)-1,"") -> 0.24571549 | AR41: =IFERROR((AI41/Y41)^(1/10)-1,"") -> 0.064474332 | AS41: =IFERROR(PRODUCT(1+Z42,1+AA42,1+AB42,1+AC42,1+AD42,1+AE42,1+AF42,1+AG42,1+AH42,1+AI42)^(1/10)-1,"") -> 0.064474332 | AU41: =IFERROR((AI41/AD41)^(1/5)-1,"") -> 0.14951857 | AV41: =IFERROR(PRODUCT(1+AE42,1+AF42,1+AG42,1+AH42,1+AI42)^(1/5)-1,"") -> 0.14951857
A42: % Growth | C42: =IFERROR(C41/B41-1,"") -> -0.8630716 | D42: =IFERROR(D41/C41-1,"") -> 3.733401 | E42: =IFERROR(E41/D41-1,"") -> 0.30965738 | F42: =IFERROR(F41/E41-1,"") -> -3.0219298 | G42: =IFERROR(G41/F41-1,"") -> -0.2263196 | H42: =IFERROR(H41/G41-1,"") -> -1.2439252 | I42: =IFERROR(I41/H41-1,"") -> 0.37547893 | J42: =IFERROR(J41/I41-1,"") -> 0.454039 | ... AI42: =IFERROR(AI41/AH41-1,"") -> 0.079811063
A44: Gains on Sales of Investments | B44: 0 | C44: 0 | D44: 0 | E44: 0 | F44: 0 | G44: 0 | H44: 40 | I44: 230 | J44: 0 | K44: 0 | L44: 0 | M44: 0 | N44: 0 | O44: 0 | P44: 0 | Q44: 0 | R44: 0 | S44: 0 | T44: 0 | U44: 0 | V44: 0 | W44: 0 | X44: 0 | Y44: 0 | Z44: 0 | AA44: 0 | AB44: 0 | AC44: 0 | AD44: 0 | AE44: 0 | AF44: 0 | AG44: 0 | AH44: 0 | AI44: 0
A45: % of Revenue | C45: =IFERROR(C44/C$11,"") -> 0 | D45: =IFERROR(D44/D$11,"") -> 0 | E45: =IFERROR(E44/E$11,"") -> 0 | F45: =IFERROR(F44/F$11,"") -> 0 | G45: =IFERROR(G44/G$11,"") -> 0 | H45: =IFERROR(H44/H$11,"") -> 0.0067328733 | I45: =IFERROR(I44/I$11,"") -> 0.037495924 | J45: =IFERROR(J44/J$11,"") -> 0 | ... AI45: =IFERROR(AI44/AI$11,"") -> 0
A46: Gains/(Losses) on Non-Current Investments, Net | B46: 0 | C46: 0 | D46: 0 | E46: 0 | F46: 0 | G46: 0 | H46: 0 | I46: 0 | J46: 367 | K46: 88 | L46: -42 | M46: 10 | N46: 0 | O46: 0 | P46: 0 | Q46: 0 | R46: 0 | S46: 0 | T46: 0 | U46: 0 | V46: 0 | W46: 0 | X46: 0 | Y46: 0 | Z46: 0 | AA46: 0 | AB46: 0 | AC46: 0 | AD46: 0 | AE46: 0 | AF46: 0 | AG46: 0 | AH46: 0 | AI46: 0
A47: % of Revenue | C47: =IFERROR(C46/C$11,"") -> 0 | D47: =IFERROR(D46/D$11,"") -> 0 | E47: =IFERROR(E46/E$11,"") -> 0 | F47: =IFERROR(F46/F$11,"") -> 0 | G47: =IFERROR(G46/G$11,"") -> 0 | H47: =IFERROR(H46/H$11,"") -> 0 | I47: =IFERROR(I46/I$11,"") -> 0 | J47: =IFERROR(J46/J$11,"") -> 0.045972692 | ... AI47: =IFERROR(AI46/AI$11,"") -> 0
A48: Unrealized Loss on Convertible Securities | B48: 0 | C48: 0 | D48: 0 | E48: 0 | F48: 0 | G48: 0 | H48: 0 | I48: 0 | J48: 0 | K48: -13 | L48: 0 | M48: 0 | N48: 0 | O48: 0 | P48: 0 | Q48: 0 | R48: 0 | S48: 0 | T48: 0 | U48: 0 | V48: 0 | W48: 0 | X48: 0 | Y48: 0 | Z48: 0 | AA48: 0 | AB48: 0 | AC48: 0 | AD48: 0 | AE48: 0 | AF48: 0 | AG48: 0 | AH48: 0 | AI48: 0
A49: % of Revenue | C49: =IFERROR(C48/C$11,"") -> 0 | D49: =IFERROR(D48/D$11,"") -> 0 | E49: =IFERROR(E48/E$11,"") -> 0 | F49: =IFERROR(F48/F$11,"") -> 0 | G49: =IFERROR(G48/G$11,"") -> 0 | H49: =IFERROR(H48/H$11,"") -> 0 | I49: =IFERROR(I48/I$11,"") -> 0 | J49: =IFERROR(J48/J$11,"") -> 0 | ... AI49: =IFERROR(AI48/AI$11,"") -> 0
A50: Interest and Other Income, Net | B50: 49.634 | C50: 29.321 | D50: -21.988 | E50: -10 | F50: 88 | G50: 25 | H50: 28 | I50: 87 | J50: 203 | K50: 217 | L50: 112 | M50: 83 | N50: 0 | O50: 0 | P50: 0 | Q50: 0 | R50: 0 | S50: 0 | T50: 0 | U50: 0 | V50: 0 | W50: 0 | X50: 0 | Y50: 0 | Z50: 0 | AA50: 0 | AB50: 0 | AC50: 0 | AD50: 0 | AE50: 0 | AF50: 0 | AG50: 0 | AH50: 0 | AI50: 0
A51: % of Revenue | B51: =IFERROR(B50/B$11,"") -> 0.0070039802 | C51: =IFERROR(C50/C$11,"") -> 0.0036757138 | D51: =IFERROR(D50/D$11,"") -> -0.0023929267 | E51: =IFERROR(E50/E$11,"") -> -0.00090399566 | F51: =IFERROR(F50/F$11,"") -> 0.0089494559 | G51: =IFERROR(G50/G$11,"") -> 0.0035305748 | H51: =IFERROR(H50/H$11,"") -> 0.0047130113 | I51: =IFERROR(I50/I$11,"") -> 0.014183241 | ... AI51: =IFERROR(AI50/AI$11,"") -> 0
A52: Other Income/(Expense), Net | B52: 0 | C52: 0 | D52: 0 | E52: 0 | F52: 0 | G52: 0 | H52: 0 | I52: 0 | J52: 0 | K52: 0 | L52: 0 | M52: 0 | N52: 57 | O52: 165 | P52: 365 | Q52: 599 | R52: 620 | S52: 326 | T52: 155 | U52: 415 | V52: 522 | W52: 1156 | X52: 980 | Y52: 1285 | Z52: 1348 | AA52: 2745 | AB52: 2005 | AC52: 1807 | AD52: 803 | AE52: 258 | AF52: -334 | AG52: -565 | AH52: 269 | AI52: -321
A53: % of Revenue | C53: =IFERROR(C52/C$11,"") -> 0 | D53: =IFERROR(D52/D$11,"") -> 0 | E53: =IFERROR(E52/E$11,"") -> 0 | F53: =IFERROR(F52/F$11,"") -> 0 | G53: =IFERROR(G52/G$11,"") -> 0 | H53: =IFERROR(H52/H$11,"") -> 0 | I53: =IFERROR(I52/I$11,"") -> 0 | J53: =IFERROR(J52/J$11,"") -> 0 | ... AI53: =IFERROR(AI52/AI$11,"") -> -0.00077133609
A54: Total Other Income/(Expense) | B54: =B44+B46+B48+B50+B52 -> 49.634 | C54: =C44+C46+C48+C50+C52 -> 29.321 | D54: =D44+D46+D48+D50+D52 -> -21.988 | E54: =E44+E46+E48+E50+E52 -> -10 | F54: =F44+F46+F48+F50+F52 -> 88 | G54: =G44+G46+G48+G50+G52 -> 25 | H54: =H44+H46+H48+H50+H52 -> 68 | I54: =I44+I46+I48+I50+I52 -> 317 | ... AI54: =AI44+AI46+AI48+AI50+AI52 -> -321
A57: Income Before Income Taxes | B57: =B41+B54 -> 855.442 | C57: =C41+C54 -> 139.659 | D57: =D41+D54 -> 500.286 | E57: =E41+E54 -> 674 | F57: =F41+F54 -> -1295 | G57: =G41+G54 -> -1045 | H57: =H41+H54 -> 329 | I57: =I41+I54 -> 676 | ... AI57: =AI41+AI54 -> 132729
A58: % of Revenue | B58: =IFERROR(B57/B$11,"") -> 0.1207136 | C58: =IFERROR(C57/C$11,"") -> 0.017507811 | D58: =IFERROR(D57/D$11,"") -> 0.054445502 | E58: =IFERROR(E57/E$11,"") -> 0.060929308 | F58: =IFERROR(F57/F$11,"") -> -0.13169938 | G58: =IFERROR(G57/G$11,"") -> -0.14757803 | H58: =IFERROR(H57/H$11,"") -> 0.055377883 | I58: =IFERROR(I57/I$11,"") -> 0.11020541 | ... AI58: =IFERROR(AI57/AI$11,"") -> 0.31893666
A59: Provision for Income Taxes | B59: 325.069 | C59: 53.07 | D59: 190.108 | E59: 250 | F59: -479 | G59: 0 | H59: 20 | I59: 75 | J59: 306 | K59: -15 | L59: 22 | M59: 24 | N59: 104 | O59: 480 | P59: 829 | Q59: 1511 | R59: 2828 | S59: 3831 | T59: 4527 | U59: 8283 | V59: 14030 | W59: 13118 | X59: 13973 | Y59: 19121 | Z59: 15685 | AA59: 15738 | AB59: 13372 | AC59: 10481 | AD59: 9680 | AE59: 14527 | AF59: 19300 | AG59: 16741 | AH59: 29749 | AI59: 20719
A60: % of Revenue | B60: =IFERROR(B59/B$11,"") -> 0.045871315 | C60: =IFERROR(C59/C$11,"") -> 0.0066529154 | D60: =IFERROR(D59/D$11,"") -> 0.020689217 | E60: =IFERROR(E59/E$11,"") -> 0.022599892 | F60: =IFERROR(F59/F$11,"") -> -0.048713516 | G60: =IFERROR(G59/G$11,"") -> 0 | H60: =IFERROR(H59/H$11,"") -> 0.0033664366 | I60: =IFERROR(I59/I$11,"") -> 0.012226932 | ... AI60: =IFERROR(AI59/AI$11,"") -> 0.04978602
A61: Income Before Accounting Changes | B61: 0 | C61: 0 | D61: 0 | E61: 0 | F61: 0 | G61: 0 | H61: 0 | I61: 0 | J61: 786 | K61: -37 | L61: 65 | M61: 68 | N61: 266 | O61: 1328 | P61: 0 | Q61: 0 | R61: 0 | S61: 0 | T61: 0 | U61: 0 | V61: 0 | W61: 0 | X61: 0 | Y61: 0 | Z61: 0 | AA61: 0 | AB61: 0 | AC61: 0 | AD61: 0 | AE61: 0 | AF61: 0 | AG61: 0 | AH61: 0 | AI61: 0
A62: % of Revenue | B62: =IFERROR(B61/B$11,"") -> 0 | C62: =IFERROR(C61/C$11,"") -> 0 | D62: =IFERROR(D61/D$11,"") -> 0 | E62: =IFERROR(E61/E$11,"") -> 0 | F62: =IFERROR(F61/F$11,"") -> 0 | G62: =IFERROR(G61/G$11,"") -> 0 | H62: =IFERROR(H61/H$11,"") -> 0 | I62: =IFERROR(I61/I$11,"") -> 0 | ... AI62: =IFERROR(AI61/AI$11,"") -> 0
A63: Cumulative Effect of Accounting Changes | B63: 0 | C63: 0 | D63: 0 | E63: 0 | F63: 0 | G63: 0 | H63: 0 | I63: 0 | J63: 0 | K63: 12 | L63: 0 | M63: 1 | N63: 0 | O63: 0 | P63: 0 | Q63: 0 | R63: 0 | S63: 0 | T63: 0 | U63: 0 | V63: 0 | W63: 0 | X63: 0 | Y63: 0 | Z63: 0 | AA63: 0 | AB63: 0 | AC63: 0 | AD63: 0 | AE63: 0 | AF63: 0 | AG63: 0 | AH63: 0 | AI63: 0
A64: % of Revenue | B64: =IFERROR(B63/B$11,"") -> 0 | C64: =IFERROR(C63/C$11,"") -> 0 | D64: =IFERROR(D63/D$11,"") -> 0 | E64: =IFERROR(E63/E$11,"") -> 0 | F64: =IFERROR(F63/F$11,"") -> 0 | G64: =IFERROR(G63/G$11,"") -> 0 | H64: =IFERROR(H63/H$11,"") -> 0 | I64: =IFERROR(I63/I$11,"") -> 0 | ... AI64: =IFERROR(AI63/AI$11,"") -> 0 | AL64: 33yr | AM64: Check | AO64: 20yr | AP64: Check | AR64: 10yr | AS64: Check | AU64: 5yr | AV64: Check
A65: Net Income | B65: =B57-B59+B63+B61 -> 530.373 | C65: =C57-C59+C63+C61 -> 86.589 | D65: =D57-D59+D63+D61 -> 310.178 | E65: =E57-E59+E63+E61 -> 424 | F65: =F57-F59+F63+F61 -> -816 | G65: =G57-G59+G63+G61 -> -1045 | H65: =H57-H59+H63+H61 -> 309 | I65: =I57-I59+I63+I61 -> 601 | ... AI65: =AI57-AI59+AI63+AI61 -> 112010 | AL65: =IFERROR((AI65/B65)^(1/33)-1,"") -> 0.17610124 | AM65: =IFERROR(PRODUCT(1+C66,1+D66,1+E66,1+F66,1+G66,1+H66,1+I66,1+J66,1+K66,1+L66,1+M66,1+N66,1+O66,1+P66,1+Q66,1+R66,1+S66,1+T66,1+U66,1+V66,1+W66,1+X66,1+Y66,1+Z66,1+AA66,1+AB66,1+AC66,1+AD66,1+AE66,1+AF66,1+AG66,1+AH66,1+AI66)^(1/33)-1,"") -> 0.17610124 | AO65: =IFERROR((AI65/O65)^(1/20)-1, "") -> 0.2057338 | AP65: =IFERROR(PRODUCT(1+P66,1+Q66,1+R66,1+S66,1+T66,1+U66,1+V66,1+W66,1+X66,1+Y66,1+Z66,1+AA66,1+AB66,1+AC66,1+AD66,1+AE66,1+AF66,1+AG66,1+AH66,1+AI66)^(1/20)-1,"") -> 0.2057338 | AR65: =IFERROR((AI65/Y65)^(1/10)-1,"") -> 0.076902621 | AS65: =IFERROR(PRODUCT(1+Z66,1+AA66,1+AB66,1+AC66,1+AD66,1+AE66,1+AF66,1+AG66,1+AH66,1+AI66)^(1/10)-1,"") -> 0.076902621 | AU65: =IFERROR((AI65/AD65)^(1/5)-1,"") -> 0.14301607 | AV65: =IFERROR(PRODUCT(1+AE66,1+AF66,1+AG66,1+AH66,1+AI66)^(1/5)-1,"") -> 0.14301607
C66: =IFERROR(C65/B65-1,"") -> -0.83673943 | D66: =IFERROR(D65/C65-1,"") -> 2.5821871 | E66: =IFERROR(E65/D65-1,"") -> 0.36695704 | F66: =IFERROR(F65/E65-1,"") -> -2.9245283 | G66: =IFERROR(G65/F65-1,"") -> 0.28063725 | H66: =IFERROR(H65/G65-1,"") -> -1.2956938 | I66: =IFERROR(I65/H65-1,"") -> 0.94498382 | J66: =IFERROR(J65/I65-1,"") -> 1.6156406 | ... AI66: =IFERROR(AI65/AH65-1,"") -> 0.19495178
A68: EPS - Basic ($/share) | B68: 4.33 | C68: 0.73 | D68: 2.61 | E68: 3.45 | F68: -6.59 | G68: -8.29 | H68: 2.34 | I68: 4.2 | J68: 2.42 | K68: -0.07 | L68: 0.18 | M68: 0.1 | N68: 0.36 | O68: 1.64 | P68: 2.36 | Q68: 4.04 | R68: 6.94 | S68: 9.22 | T68: 15.41 | U68: 28.05 | V68: 44.64 | W68: 40.03 | X68: 6.49 | Y68: 9.28 | Z68: 8.35 | AA68: 9.27 | AB68: 12.01 | AC68: 11.97 | AD68: 3.31 | AE68: 5.67 | AF68: 6.15 | AG68: 6.16 | AH68: 6.11 | AI68: 7.49
A69: EPS - Diluted ($/share) | B69: 0 | C69: 0 | D69: 0 | E69: 0 | F69: 0 | G69: 0 | H69: 2.1 | I69: 3.61 | J69: 2.18 | K69: -0.07 | L69: 0.18 | M69: 0.09 | N69: 0.34 | O69: 1.55 | P69: 2.27 | Q69: 3.93 | R69: 6.78 | S69: 9.08 | T69: 15.15 | U69: 27.68 | V69: 44.15 | W69: 39.75 | X69: 6.45 | Y69: 9.22 | Z69: 8.31 | AA69: 9.21 | AB69: 11.91 | AC69: 11.89 | AD69: 3.28 | AE69: 5.61 | AF69: 6.11 | AG69: 6.13 | AH69: 6.08 | AI69: 7.46
A70: EPS - Basic ($/share) % Growth | C70: =IFERROR(C68/B68-1,"") -> -0.83140878 | D70: =IFERROR(D68/C68-1,"") -> 2.5753425 | E70: =IFERROR(E68/D68-1,"") -> 0.32183908 | F70: =IFERROR(F68/E68-1,"") -> -2.9101449 | G70: =IFERROR(G68/F68-1,"") -> 0.25796662 | H70: =IFERROR(H68/G68-1,"") -> -1.2822678 | I70: =IFERROR(I68/H68-1,"") -> 0.79487179 | J70: =IFERROR(J68/I68-1,"") -> -0.42380952 | ... AI70: =IFERROR(AI68/AH68-1,"") -> 0.22585925
A71: EPS - Diluted ($/share) % Growth | C71: =IFERROR(C69/B69-1,"") | D71: =IFERROR(D69/C69-1,"") | E71: =IFERROR(E69/D69-1,"") | F71: =IFERROR(F69/E69-1,"") | G71: =IFERROR(G69/F69-1,"") | H71: =IFERROR(H69/G69-1,"") | I71: =IFERROR(I69/H69-1,"") -> 0.71904762 | J71: =IFERROR(J69/I69-1,"") -> -0.39612188 | ... AI71: =IFERROR(AI69/AH69-1,"") -> 0.22697368
A74: Shares Used - Basic (000s) | B74: 122490 | C74: 119125 | D74: 118735 | E74: 123047 | F74: 123734 | G74: 126062 | H74: 131974 | I74: 143157 | J74: 324568 | K74: 345613 | L74: 355022 | M74: 721262 | N74: 743180 | O74: 808439 | P74: 844058 | Q74: 864595 | R74: 881592 | S74: 893016 | T74: 909461 | U74: 924258 | V74: 934818 | W74: 925331 | X74: 6085572 | Y74: 5753421 | Z74: 5470820 | AA74: 5217242 | AB74: 4955377 | AC74: 4617834 | AD74: 17352119 | AE74: 16701272 | AF74: 16215963 | AG74: 15744231 | AH74: 15343783 | AI74: 14948500
A75: Shares Used - Diluted (000s) | B75: 0 | C75: 0 | D75: 0 | E75: 0 | F75: 0 | G75: 0 | H75: 167917 | I75: 174164 | J75: 360324 | K75: 345613 | L75: 361785 | M75: 726932 | N75: 774776 | O75: 856878 | P75: 877526 | Q75: 889292 | R75: 902139 | S75: 907005 | T75: 924712 | U75: 936645 | V75: 945355 | W75: 931662 | X75: 6122663 | Y75: 5793069 | Z75: 5500281 | AA75: 5251692 | AB75: 5000109 | AC75: 4648913 | AD75: 17528214 | AE75: 16864919 | AF75: 16325819 | AG75: 15812547 | AH75: 15408095 | AI75: 15004697
A76: Cash Dividends Declared per Share | B76: 0 | C76: 0 | D76: 0 | E76: 0 | F76: 0 | G76: 0 | H76: 0 | I76: 0 | J76: 0 | K76: 0 | L76: 0 | M76: 0 | N76: 0 | O76: 0 | P76: 0 | Q76: 0 | R76: 0 | S76: 0 | T76: 0 | U76: 0 | V76: 0.38 | W76: 1.64 | X76: 1.82 | Y76: 1.98 | Z76: 2.18 | AA76: 2.4 | AB76: 0 | AC76: 0 | AD76: 0 | AE76: 0 | AF76: 0 | AG76: 0 | AH76: 0 | AI76: 0
A79: BALANCE SHEET
A80: Cash & Cash Equivalents (FY1992 source reports Cash + ST Investments combined) | B80: 1435.5 | C80: 676.413 | D80: 1203.488 | E80: 756 | F80: 1552 | G80: 1230 | H80: 1481 | I80: 1326 | J80: 1191 | K80: 2310 | L80: 2252 | M80: 3396 | N80: 2969 | O80: 3491 | P80: 6392 | Q80: 9352 | R80: 11875 | S80: 5263 | T80: 11261 | U80: 9815 | V80: 10746 | W80: 14259 | X80: 13844 | Y80: 21120 | Z80: 20484 | AA80: 20289 | AB80: 25913 | AC80: 48844 | AD80: 38016 | AE80: 34940 | AF80: 23646 | AG80: 29965 | AH80: 29943 | AI80: 35934
A81: Short-Term Investments / Marketable Securities | B81: 0 | C81: 215.89 | D81: 54.368 | E81: 196 | F81: 193 | G81: 229 | H81: 819 | I81: 1900 | J81: 2836 | K81: 2026 | L81: 2085 | M81: 1170 | N81: 2495 | O81: 4770 | P81: 3718 | Q81: 6034 | R81: 10236 | S81: 18201 | T81: 14359 | U81: 16137 | V81: 18383 | W81: 26287 | X81: 11233 | Y81: 20481 | Z81: 46671 | AA81: 53892 | AB81: 40388 | AC81: 51713 | AD81: 52927 | AE81: 27699 | AF81: 24658 | AG81: 31590 | AH81: 35228 | AI81: 18763
A82: Accounts Receivable, Net | B82: 1087.185 | C82: 1381.946 | D82: 1581.347 | E82: 1931 | F82: 1496 | G82: 1035 | H82: 955 | I82: 681 | J82: 953 | K82: 466 | L82: 565 | M82: 766 | N82: 774 | O82: 895 | P82: 1252 | Q82: 1637 | R82: 2422 | S82: 3361 | T82: 5510 | U82: 5369 | V82: 10930 | W82: 13102 | X82: 17460 | Y82: 16849 | Z82: 15754 | AA82: 17874 | AB82: 23186 | AC82: 22926 | AD82: 16120 | AE82: 26278 | AF82: 28184 | AG82: 29508 | AH82: 33410 | AI82: 39777
A83: % of Revenue | B83: =IFERROR(B82/B$11,"") -> 0.15341545 | C83: =IFERROR(C82/C$11,"") -> 0.17324232 | D83: =IFERROR(D82/D$11,"") -> 0.17209602 | E83: =IFERROR(E82/E$11,"") -> 0.17456156 | F83: =IFERROR(F82/F$11,"") -> 0.15214075 | G83: =IFERROR(G82/G$11,"") -> 0.1461658 | H83: =IFERROR(H82/H$11,"") -> 0.16074735 | I83: =IFERROR(I82/I$11,"") -> 0.11102054 | ... AI83: =IFERROR(AI82/AI$11,"") -> 0.095580797
A84: Inventories | B84: 580.097 | C84: 1506.638 | D84: 1088.434 | E84: 1775 | F84: 662 | G84: 437 | H84: 78 | I84: 20 | J84: 33 | K84: 11 | L84: 45 | M84: 56 | N84: 101 | O84: 165 | P84: 270 | Q84: 346 | R84: 509 | S84: 455 | T84: 1051 | U84: 776 | V84: 791 | W84: 1764 | X84: 2111 | Y84: 2349 | Z84: 2132 | AA84: 4855 | AB84: 3956 | AC84: 4106 | AD84: 4061 | AE84: 6580 | AF84: 4946 | AG84: 6331 | AH84: 7286 | AI84: 5718
A85: Prepaid Income Taxes | B85: 199.139 | C85: 0 | D85: 0 | E85: 0 | F85: 0 | G85: 0 | H85: 0 | I85: 0 | J85: 0 | K85: 0 | L85: 0 | M85: 0 | N85: 0 | O85: 0 | P85: 0 | Q85: 0 | R85: 0 | S85: 0 | T85: 0 | U85: 0 | V85: 0 | W85: 0 | X85: 0 | Y85: 0 | Z85: 0 | AA85: 0 | AB85: 0 | AC85: 0 | AD85: 0 | AE85: 0 | AF85: 0 | AG85: 0 | AH85: 0 | AI85: 0
A86: Deferred Tax Assets | B86: 0 | C86: 268.085 | D86: 293.048 | E86: 251 | F86: 342 | G86: 259 | H86: 182 | I86: 143 | J86: 162 | K86: 169 | L86: 166 | M86: 190 | N86: 231 | O86: 331 | P86: 607 | Q86: 782 | R86: 1044 | S86: 1135 | T86: 1636 | U86: 2014 | V86: 2583 | W86: 3453 | X86: 4318 | Y86: 5546 | Z86: 0 | AA86: 0 | AB86: 0 | AC86: 0 | AD86: 0 | AE86: 0 | AF86: 0 | AG86: 0 | AH86: 0 | AI86: 0
A87: Vendor Non-Trade Receivables | B87: 0 | C87: 0 | D87: 0 | E87: 0 | F87: 0 | G87: 0 | H87: 0 | I87: 0 | J87: 0 | K87: 0 | L87: 0 | M87: 0 | N87: 0 | O87: 0 | P87: 0 | Q87: 0 | R87: 0 | S87: 0 | T87: 4414 | U87: 6348 | V87: 7762 | W87: 7539 | X87: 9759 | Y87: 13494 | Z87: 13545 | AA87: 17799 | AB87: 25809 | AC87: 22878 | AD87: 21325 | AE87: 25228 | AF87: 32748 | AG87: 31477 | AH87: 32833 | AI87: 33180
A88: Other Current Assets | B88: 256.473 | C88: 289.383 | D88: 255.767 | E88: 315 | F88: 270 | G88: 234 | H88: 183 | I88: 215 | J88: 252 | K88: 161 | L88: 275 | M88: 309 | N88: 485 | O88: 648 | P88: 2270 | Q88: 3805 | R88: 3920 | S88: 3140 | T88: 3447 | U88: 4529 | V88: 6458 | W88: 6882 | X88: 9806 | Y88: 9539 | Z88: 8283 | AA88: 13936 | AB88: 12087 | AC88: 12352 | AD88: 11264 | AE88: 14111 | AF88: 21223 | AG88: 14695 | AH88: 14287 | AI88: 14585
A89: Total Current Assets | B89: =B80+B81+B82+B84+B85+B86+B87+B88 -> 3558.394 | C89: =C80+C81+C82+C84+C85+C86+C87+C88 -> 4338.355 | D89: =D80+D81+D82+D84+D85+D86+D87+D88 -> 4476.452 | E89: =E80+E81+E82+E84+E85+E86+E87+E88 -> 5224 | F89: =F80+F81+F82+F84+F85+F86+F87+F88 -> 4515 | G89: =G80+G81+G82+G84+G85+G86+G87+G88 -> 3424 | H89: =H80+H81+H82+H84+H85+H86+H87+H88 -> 3698 | I89: =I80+I81+I82+I84+I85+I86+I87+I88 -> 4285 | ... AI89: =AI80+AI81+AI82+AI84+AI85+AI86+AI87+AI88 -> 147957
AL90: 33yr | AM90: Check | AO90: 20yr | AP90: Check | AR90: 10yr | AS90: Check | AU90: 5yr | AV90: Check
A91: Property, Plant & Equipment, Net | B91: 462.221 | C91: 659.546 | D91: 667.1 | E91: 711 | F91: 598 | G91: 486 | H91: 348 | I91: 318 | J91: 313 | K91: 564 | L91: 621 | M91: 669 | N91: 707 | O91: 817 | P91: 1281 | Q91: 1832 | R91: 2455 | S91: 2954 | T91: 4768 | U91: 7777 | V91: 15452 | W91: 16597 | X91: 20624 | Y91: 22471 | Z91: 27010 | AA91: 33783 | AB91: 41304 | AC91: 37378 | AD91: 36766 | AE91: 39440 | AF91: 42117 | AG91: 43715 | AH91: 45680 | AI91: 49834 | AL91: =IFERROR((AI91/B91)^(1/33)-1,"") -> 0.15238141 | AM91: =IFERROR(PRODUCT(1+C92,1+D92,1+E92,1+F92,1+G92,1+H92,1+I92,1+J92,1+K92,1+L92,1+M92,1+N92,1+O92,1+P92,1+Q92,1+R92,1+S92,1+T92,1+U92,1+V92,1+W92,1+X92,1+Y92,1+Z92,1+AA92,1+AB92,1+AC92,1+AD92,1+AE92,1+AF92,1+AG92,1+AH92,1+AI92)^(1/33)-1,"") -> 0.15238141 | AO91: =IFERROR((AI91/O91)^(1/20)-1, "") -> 0.22818895 | AP91: =IFERROR(PRODUCT(1+P92,1+Q92,1+R92,1+S92,1+T92,1+U92,1+V92,1+W92,1+X92,1+Y92,1+Z92,1+AA92,1+AB92,1+AC92,1+AD92,1+AE92,1+AF92,1+AG92,1+AH92,1+AI92)^(1/20)-1,"") -> 0.22818895 | AR91: =IFERROR((AI91/Y91)^(1/10)-1,"") -> 0.08290494 | AS91: =IFERROR(PRODUCT(1+Z92,1+AA92,1+AB92,1+AC92,1+AD92,1+AE92,1+AF92,1+AG92,1+AH92,1+AI92)^(1/10)-1,"") -> 0.08290494 | AU91: =IFERROR((AI91/AD91)^(1/5)-1,"") -> 0.062712706 | AV91: =IFERROR(PRODUCT(1+AE92,1+AF92,1+AG92,1+AH92,1+AI92)^(1/5)-1,"") -> 0.062712706
A92: % Growth | C92: =IFERROR(C91/B91-1,"") -> 0.42690618 | D92: =IFERROR(D91/C91-1,"") -> 0.011453333 | E92: =IFERROR(E91/D91-1,"") -> 0.065807225 | F92: =IFERROR(F91/E91-1,"") -> -0.15893108 | G92: =IFERROR(G91/F91-1,"") -> -0.18729097 | H92: =IFERROR(H91/G91-1,"") -> -0.28395062 | I92: =IFERROR(I91/H91-1,"") -> -0.086206897 | J92: =IFERROR(J91/I91-1,"") -> -0.01572327 | ... AI92: =IFERROR(AI91/AH91-1,"") -> 0.090936953
A93: Non-Current Debt & Equity Investments | B93: 0 | C93: 0 | D93: 0 | E93: 0 | F93: 0 | G93: 0 | H93: 0 | I93: 0 | J93: 786 | K93: 128 | L93: 39 | M93: 0 | N93: 0 | O93: 0 | P93: 0 | Q93: 0 | R93: 0 | S93: 0 | T93: 0 | U93: 0 | V93: 0 | W93: 0 | X93: 0 | Y93: 0 | Z93: 0 | AA93: 0 | AB93: 0 | AC93: 0 | AD93: 0 | AE93: 0 | AF93: 0 | AG93: 0 | AH93: 0 | AI93: 0
A94: Long-Term Marketable Securities | B94: 0 | C94: 0 | D94: 0 | E94: 0 | F94: 0 | G94: 0 | H94: 0 | I94: 0 | J94: 0 | K94: 0 | L94: 0 | M94: 0 | N94: 0 | O94: 0 | P94: 0 | Q94: 0 | R94: 2379 | S94: 10528 | T94: 25391 | U94: 55618 | V94: 92122 | W94: 106215 | X94: 130162 | Y94: 164065 | Z94: 170430 | AA94: 194714 | AB94: 170799 | AC94: 105341 | AD94: 100887 | AE94: 127877 | AF94: 120805 | AG94: 100544 | AH94: 91479 | AI94: 77723
A95: Goodwill | B95: 0 | C95: 0 | D95: 0 | E95: 0 | F95: 0 | G95: 0 | H95: 0 | I95: 0 | J95: 0 | K95: 0 | L95: 0 | M95: 85 | N95: 80 | O95: 69 | P95: 38 | Q95: 38 | R95: 207 | S95: 206 | T95: 741 | U95: 896 | V95: 1135 | W95: 1577 | X95: 4616 | Y95: 5116 | Z95: 5414 | AA95: 5717 | AB95: 0 | AC95: 0 | AD95: 0 | AE95: 0 | AF95: 0 | AG95: 0 | AH95: 0 | AI95: 0
A96: % Growth | C96: =IFERROR(C95/B95-1,"") | D96: =IFERROR(D95/C95-1,"") | E96: =IFERROR(E95/D95-1,"") | F96: =IFERROR(F95/E95-1,"") | G96: =IFERROR(G95/F95-1,"") | H96: =IFERROR(H95/G95-1,"") | I96: =IFERROR(I95/H95-1,"") | J96: =IFERROR(J95/I95-1,"") | ... AI96: =IFERROR(AI95/AH95-1,"")
A97: Acquired Intangible Assets, Net | B97: 0 | C97: 0 | D97: 0 | E97: 0 | F97: 0 | G97: 0 | H97: 0 | I97: 0 | J97: 0 | K97: 76 | L97: 119 | M97: 24 | N97: 17 | O97: 27 | P97: 139 | Q97: 299 | R97: 285 | S97: 247 | T97: 342 | U97: 3536 | V97: 4224 | W97: 4179 | X97: 4142 | Y97: 3893 | Z97: 3206 | AA97: 2298 | AB97: 0 | AC97: 0 | AD97: 0 | AE97: 0 | AF97: 0 | AG97: 0 | AH97: 0 | AI97: 0
A98: Other Assets (legacy) | B98: 203.078 | C98: 173.511 | D98: 159.194 | E98: 296 | F98: 251 | G98: 323 | H98: 243 | I98: 558 | J98: 277 | K98: 110 | L98: 131 | M98: 150 | N98: 191 | O98: 303 | P98: 1238 | Q98: 1222 | R98: 839 | S98: 2011 | T98: 2263 | U98: 3556 | V98: 5478 | W98: 5146 | X98: 3764 | Y98: 5556 | Z98: 8757 | AA98: 10162 | AB98: 0 | AC98: 0 | AD98: 0 | AE98: 0 | AF98: 0 | AG98: 0 | AH98: 0 | AI98: 0
A99: Other Non-Current Assets | B99: 0 | C99: 0 | D99: 0 | E99: 0 | F99: 0 | G99: 0 | H99: 0 | I99: 0 | J99: 0 | K99: 0 | L99: 0 | M99: 0 | N99: 0 | O99: 0 | P99: 0 | Q99: 0 | R99: 0 | S99: 0 | T99: 0 | U99: 0 | V99: 0 | W99: 0 | X99: 0 | Y99: 0 | Z99: 0 | AA99: 0 | AB99: 22283 | AC99: 32978 | AD99: 42522 | AE99: 48849 | AF99: 54428 | AG99: 64758 | AH99: 74834 | AI99: 83727
A100: Total Non-Current Assets | B100: =B91+B93+B94+B95+B97+B98+B99 -> 665.299 | C100: =C91+C93+C94+C95+C97+C98+C99 -> 833.057 | D100: =D91+D93+D94+D95+D97+D98+D99 -> 826.294 | E100: =E91+E93+E94+E95+E97+E98+E99 -> 1007 | F100: =F91+F93+F94+F95+F97+F98+F99 -> 849 | G100: =G91+G93+G94+G95+G97+G98+G99 -> 809 | H100: =H91+H93+H94+H95+H97+H98+H99 -> 591 | I100: =I91+I93+I94+I95+I97+I98+I99 -> 876 | ... AI100: =AI91+AI93+AI94+AI95+AI97+AI98+AI99 -> 211284
A101: Total Assets | B101: =B89+B100 -> 4223.693 | C101: =C89+C100 -> 5171.412 | D101: =D89+D100 -> 5302.746 | E101: =E89+E100 -> 6231 | F101: =F89+F100 -> 5364 | G101: =G89+G100 -> 4233 | H101: =H89+H100 -> 4289 | I101: =I89+I100 -> 5161 | ... AI101: =AI89+AI100 -> 359241
A103: Short-Term Borrowings / Notes Payable | B103: 184.461 | C103: 823.182 | D103: 292.2 | E103: 461 | F103: 186 | G103: 25 | H103: 0 | I103: 0 | J103: 0 | K103: 0 | L103: 0 | M103: 0 | N103: 0 | O103: 0 | P103: 0 | Q103: 0 | R103: 0 | S103: 0 | T103: 0 | U103: 0 | V103: 0 | W103: 0 | X103: 0 | Y103: 0 | Z103: 0 | AA103: 0 | AB103: 0 | AC103: 0 | AD103: 0 | AE103: 0 | AF103: 0 | AG103: 0 | AH103: 0 | AI103: 0
A104: Accounts Payable | B104: 426.936 | C104: 742.622 | D104: 881.717 | E104: 1165 | F104: 791 | G104: 685 | H104: 719 | I104: 812 | J104: 1157 | K104: 801 | L104: 911 | M104: 1154 | N104: 1451 | O104: 1779 | P104: 3390 | Q104: 4970 | R104: 5520 | S104: 5601 | T104: 12015 | U104: 14632 | V104: 21175 | W104: 22367 | X104: 30196 | Y104: 35490 | Z104: 37294 | AA104: 49049 | AB104: 55888 | AC104: 46236 | AD104: 42296 | AE104: 54763 | AF104: 64115 | AG104: 62611 | AH104: 68960 | AI104: 69860
A105: Accrued Compensation & Employee Benefits | B105: 142.382 | C105: 144.779 | D105: 136.895 | E105: 131 | F105: 120 | G105: 99 | H105: 0 | I105: 0 | J105: 0 | K105: 0 | L105: 0 | M105: 0 | N105: 0 | O105: 0 | P105: 0 | Q105: 0 | R105: 0 | S105: 0 | T105: 0 | U105: 0 | V105: 0 | W105: 0 | X105: 0 | Y105: 0 | Z105: 0 | AA105: 0 | AB105: 0 | AC105: 0 | AD105: 0 | AE105: 0 | AF105: 0 | AG105: 0 | AH105: 0 | AI105: 0
A106: Accrued Marketing & Distribution | B106: 187.767 | C106: 174.547 | D106: 178.294 | E106: 206 | F106: 257 | G106: 278 | H106: 0 | I106: 0 | J106: 0 | K106: 0 | L106: 0 | M106: 0 | N106: 0 | O106: 0 | P106: 0 | Q106: 0 | R106: 0 | S106: 0 | T106: 0 | U106: 0 | V106: 0 | W106: 0 | X106: 0 | Y106: 0 | Z106: 0 | AA106: 0 | AB106: 0 | AC106: 0 | AD106: 0 | AE106: 0 | AF106: 0 | AG106: 0 | AH106: 0 | AI106: 0
A107: Accrued Warranty & Related | B107: 0 | C107: 0 | D107: 0 | E107: 0 | F107: 181 | G107: 128 | H107: 0 | I107: 0 | J107: 0 | K107: 0 | L107: 0 | M107: 0 | N107: 0 | O107: 0 | P107: 0 | Q107: 0 | R107: 0 | S107: 0 | T107: 0 | U107: 0 | V107: 0 | W107: 0 | X107: 0 | Y107: 0 | Z107: 0 | AA107: 0 | AB107: 0 | AC107: 0 | AD107: 0 | AE107: 0 | AF107: 0 | AG107: 0 | AH107: 0 | AI107: 0
A108: Accrued Restructuring Costs | B108: 105.038 | C108: 307.932 | D108: 58.238 | E108: 0 | F108: 117 | G108: 180 | H108: 0 | I108: 0 | J108: 0 | K108: 0 | L108: 0 | M108: 0 | N108: 0 | O108: 0 | P108: 0 | Q108: 0 | R108: 0 | S108: 0 | T108: 0 | U108: 0 | V108: 0 | W108: 0 | X108: 0 | Y108: 0 | Z108: 0 | AA108: 0 | AB108: 0 | AC108: 0 | AD108: 0 | AE108: 0 | AF108: 0 | AG108: 0 | AH108: 0 | AI108: 0
A109: Accrued Expenses | B109: 0 | C109: 0 | D109: 0 | E109: 0 | F109: 0 | G109: 0 | H109: 801 | I109: 737 | J109: 776 | K109: 717 | L109: 747 | M109: 899 | N109: 1200 | O109: 1708 | P109: 3081 | Q109: 4310 | R109: 4224 | S109: 3852 | T109: 5723 | U109: 9247 | V109: 11414 | W109: 13856 | X109: 18453 | Y109: 25181 | Z109: 22027 | AA109: 25744 | AB109: 0 | AC109: 0 | AD109: 0 | AE109: 0 | AF109: 0 | AG109: 0 | AH109: 0 | AI109: 0
A110: Deferred Revenue - Current | B110: 0 | C110: 0 | D110: 0 | E110: 0 | F110: 0 | G110: 0 | H110: 0 | I110: 0 | J110: 0 | K110: 0 | L110: 0 | M110: 0 | N110: 0 | O110: 0 | P110: 0 | Q110: 0 | R110: 1617 | S110: 2053 | T110: 2984 | U110: 4091 | V110: 5953 | W110: 7435 | X110: 8491 | Y110: 8940 | Z110: 8080 | AA110: 7548 | AB110: 7543 | AC110: 5522 | AD110: 6643 | AE110: 7612 | AF110: 7912 | AG110: 8061 | AH110: 8249 | AI110: 9055
A111: Other Current Liabilities | B111: 378.936 | C111: 315.023 | D111: 396.961 | E111: 362 | F111: 351 | G111: 423 | H111: 0 | I111: 0 | J111: 0 | K111: 0 | L111: 0 | M111: 0 | N111: 0 | O111: 0 | P111: 0 | Q111: 0 | R111: 0 | S111: 0 | T111: 0 | U111: 0 | V111: 0 | W111: 0 | X111: 0 | Y111: 0 | Z111: 0 | AA111: 0 | AB111: 32687 | AC111: 37720 | AD111: 42684 | AE111: 47493 | AF111: 60845 | AG111: 58829 | AH111: 78304 | AI111: 66387
A112: Commercial Paper | B112: 0 | C112: 0 | D112: 0 | E112: 0 | F112: 0 | G112: 0 | H112: 0 | I112: 0 | J112: 0 | K112: 0 | L112: 0 | M112: 0 | N112: 0 | O112: 0 | P112: 0 | Q112: 0 | R112: 0 | S112: 0 | T112: 0 | U112: 0 | V112: 0 | W112: 0 | X112: 6308 | Y112: 8499 | Z112: 8105 | AA112: 11977 | AB112: 11964 | AC112: 5980 | AD112: 4996 | AE112: 6000 | AF112: 9982 | AG112: 5985 | AH112: 9967 | AI112: 7979
...

Sheet Apple Unit Volumes
A1: Units Sold ('000)
A3: Product | B3: 1994 | C3: 1995 | D3: 1996 | E3: 1997 | F3: 1998 | G3: 1999 | H3: 2000 | I3: 2001 | J3: 2002 | K3: 2003 | L3: 2004 | M3: 2005 | N3: 2006 | O3: 2007 | P3: 2008 | Q3: 2009 | R3: 2010 | S3: 2011 | T3: 2012 | U3: 2013 | V3: 2014 | W3: 2015 | X3: 2016 | Y3: 2017 | Z3: 2018 | AA3: 2019 | AB3: 2020 | AC3: 2021 | AD3: 2022 | AE3: 2023 | AF3: 2024 | AG3: 2025 | AJ3: Source (2007 - 2018) | AK3: Source (2019 - 2025
A4: iPhone | B4: 0 | C4: 0 | D4: 0 | E4: 0 | F4: 0 | G4: 0 | H4: 0 | I4: 0 | J4: 0 | K4: 0 | L4: 0 | M4: 0 | N4: 0 | O4: 1389 | P4: 11627 | Q4: 20731 | R4: 39989 | S4: 72293 | T4: 125046 | U4: 150257 | V4: 169219 | W4: 231218 | X4: 211884 | Y4: 216756 | Z4: 217722 | AA4: 187200 | AB4: 196900 | AC4: 242000 | AD4: 232200 | AE4: 231300 | AF4: 232100 | AG4: 247000 | AJ4: Financial Statements | AK4: https://backlinko.com/iphone-users?
A5: % Growth | P5: =IFERROR(P4/O4-1,"") -> 7.3707703 | Q5: =IFERROR(Q4/P4-1,"") -> 0.78300507 | R5: =IFERROR(R4/Q4-1,"") -> 0.92894699 | S5: =IFERROR(S4/R4-1,"") -> 0.80782215 | T5: =IFERROR(T4/S4-1,"") -> 0.72971104 | U5: =IFERROR(U4/T4-1,"") -> 0.20161381 | V5: =IFERROR(V4/U4-1,"") -> 0.12619712 | W5: =IFERROR(W4/V4-1,"") -> 0.36638321 | ... AG5: =IFERROR(AG4/AF4-1,"") -> 0.064196467
A6: Mac | E6: 2874 | F6: 2763 | G6: 3448 | H6: 4558 | I6: 3087 | J6: 3101 | K6: 3012 | L6: 3290 | M6: 4534 | N6: 5303 | O6: 7051 | P6: 9715 | Q6: 10396 | R6: 13662 | S6: 16735 | T6: 18158 | U6: 16341 | V6: 18906 | W6: 20587 | X6: 18484 | Y6: 19251 | Z6: 18209 | AA6: 17500 | AB6: 20200 | AC6: 25700 | AD6: 26100 | AE6: 22100 | AF6: 23000 | AG6: 25600 | AJ6: Financial Statements | AK6: https://www.businessofapps.com/data/apple-statistics/?utm_source=chatgpt.com
A7: % Growth | F7: =IFERROR(F6/E6-1,"") -> -0.038622129 | G7: =IFERROR(G6/F6-1,"") -> 0.24791893 | H7: =IFERROR(H6/G6-1,"") -> 0.32192575 | I7: =IFERROR(I6/H6-1,"") -> -0.32272927 | J7: =IFERROR(J6/I6-1,"") -> 0.0045351474 | K7: =IFERROR(K6/J6-1,"") -> -0.028700419 | L7: =IFERROR(L6/K6-1,"") -> 0.092297477 | M7: =IFERROR(M6/L6-1,"") -> 0.3781155 | ... AG7: =IFERROR(AG6/AF6-1,"") -> 0.11304348
A8: iPad | B8: 0 | C8: 0 | D8: 0 | E8: 0 | F8: 0 | G8: 0 | H8: 0 | I8: 0 | J8: 0 | K8: 0 | L8: 0 | M8: 0 | N8: 0 | O8: 0 | P8: 0 | Q8: 0 | R8: 7458 | S8: 32394 | T8: 58310 | U8: 71033 | V8: 67977 | W8: 54856 | X8: 45590 | Y8: 43753 | Z8: 43535 | AA8: 45200 | AB8: 71100 | AC8: 57800 | AD8: 61800 | AE8: 49500 | AF8: 52100 | AG8: 58300 | AJ8: Financial Statements | AK8: https://www.businessofapps.com/data/apple-statistics/?utm_source=chatgpt.com
A9: % Growth | S9: =IFERROR(S8/R8-1,"") -> 3.3435237 | T9: =IFERROR(T8/S8-1,"") -> 0.8000247 | U9: =IFERROR(U8/T8-1,"") -> 0.21819585 | V9: =IFERROR(V8/U8-1,"") -> -0.043022257 | W9: =IFERROR(W8/V8-1,"") -> -0.19302117 | X9: =IFERROR(X8/W8-1,"") -> -0.16891498 | Y9: =IFERROR(Y8/X8-1,"") -> -0.040293924 | Z9: =IFERROR(Z8/Y8-1,"") -> -0.0049825155 | ... AG9: =IFERROR(AG8/AF8-1,"") -> 0.11900192
A11: Active iPhone, Mac, iPad | AJ11: Source
A12: iPhone | P12: 10000 | Q12: 25000 | R12: 60000 | S12: 115000 | T12: 206000 | U12: 329000 | V12: 442000 | W12: 569000 | X12: 710000 | Y12: 814000 | Z12: 888000 | AA12: 948000 | AB12: 1042000 | AC12: 1231000 | AD12: 1334000 | AE12: 1382000 | AF12: 1404000 | AG12: 1595000 | AJ12: https://backlinko.com/iphone-users?
A13: % Growth | Q13: =IFERROR(Q12/P12-1,"") -> 1.5 | R13: =IFERROR(R12/Q12-1,"") -> 1.4 | S13: =IFERROR(S12/R12-1,"") -> 0.91666667 | T13: =IFERROR(T12/S12-1,"") -> 0.79130435 | U13: =IFERROR(U12/T12-1,"") -> 0.59708738 | V13: =IFERROR(V12/U12-1,"") -> 0.34346505 | W13: =IFERROR(W12/V12-1,"") -> 0.28733032 | X13: =IFERROR(X12/W12-1,"") -> 0.24780316 | ... AG13: =IFERROR(AG12/AF12-1,"") -> 0.13603989
A14: Mac | U14: 70400 | V14: 77600 | W14: 86000 | X14: 91900 | Y14: 97900 | Z14: 103600 | AA14: 109400 | AB14: 120000 | AC14: 134300 | AD14: 144600 | AE14: 154100 | AF14: =AE14*(1+AF15) -> 172463.58 | AG14: 233000 | AJ14: https://reportify-1252068037.cos.ap-beijing.myqcloud.com/media/production/s_0132ddf6_0132ddf6f76452b09a6eaf33303689a1.pdf | AL14: https://asymco.com/2026/04/24/the-composition-of-active-devices/?utm_source=chatgpt.com
A15: % Growth | V15: =IFERROR(V14/U14-1,"") -> 0.10227273 | W15: =IFERROR(W14/V14-1,"") -> 0.10824742 | X15: =IFERROR(X14/W14-1,"") -> 0.068604651 | Y15: =IFERROR(Y14/X14-1,"") -> 0.065288357 | Z15: =IFERROR(Z14/Y14-1,"") -> 0.058222676 | AA15: =IFERROR(AA14/Z14-1,"") -> 0.055984556 | AB15: =IFERROR(AB14/AA14-1,"") -> 0.096892139 | AC15: =IFERROR(AC14/AB14-1,"") -> 0.11916667 | ... AE15: =IFERROR(AE14/AD14-1,"") -> 0.065698479 | AF15: =AC15 -> 0.11916667 | AG15: =IFERROR(AG14/AF14-1,"") -> 0.35100985
A16: iPad | U16: 121000 | V16: 195200 | W16: 258600 | X16: 293400 | Y16: 310800 | Z16: 296400 | AA16: 298200 | AB16: 311500 | AC16: 339200 | AD16: 377800 | AE16: 405700 | AF16: =AE16*(1+AF17) -> 435660.38 | AG16: 442000 | AJ16: https://reportify-1252068037.cos.ap-beijing.myqcloud.com/media/production/s_0132ddf6_0132ddf6f76452b09a6eaf33303689a1.pdf | AL16: https://asymco.com/2026/04/24/the-composition-of-active-devices/?utm_source=chatgpt.com
A17: % Growth | V17: =IFERROR(V16/U16-1,"") -> 0.61322314 | W17: =IFERROR(W16/V16-1,"") -> 0.32479508 | X17: =IFERROR(X16/W16-1,"") -> 0.13457077 | Y17: =IFERROR(Y16/X16-1,"") -> 0.059304703 | Z17: =IFERROR(Z16/Y16-1,"") -> -0.046332046 | AA17: =IFERROR(AA16/Z16-1,"") -> 0.0060728745 | AB17: =IFERROR(AB16/AA16-1,"") -> 0.044600939 | AC17: =IFERROR(AC16/AB16-1,"") -> 0.088924559 | ... AE17: =IFERROR(AE16/AD16-1,"") -> 0.073848597 | AF17: =AE17 -> 0.073848597 | AG17: =IFERROR(AG16/AF16-1,"") -> 0.014551757
A22: iPhone Units Sold By Region | AJ22: Source
A23: Americas | W23: 70300 | X23: 62900 | Y23: 69300 | Z23: 74800 | AA23: 65700 | AB23: 73300 | AC23: 84300 | AD23: 99800 | AE23: 98100 | AF23: 100400 | AG23: 105900 | AJ23: https://backlinko.com/iphone-users?
A24: % Growth | X24: =IFERROR(X23/W23-1,"") -> -0.10526316 | Y24: =IFERROR(Y23/X23-1,"") -> 0.10174881 | Z24: =IFERROR(Z23/Y23-1,"") -> 0.079365079 | AA24: =IFERROR(AA23/Z23-1,"") -> -0.12165775 | AB24: =IFERROR(AB23/AA23-1,"") -> 0.11567732 | AC24: =IFERROR(AC23/AB23-1,"") -> 0.15006821 | AD24: =IFERROR(AD23/AC23-1,"") -> 0.18386714 | AE24: =IFERROR(AE23/AD23-1,"") -> -0.017034068 | ... AG24: =IFERROR(AG23/AF23-1,"") -> 0.054780876
A25: Europe | W25: 33900 | X25: 34600 | Y25: 36800 | Z25: 38200 | AA25: 36300 | AB25: 37300 | AC25: 56100 | AD25: 56000 | AE25: 56800 | AF25: 58800 | AG25: 65900
A26: % Growth | X26: =IFERROR(X25/W25-1,"") -> 0.020648968 | Y26: =IFERROR(Y25/X25-1,"") -> 0.063583815 | Z26: =IFERROR(Z25/Y25-1,"") -> 0.038043478 | AA26: =IFERROR(AA25/Z25-1,"") -> -0.04973822 | AB26: =IFERROR(AB25/AA25-1,"") -> 0.027548209 | AC26: =IFERROR(AC25/AB25-1,"") -> 0.50402145 | AD26: =IFERROR(AD25/AC25-1,"") -> -0.0017825312 | AE26: =IFERROR(AE25/AD25-1,"") -> 0.014285714 | ... AG26: =IFERROR(AG25/AF25-1,"") -> 0.1207483
A27: China | W27: 71200 | X27: 58300 | Y27: 51600 | Z27: 44800 | AA27: 31400 | AB27: 34900 | AC27: 42900 | AD27: 43600 | AE27: 43700 | AF27: 38500 | AG27: 38200
A28: % Growth | X28: =IFERROR(X27/W27-1,"") -> -0.18117978 | Y28: =IFERROR(Y27/X27-1,"") -> -0.11492281 | Z28: =IFERROR(Z27/Y27-1,"") -> -0.13178295 | AA28: =IFERROR(AA27/Z27-1,"") -> -0.29910714 | AB28: =IFERROR(AB27/AA27-1,"") -> 0.11146497 | AC28: =IFERROR(AC27/AB27-1,"") -> 0.22922636 | AD28: =IFERROR(AD27/AC27-1,"") -> 0.016317016 | AE28: =IFERROR(AE27/AD27-1,"") -> 0.002293578 | ... AG28: =IFERROR(AG27/AF27-1,"") -> -0.0077922078
A29: Japan | W29: 15000 | X29: 14600 | Y29: 15300 | Z29: 14900 | AA29: 14800 | AB29: 14700 | AC29: 17800 | AD29: 15200 | AE29: 14600 | AF29: 14500 | AG29: 17000
A30: % Growth | X30: =IFERROR(X29/W29-1,"") -> -0.026666667 | Y30: =IFERROR(Y29/X29-1,"") -> 0.047945205 | Z30: =IFERROR(Z29/Y29-1,"") -> -0.026143791 | AA30: =IFERROR(AA29/Z29-1,"") -> -0.0067114094 | AB30: =IFERROR(AB29/AA29-1,"") -> -0.0067567568 | AC30: =IFERROR(AC29/AB29-1,"") -> 0.21088435 | AD30: =IFERROR(AD29/AC29-1,"") -> -0.14606742 | AE30: =IFERROR(AE29/AD29-1,"") -> -0.039473684 | ... AG30: =IFERROR(AG29/AF29-1,"") -> 0.17241379
A31: Rest of Asia Pacific | W31: 12200 | X31: 14800 | Y31: 13300 | Z31: 14200 | AA31: 12800 | AB31: 14000 | AC31: 17300 | AD31: 17200 | AE31: 17800 | AF31: 19900 | AG31: 20000
A32: % Growth | X32: =IFERROR(X31/W31-1,"") -> 0.21311475 | Y32: =IFERROR(Y31/X31-1,"") -> -0.10135135 | Z32: =IFERROR(Z31/Y31-1,"") -> 0.067669173 | AA32: =IFERROR(AA31/Z31-1,"") -> -0.098591549 | AB32: =IFERROR(AB31/AA31-1,"") -> 0.09375 | AC32: =IFERROR(AC31/AB31-1,"") -> 0.23571429 | AD32: =IFERROR(AD31/AC31-1,"") -> -0.0057803468 | AE32: =IFERROR(AE31/AD31-1,"") -> 0.034883721 | ... AG32: =IFERROR(AG31/AF31-1,"") -> 0.0050251256
A33: Total Sales | W33: =W31+W29+W27+W25+W23 -> 202600 | X33: =X31+X29+X27+X25+X23 -> 185200 | Y33: =Y31+Y29+Y27+Y25+Y23 -> 186300 | Z33: =Z31+Z29+Z27+Z25+Z23 -> 186900 | AA33: =AA31+AA29+AA27+AA25+AA23 -> 161000 | AB33: =AB31+AB29+AB27+AB25+AB23 -> 174200 | AC33: =AC31+AC29+AC27+AC25+AC23 -> 218400 | AD33: =AD31+AD29+AD27+AD25+AD23 -> 231800 | ... AG33: =AG31+AG29+AG27+AG25+AG23 -> 247000
A34: % Growth | X34: =IFERROR(X33/W33-1,"") -> -0.085883514 | Y34: =IFERROR(Y33/X33-1,"") -> 0.0059395248 | Z34: =IFERROR(Z33/Y33-1,"") -> 0.0032206119 | AA34: =IFERROR(AA33/Z33-1,"") -> -0.13857678 | AB34: =IFERROR(AB33/AA33-1,"") -> 0.081987578 | AC34: =IFERROR(AC33/AB33-1,"") -> 0.25373134 | AD34: =IFERROR(AD33/AC33-1,"") -> 0.061355311 | AE34: =IFERROR(AE33/AD33-1,"") -> -0.0034512511 | ... AG34: =IFERROR(AG33/AF33-1,"") -> 0.064196467
A38: Active Service Users/Subsribers
A39: Number of iOS Subscriptions | W39: 30000 | X39: 95000 | Y39: 200000 | Z39: 325000 | AA39: 480000 | AB39: 620000 | AC39: 745000 | AD39: 900000 | AE39: 1050000 | AF39: 1160000 | AG39: 1250000 | AJ39: Source
A40: % Growth | X40: =IFERROR(X39/W39-1,"") -> 2.1666667 | Y40: =IFERROR(Y39/X39-1,"") -> 1.1052632 | Z40: =IFERROR(Z39/Y39-1,"") -> 0.625 | AA40: =IFERROR(AA39/Z39-1,"") -> 0.47692308 | AB40: =IFERROR(AB39/AA39-1,"") -> 0.29166667 | AC40: =IFERROR(AC39/AB39-1,"") -> 0.2016129 | AD40: =IFERROR(AD39/AC39-1,"") -> 0.20805369 | AE40: =IFERROR(AE39/AD39-1,"") -> 0.16666667 | ... AG40: =IFERROR(AG39/AF39-1,"") -> 0.077586207 | AJ40: https://backlinko.com/iphone-users?
A41: Apple Pay Active Users | Y41: 337000 | Z41: 389000 | AA41: 441000 | AB41: 507000 | AC41: 631000 | AD41: 701000 | AE41: 744000 | AF41: 785000 | AG41: 803000
A42: % Growth | Z42: =IFERROR(Z41/Y41-1,"") -> 0.15430267 | AA42: =IFERROR(AA41/Z41-1,"") -> 0.13367609 | AB42: =IFERROR(AB41/AA41-1,"") -> 0.14965986 | AC42: =IFERROR(AC41/AB41-1,"") -> 0.24457594 | AD42: =IFERROR(AD41/AC41-1,"") -> 0.11093502 | AE42: =IFERROR(AE41/AD41-1,"") -> 0.061340942 | AF42: =IFERROR(AF41/AE41-1,"") -> 0.055107527 | AG42: =IFERROR(AG41/AF41-1,"") -> 0.022929936
A43: Apple Pay Transaction Volume | X43: 65000 | Y43: 90000 | Z43: 325000 | AA43: 650000 | AB43: 1900000 | AC43: 3700000 | AD43: 6000000 | AE43: 7300000 | AF43: 8500000 | AG43: 9450000
A44: % Growth | Y44: =IFERROR(Y43/X43-1,"") -> 0.38461538 | Z44: =IFERROR(Z43/Y43-1,"") -> 2.6111111 | AA44: =IFERROR(AA43/Z43-1,"") -> 1 | AB44: =IFERROR(AB43/AA43-1,"") -> 1.9230769 | AC44: =IFERROR(AC43/AB43-1,"") -> 0.94736842 | AD44: =IFERROR(AD43/AC43-1,"") -> 0.62162162 | AE44: =IFERROR(AE43/AD43-1,"") -> 0.21666667 | AF44: =IFERROR(AF43/AE43-1,"") -> 0.16438356 | AG44: =IFERROR(AG43/AF43-1,"") -> 0.11176471
A45: Apple Music Subscribers | W45: 11000 | X45: 20000 | Y45: 27000 | Z45: 40000 | AA45: 50000 | AB45: 72000 | AC45: 80000 | AD45: 88000 | AE45: 93000 | AF45: 95000 | AG45: 104000
A46: % Growth | X46: =IFERROR(X45/W45-1,"") -> 0.81818182 | Y46: =IFERROR(Y45/X45-1,"") -> 0.35 | Z46: =IFERROR(Z45/Y45-1,"") -> 0.48148148 | AA46: =IFERROR(AA45/Z45-1,"") -> 0.25 | AB46: =IFERROR(AB45/AA45-1,"") -> 0.44 | AC46: =IFERROR(AC45/AB45-1,"") -> 0.11111111 | AD46: =IFERROR(AD45/AC45-1,"") -> 0.1 | AE46: =IFERROR(AE45/AD45-1,"") -> 0.056818182 | ... AG46: =IFERROR(AG45/AF45-1,"") -> 0.094736842
A47: Apple TV+ Subscribers | AA47: 5700 | AB47: 33600 | AC47: 48000 | AD47: 55000 | AE47: 40000 | AF47: 30000 | AG47: 45000
A48: % Growth | AB48: =IFERROR(AB47/AA47-1,"") -> 4.8947368 | AC48: =IFERROR(AC47/AB47-1,"") -> 0.42857143 | AD48: =IFERROR(AD47/AC47-1,"") -> 0.14583333 | AE48: =IFERROR(AE47/AD47-1,"") -> -0.27272727 | AF48: =IFERROR(AF47/AE47-1,"") -> -0.25 | AG48: =IFERROR(AG47/AF47-1,"") -> 0.5
A49: Apple News Users | Y49: 70000 | Z49: 85000 | AA49: 90000 | AB49: 100000 | AC49: 135000 | AD49: 160000 | AE49: 185000 | AF49: 195000 | AG49: 220000
A50: % Growth | Z50: =IFERROR(Z49/Y49-1,"") -> 0.21428571 | AA50: =IFERROR(AA49/Z49-1,"") -> 0.058823529 | AB50: =IFERROR(AB49/AA49-1,"") -> 0.11111111 | AC50: =IFERROR(AC49/AB49-1,"") -> 0.35 | AD50: =IFERROR(AD49/AC49-1,"") -> 0.18518519 | AE50: =IFERROR(AE49/AD49-1,"") -> 0.15625 | AF50: =IFERROR(AF49/AE49-1,"") -> 0.054054054 | AG50: =IFERROR(AG49/AF49-1,"") -> 0.12820513
A51: Siri Active Users | W51: 265000 | X51: 320000 | Y51: 375000 | Z51: 500000 | AA51: 585000 | AB51: 600000 | AC51: 550000 | AD51: 485000 | AE51: 410000 | AF51: 450000 | AG51: 475000
A52: % Growth | X52: =IFERROR(X51/W51-1,"") -> 0.20754717 | Y52: =IFERROR(Y51/X51-1,"") -> 0.171875 | Z52: =IFERROR(Z51/Y51-1,"") -> 0.33333333 | AA52: =IFERROR(AA51/Z51-1,"") -> 0.17 | AB52: =IFERROR(AB51/AA51-1,"") -> 0.025641026 | AC52: =IFERROR(AC51/AB51-1,"") -> -0.083333333 | AD52: =IFERROR(AD51/AC51-1,"") -> -0.11818182 | AE52: =IFERROR(AE51/AD51-1,"") -> -0.15463918 | ... AG52: =IFERROR(AG51/AF51-1,"") -> 0.055555556
A53: Total Users/Subscribers | W53: =W51+W49+W47+W45+W43+W41+W39 -> 306000 | X53: =X51+X49+X47+X45+X43+X41+X39 -> 500000 | Y53: =Y51+Y49+Y47+Y45+Y43+Y41+Y39 -> 1099000 | Z53: =Z51+Z49+Z47+Z45+Z43+Z41+Z39 -> 1664000 | AA53: =AA51+AA49+AA47+AA45+AA43+AA41+AA39 -> 2301700 | AB53: =AB51+AB49+AB47+AB45+AB43+AB41+AB39 -> 3832600 | AC53: =AC51+AC49+AC47+AC45+AC43+AC41+AC39 -> 5889000 | AD53: =AD51+AD49+AD47+AD45+AD43+AD41+AD39 -> 8389000 | ... AG53: =AG51+AG49+AG47+AG45+AG43+AG41+AG39 -> 12347000
X54: =IFERROR(X53/W53-1,"") -> 0.63398693 | Y54: =IFERROR(Y53/X53-1,"") -> 1.198 | Z54: =IFERROR(Z53/Y53-1,"") -> 0.51410373 | AA54: =IFERROR(AA53/Z53-1,"") -> 0.38323317 | AB54: =IFERROR(AB53/AA53-1,"") -> 0.66511709 | AC54: =IFERROR(AC53/AB53-1,"") -> 0.53655482 | AD54: =IFERROR(AD53/AC53-1,"") -> 0.42452029 | AE54: =IFERROR(AE53/AD53-1,"") -> 0.17081893 | ... AG54: =IFERROR(AG53/AF53-1,"") -> 0.10093625

Sheet Apple Product Revenue
A1: Main Products Net Sales ($mm)
A3: Product | B3: 1994 | C3: 1995 | D3: 1996 | E3: 1997 | F3: 1998 | G3: 1999 | H3: 2000 | I3: 2001 | J3: 2002 | K3: 2003 | L3: 2004 | M3: 2005 | N3: 2006 | O3: 2007 | P3: 2008 | Q3: 2009 | R3: 2010 | S3: 2011 | T3: 2012 | U3: 2013 | V3: 2014 | W3: 2015 | X3: 2016 | Y3: 2017 | Z3: 2018 | AA3: 2019 | AB3: 2020 | AC3: 2021 | AD3: 2022 | AE3: 2023 | AF3: 2024 | AG3: 2025 | AM3: 13yrs | AO3: 3yrs
A4: iPhone | B4: 0 | C4: 0 | D4: 0 | E4: 0 | F4: 0 | G4: 0 | H4: 0 | I4: 0 | J4: 0 | K4: 0 | L4: 0 | M4: 0 | N4: 0 | O4: 630 | P4: 1800 | Q4: 13033 | R4: 25179 | S4: 45998 | T4: 78692 | U4: 91279 | V4: 101991 | W4: 155041 | X4: 136700 | Y4: 139337 | Z4: 164888 | AA4: 142381 | AB4: 137781 | AC4: 191973 | AD4: 205489 | AE4: 200583 | AF4: 201183 | AG4: 209586 | AM4: =(AG4/T4)^(1/13)-1 -> 0.078265015 | AO4: =(AG4/AD4)^(1/3)-1 -> 0.00660225
A5: % Growth | P5: =P4/O4-1 -> 1.8571429 | Q5: =Q4/P4-1 -> 6.2405556 | R5: =R4/Q4-1 -> 0.93194199 | S5: =S4/R4-1 -> 0.82683983 | T5: =T4/S4-1 -> 0.71077003 | U5: =U4/T4-1 -> 0.15995273 | V5: =V4/U4-1 -> 0.11735448 | W5: =W4/V4-1 -> 0.52014393 | ... AG5: =AG4/AF4-1 -> 0.041767943
A6: Mac | E6: 5671 | F6: 4862 | G6: 5082 | H6: 6885 | I6: 4403 | J6: 4534 | K6: 4491 | L6: 4923 | M6: 6275 | N6: 7375 | O6: 10336 | P6: 14354 | Q6: 13859 | R6: 17479 | S6: 21783 | T6: 23221 | U6: 21483 | V6: 24079 | W6: 25471 | X6: 22831 | Y6: 25569 | Z6: 25198 | AA6: 25740 | AB6: 28622 | AC6: 35190 | AD6: 40177 | AE6: 29357 | AF6: 29984 | AG6: 33708 | AM6: =(AG6/T6)^(1/13)-1 -> 0.02908242 | AO6: =(AG6/AD6)^(1/3)-1 -> -0.056840464
A7: % Growth | F7: =F6/E6-1 -> -0.14265562 | G7: =G6/F6-1 -> 0.045248869 | H7: =H6/G6-1 -> 0.35478158 | I7: =I6/H6-1 -> -0.36049383 | J7: =J6/I6-1 -> 0.029752442 | K7: =K6/J6-1 -> -0.0094838994 | L7: =L6/K6-1 -> 0.096192385 | M7: =M6/L6-1 -> 0.27462929 | ... AG7: =AG6/AF6-1 -> 0.12419957
A8: iPad | B8: 0 | C8: 0 | D8: 0 | E8: 0 | F8: 0 | G8: 0 | H8: 0 | I8: 0 | J8: 0 | K8: 0 | L8: 0 | M8: 0 | N8: 0 | O8: 0 | P8: 0 | Q8: 0 | R8: 4958 | S8: 19168 | T8: 30945 | U8: 31980 | V8: 30283 | W8: 23227 | X8: 20628 | Y8: 18802 | Z8: 18380 | AA8: 21280 | AB8: 23724 | AC8: 31862 | AD8: 29292 | AE8: 28300 | AF8: 26694 | AG8: 28023 | AM8: =(AG8/T8)^(1/13)-1 -> -0.0076006474 | AO8: =(AG8/AD8)^(1/3)-1 -> -0.014654509
A9: % Growth | S9: =S8/R8-1 -> 2.866075 | T9: =T8/S8-1 -> 0.61440943 | U9: =U8/T8-1 -> 0.033446437 | V9: =V8/U8-1 -> -0.053064415 | W9: =W8/V8-1 -> -0.23300201 | X9: =X8/W8-1 -> -0.11189564 | Y9: =Y8/X8-1 -> -0.088520458 | Z9: =Z8/Y8-1 -> -0.022444421 | ... AG9: =AG8/AF8-1 -> 0.049786469
A10: Wearables, Home & Accessories | B10: 0 | C10: 0 | D10: 0 | E10: 0 | F10: 0 | G10: 0 | H10: 0 | I10: 0 | J10: 0 | K10: 0 | L10: 0 | M10: 0 | N10: 0 | O10: 0 | P10: 0 | Q10: 0 | R10: 0 | S10: 0 | T10: 0 | U10: 0 | V10: 0 | W10: 9800 | X10: 10900 | Y10: 12826 | Z10: 17381 | AA10: 24482 | AB10: 30620 | AC10: 38367 | AD10: 41241 | AE10: 39845 | AF10: 37005 | AG10: 35686 | AM10: =(AG10/W10)^(1/10)-1 -> 0.13796048 | AO10: =(AG10/AD10)^(1/3)-1 -> -0.04708047
A11: % Growth | X11: =X10/W10-1 -> 0.1122449 | Y11: =Y10/X10-1 -> 0.17669725 | Z11: =Z10/Y10-1 -> 0.355138 | AA11: =AA10/Z10-1 -> 0.40854957 | AB11: =AB10/AA10-1 -> 0.25071481 | AC11: =AC10/AB10-1 -> 0.25300457 | AD11: =AD10/AC10-1 -> 0.074908124 | AE11: =AE10/AD10-1 -> -0.03384981 | ... AG11: =AG10/AF10-1 -> -0.035643832
A12: Services Net Sales | B12: 0 | C12: 0 | D12: 0 | E12: 0 | F12: 0 | G12: 0 | H12: 0 | I12: 0 | J12: 0 | K12: 0 | L12: 0 | M12: 0 | N12: 0 | O12: 0 | P12: 0 | Q12: 0 | R12: 0 | S12: 9373 | T12: 12890 | U12: 16051 | V12: 18063 | W12: 19909 | X12: 24348 | Y12: 32700 | Z12: 39748 | AA12: 46291 | AB12: 53768 | AC12: 68425 | AD12: 78129 | AE12: 85200 | AF12: 96169 | AG12: 109158 | AM12: =(AG12/T12)^(1/13)-1 -> 0.17860814 | AO12: =(AG12/AD12)^(1/3)-1 -> 0.11792955
A13: % Growth | T13: =T12/S12-1 -> 0.37522672 | U13: =U12/T12-1 -> 0.24522886 | V13: =V12/U12-1 -> 0.12535045 | W13: =W12/V12-1 -> 0.10219786 | X13: =X12/W12-1 -> 0.22296449 | Y13: =Y12/X12-1 -> 0.34302612 | Z13: =Z12/Y12-1 -> 0.21553517 | AA13: =AA12/Z12-1 -> 0.16461206 | ... AG13: =AG12/AF12-1 -> 0.13506431
A14: Total Net Sales | B14: =B4+B6+B8+B10 -> 0 | C14: =C4+C6+C8+C10 -> 0 | D14: =D4+D6+D8+D10 -> 0 | E14: =E4+E6+E8+E10 -> 5671 | F14: =F4+F6+F8+F10 -> 4862 | G14: =G4+G6+G8+G10 -> 5082 | H14: =H4+H6+H8+H10 -> 6885 | I14: =I4+I6+I8+I10 -> 4403 | ... R14: =R4+R6+R8+R10 -> 47616 | S14: =S4+S6+S8+S10+S12 -> 96322 | T14: =T4+T6+T8+T10+T12 -> 145748 | U14: =U4+U6+U8+U10+U12 -> 160793 | V14: =V4+V6+V8+V10+V12 -> 174416 | W14: =W4+W6+W8+W10+W12 -> 233448 | X14: =X4+X6+X8+X10+X12 -> 215407 | Y14: =Y4+Y6+Y8+Y10+Y12 -> 229234 | Z14: =Z4+Z6+Z8+Z10+Z12 -> 265595 | ... AG14: =AG4+AG6+AG8+AG10+AG12 -> 416161
A15: % Growth | F15: =F14/E14-1 -> -0.14265562 | G15: =G14/F14-1 -> 0.045248869 | H15: =H14/G14-1 -> 0.35478158 | I15: =I14/H14-1 -> -0.36049383 | J15: =J14/I14-1 -> 0.029752442 | K15: =K14/J14-1 -> -0.0094838994 | L15: =L14/K14-1 -> 0.096192385 | M15: =M14/L14-1 -> 0.27462929 | ... AG15: =AG14/AF14-1 -> 0.064255118

Sheet Apple Country Revenue
A1: Country / International Net Sales ($mm) | X1: Source
X2: Financial Statements
A3: Country / Group | B3: 2006 | C3: 2007 | D3: 2008 | E3: 2009 | F3: 2010 | G3: 2011 | H3: 2012 | I3: 2013 | J3: 2014 | K3: 2015 | L3: 2016 | M3: 2017 | N3: 2018 | O3: 2019 | P3: 2020 | Q3: 2021 | R3: 2022 | S3: 2023 | T3: 2024 | U3: 2025
A4: U.S. | B4: 11486 | C4: 14128 | D4: 18469 | E4: 22325 | F4: 28633 | G4: 41812 | H4: 60949 | I4: 66197 | J4: 68909 | K4: 81732 | L4: 75667 | M4: 84339 | N4: 98061 | O4: 102266 | P4: 109197 | Q4: 133803 | R4: 147859 | S4: 138573 | T4: 142196 | U4: 151790
A5: % Growth | C5: =IFERROR(C4/B4-1,"") -> 0.23001915 | D5: =IFERROR(D4/C4-1,"") -> 0.30726217 | E5: =IFERROR(E4/D4-1,"") -> 0.20878228 | F5: =IFERROR(F4/E4-1,"") -> 0.28255319 | G5: =IFERROR(G4/F4-1,"") -> 0.46027311 | H5: =IFERROR(H4/G4-1,"") -> 0.45769157 | I5: =IFERROR(I4/H4-1,"") -> 0.086104776 | J5: =IFERROR(J4/I4-1,"") -> 0.040968624 | ... U5: =IFERROR(U4/T4-1,"") -> 0.067470252
A6: China | E6: 769 | F6: 2764 | G6: 12472 | H6: 22797 | I6: 25946 | J6: 30638 | K6: 56547 | L6: 46349 | M6: 44764 | N6: 51942 | O6: 43678 | P6: 40308 | Q6: 68366 | R6: 74200 | S6: 72559 | T6: 66952 | U6: 64377
A7: % Growth | F7: =IFERROR(F6/E6-1,"") -> 2.5942783 | G7: =IFERROR(G6/F6-1,"") -> 3.512301 | H7: =IFERROR(H6/G6-1,"") -> 0.82785439 | I7: =IFERROR(I6/H6-1,"") -> 0.13813221 | J7: =IFERROR(J6/I6-1,"") -> 0.18083712 | K7: =IFERROR(K6/J6-1,"") -> 0.84564919 | L7: =IFERROR(L6/K6-1,"") -> -0.18034555 | M7: =IFERROR(M6/L6-1,"") -> -0.03419707 | ... U7: =IFERROR(U6/T6-1,"") -> -0.03846039
A8: International | B8: 7829 | C8: 9878 | D8: 14010 | E8: 19811 | F8: 33828 | G8: 53965 | H8: 72762 | I8: 78767 | J8: 83248 | K8: 95436 | L8: 93623 | M8: 100131 | N8: 115592 | O8: 114230 | P8: 125010 | Q8: 163648 | R8: 172269 | S8: 172153 | T8: 181887 | U8: 199994
A9: % Growth | C9: =IFERROR(C8/B8-1,"") -> 0.26171925 | D9: =IFERROR(D8/C8-1,"") -> 0.4183033 | E9: =IFERROR(E8/D8-1,"") -> 0.41406138 | F9: =IFERROR(F8/E8-1,"") -> 0.70753622 | G9: =IFERROR(G8/F8-1,"") -> 0.5952761 | H9: =IFERROR(H8/G8-1,"") -> 0.34831835 | I9: =IFERROR(I8/H8-1,"") -> 0.082529342 | J9: =IFERROR(J8/I8-1,"") -> 0.056889306 | ... U9: =IFERROR(U8/T8-1,"") -> 0.09955082
A10: Total net sales | B10: =B4+B6+B8 -> 19315 | C10: =C4+C6+C8 -> 24006 | D10: =D4+D6+D8 -> 32479 | E10: =E4+E6+E8 -> 42905 | F10: =F4+F6+F8 -> 65225 | G10: =G4+G6+G8 -> 108249 | H10: =H4+H6+H8 -> 156508 | I10: =I4+I6+I8 -> 170910 | ... U10: =U4+U6+U8 -> 416161
A11: % Growth | C11: =IFERROR(C10/B10-1,"") -> 0.24286824 | D11: =IFERROR(D10/C10-1,"") -> 0.35295343 | E11: =IFERROR(E10/D10-1,"") -> 0.32100742 | F11: =IFERROR(F10/E10-1,"") -> 0.52021909 | G11: =IFERROR(G10/F10-1,"") -> 0.65962438 | H11: =IFERROR(H10/G10-1,"") -> 0.44581474 | I11: =IFERROR(I10/H10-1,"") -> 0.092020855 | J11: =IFERROR(J10/I10-1,"") -> 0.069539524 | ... U11: =IFERROR(U10/T10-1,"") -> 0.064255118
A16: Americas | K16: 93800 | L16: 86600 | M16: 96600 | N16: 112000 | O16: 116900 | P16: 124500 | Q16: 153300 | R16: 169600 | S16: 162500 | T16: 167000 | U16: 178300 | X16: Source
A17: % Growth | L17: =IFERROR(L16/K16-1,"") -> -0.076759062 | M17: =IFERROR(M16/L16-1,"") -> 0.11547344 | N17: =IFERROR(N16/M16-1,"") -> 0.15942029 | O17: =IFERROR(O16/N16-1,"") -> 0.04375 | P17: =IFERROR(P16/O16-1,"") -> 0.065012831 | Q17: =IFERROR(Q16/P16-1,"") -> 0.2313253 | R17: =IFERROR(R16/Q16-1,"") -> 0.10632746 | S17: =IFERROR(S16/R16-1,"") -> -0.041863208 | ... U17: =IFERROR(U16/T16-1,"") -> 0.067664671 | X17: https://www.businessofapps.com/data/apple-statistics/?utm_source=chatgpt.com
A18: Europe | K18: 50300 | L18: 49800 | M18: 54900 | N18: 62400 | O18: 60200 | P18: 68600 | Q18: 89300 | R18: 95100 | S18: 94200 | T18: 101300 | U18: 111000
A19: % Growth | L19: =IFERROR(L18/K18-1,"") -> -0.0099403579 | M19: =IFERROR(M18/L18-1,"") -> 0.10240964 | N19: =IFERROR(N18/M18-1,"") -> 0.13661202 | O19: =IFERROR(O18/N18-1,"") -> -0.03525641 | P19: =IFERROR(P18/O18-1,"") -> 0.13953488 | Q19: =IFERROR(Q18/P18-1,"") -> 0.30174927 | R19: =IFERROR(R18/Q18-1,"") -> 0.064949608 | S19: =IFERROR(S18/R18-1,"") -> -0.0094637224 | ... U19: =IFERROR(U18/T18-1,"") -> 0.095755183
A20: China | K20: 58700 | L20: 48500 | M20: 51600 | N20: 51900 | O20: 43600 | P20: 40300 | Q20: 68300 | R20: 74200 | S20: 72500 | T20: 66900 | U20: 64300
A21: % Growth | L21: =IFERROR(L20/K20-1,"") -> -0.17376491 | M21: =IFERROR(M20/L20-1,"") -> 0.063917526 | N21: =IFERROR(N20/M20-1,"") -> 0.0058139535 | O21: =IFERROR(O20/N20-1,"") -> -0.15992293 | P21: =IFERROR(P20/O20-1,"") -> -0.075688073 | Q21: =IFERROR(Q20/P20-1,"") -> 0.69478908 | R21: =IFERROR(R20/Q20-1,"") -> 0.086383602 | S21: =IFERROR(S20/R20-1,"") -> -0.022911051 | ... U21: =IFERROR(U20/T20-1,"") -> -0.038863976
A22: Japan | K22: 15700 | L22: 16900 | M22: 15300 | N22: 21700 | O22: 21500 | P22: 21400 | Q22: 28400 | R22: 25900 | S22: 24200 | T22: 25000 | U22: 28700
A23: % Growth | L23: =IFERROR(L22/K22-1,"") -> 0.076433121 | M23: =IFERROR(M22/L22-1,"") -> -0.094674556 | N23: =IFERROR(N22/M22-1,"") -> 0.41830065 | O23: =IFERROR(O22/N22-1,"") -> -0.0092165899 | P23: =IFERROR(P22/O22-1,"") -> -0.0046511628 | Q23: =IFERROR(Q22/P22-1,"") -> 0.3271028 | R23: =IFERROR(R22/Q22-1,"") -> -0.088028169 | S23: =IFERROR(S22/R22-1,"") -> -0.065637066 | ... U23: =IFERROR(U22/T22-1,"") -> 0.148
A24: Rest of Asia Pacific | K24: 15000 | L24: 13600 | M24: 14100 | N24: 17400 | O24: 17800 | P24: 19600 | Q24: 26300 | R24: 29300 | S24: 29600 | T24: 30600 | U24: 33600
A25: % Growth | L25: =IFERROR(L24/K24-1,"") -> -0.093333333 | M25: =IFERROR(M24/L24-1,"") -> 0.036764706 | N25: =IFERROR(N24/M24-1,"") -> 0.23404255 | O25: =IFERROR(O24/N24-1,"") -> 0.022988506 | P25: =IFERROR(P24/O24-1,"") -> 0.1011236 | Q25: =IFERROR(Q24/P24-1,"") -> 0.34183673 | R25: =IFERROR(R24/Q24-1,"") -> 0.11406844 | S25: =IFERROR(S24/R24-1,"") -> 0.010238908 | ... U25: =IFERROR(U24/T24-1,"") -> 0.098039216
A26: Total Sales | K26: =K24+K22+K20+K18+K16 -> 233500 | L26: =L24+L22+L20+L18+L16 -> 215400 | M26: =M24+M22+M20+M18+M16 -> 232500 | N26: =N24+N22+N20+N18+N16 -> 265400 | O26: =O24+O22+O20+O18+O16 -> 260000 | P26: =P24+P22+P20+P18+P16 -> 274400 | Q26: =Q24+Q22+Q20+Q18+Q16 -> 365600 | R26: =R24+R22+R20+R18+R16 -> 394100 | ... U26: =U24+U22+U20+U18+U16 -> 415900
A27: % Growth | L27: =IFERROR(L26/K26-1,"") -> -0.07751606 | M27: =IFERROR(M26/L26-1,"") -> 0.079387187 | N27: =IFERROR(N26/M26-1,"") -> 0.14150538 | O27: =IFERROR(O26/N26-1,"") -> -0.020346647 | P27: =IFERROR(P26/O26-1,"") -> 0.055384615 | Q27: =IFERROR(Q26/P26-1,"") -> 0.33236152 | R27: =IFERROR(R26/Q26-1,"") -> 0.077954048 | S27: =IFERROR(S26/R26-1,"") -> -0.02816544 | ... U27: =IFERROR(U26/T26-1,"") -> 0.064227226

Sheet Apple Debt
A1: Units: $ millions
B2: 1992 | C2: 1993 | D2: 1994 | E2: 1995 | F2: 1996 | G2: 1997 | H2: 1998 | I2: 1999 | J2: 2000 | K2: 2001 | L2: 2002 | M2: 2003 | N2: 2004 | O2: 2005 | P2: 2006 | Q2: 2007 | R2: 2008 | S2: 2009 | T2: 2010 | U2: 2011 | V2: 2012 | W2: 2013 | X2: 2014 | Y2: 2015 | Z2: 2016 | AA2: 2017 | AB2: 2018 | AC2: 2019 | AD2: 2020 | AE2: 2021 | AF2: 2022 | AG2: 2023 | AH2: 2024 | AI2: 2025
A3: Commercial Paper | B3: 0 | C3: 0 | D3: 0 | E3: 0 | F3: 0 | G3: 0 | H3: 0 | I3: 0 | J3: 0 | K3: 0 | L3: 0 | M3: 0 | N3: 0 | O3: 0 | P3: 0 | Q3: 0 | R3: 0 | S3: 0 | T3: 0 | U3: 0 | V3: 0 | W3: 0 | X3: 6308 | Y3: 8499 | Z3: 8105 | AA3: 11977 | AB3: 11964 | AC3: 5980 | AD3: 4996 | AE3: 6000 | AF3: 9982 | AG3: 5985 | AH3: 9967 | AI3: 7979
A4: Current Portion Term Debt | B4: 0 | C4: 0 | D4: 0 | E4: 0 | F4: 0 | G4: 0 | H4: 0 | I4: 0 | J4: 0 | K4: 0 | L4: 0 | M4: 304 | N4: 0 | O4: 0 | P4: 0 | Q4: 0 | R4: 0 | S4: 0 | T4: 0 | U4: 0 | V4: 0 | W4: 0 | X4: 0 | Y4: 2500 | Z4: 3500 | AA4: 6496 | AB4: 8784 | AC4: 10260 | AD4: 8773 | AE4: 9613 | AF4: 11128 | AG4: 9822 | AH4: 10912 | AI4: 12350
A5: Short-term / Current Debt | B5: 184.461 | C5: 823.182 | D5: 292.2 | E5: 461 | F5: 186 | G5: 25 | H5: 0 | I5: 0 | J5: 0 | K5: 0 | L5: 0 | M5: =M3+M4 -> 304 | N5: =N3+N4 -> 0 | O5: =O3+O4 -> 0 | P5: =P3+P4 -> 0 | Q5: =Q3+Q4 -> 0 | R5: =R3+R4 -> 0 | S5: =S3+S4 -> 0 | T5: =T3+T4 -> 0 | ... AI5: =AI3+AI4 -> 20329
A7: Non-current Term Debt | B7: =B6+B3 -> 0 | C7: 7 | D7: 304 | E7: 303 | F7: 949 | G7: 951 | H7: 954 | I7: 300 | J7: 300 | K7: 317 | L7: 316 | M7: 0 | N7: 0 | O7: 0 | P7: 0 | Q7: 0 | R7: 0 | S7: 0 | T7: 0 | U7: 0 | V7: 0 | W7: 16960 | X7: 28987 | Y7: 53463 | Z7: 75427 | AA7: 97207 | AB7: 93735 | AC7: 91807 | AD7: 98667 | AE7: 109106 | AF7: 98959 | AG7: 95281 | AH7: 85750 | AI7: 78328
A8: Term Debt Carrying Value | B8: =B7+B4 -> 0 | C8: =C7+C4 -> 7 | D8: =D7+D4 -> 304 | E8: =E7+E4 -> 303 | F8: =F7+F4 -> 949 | G8: =G7+G4 -> 951 | H8: =H7+H4 -> 954 | I8: =I7+I4 -> 300 | ... AI8: =AI7+AI4 -> 90678
A9: Gross Disclosed Term Principal | B9: =B13+B6 -> 0 | D9: 300 | E9: 300 | F9: 961 | G9: 961 | H9: 961 | I9: 300 | J9: 300 | K9: 300 | L9: 300 | M9: 300 | N9: 0 | O9: 0 | P9: 0 | Q9: 0 | R9: 0 | S9: 0 | T9: 0 | U9: 0 | V9: 0 | W9: 17000 | X9: 29000 | Y9: 55700 | Z9: 78400 | AA9: 104021 | AB9: 104193 | AC9: 101679 | AD9: 106078 | AE9: 118063 | AF9: 111824 | AG9: 106572 | AH9: 97341 | AI9: 91281
A10: Principal less Carrying | B10: =B9-B8 -> 0 | D10: =D9-D8 -> -4 | E10: =E9-E8 -> -3 | F10: =F9-F8 -> 12 | G10: =G9-G8 -> 10 | H10: =H9-H8 -> 7 | I10: =I9-I8 -> 0 | J10: =J9-J8 -> 0 | K10: =K9-K8 -> -17 | ... AI10: =AI9-AI8 -> 603
A13: Total Interest-bearing Debt | B13: 0 | C13: =C7+C5 -> 830.182 | D13: =D7+D5 -> 596.2 | E13: =E7+E5 -> 764 | F13: =F7+F5 -> 1135 | G13: =G7+G5 -> 976 | H13: =H7+H5 -> 954 | I13: =I7+I5 -> 300 | J13: =J7+J5 -> 300 | ... AI13: =AI7+AI5 -> 98657
A14: % of Revenue | C14: =C13/'Apple Consolidated Statements'!C$11 -> 0.10407256 | D14: =D13/'Apple Consolidated Statements'!D11 -> 0.064883703 | E14: =E13/'Apple Consolidated Statements'!E11 -> 0.069065268 | F14: =F13/'Apple Consolidated Statements'!F11 -> 0.11542764 | G14: =G13/'Apple Consolidated Statements'!G11 -> 0.13783364 | H14: =H13/'Apple Consolidated Statements'!H11 -> 0.16057903 | I14: =I13/'Apple Consolidated Statements'!I11 -> 0.048907727 | J14: =J13/'Apple Consolidated Statements'!J11 -> 0.037579857 | K14: =K13/'Apple Consolidated Statements'!K11 -> 0.059108708 | ... AI14: =AI13/'Apple Consolidated Statements'!AI11 -> 0.2370645
A15: =A5 -> Short-term / Current Debt | B15: =B5 -> 184.461 | C15: =C5 -> 823.182 | D15: =D5 -> 292.2 | E15: =E5 -> 461 | F15: =F5 -> 186 | G15: =G5 -> 25 | H15: =H5 -> 0 | ... AI15: =AI5 -> 20329
A16: % of Revenue | B16: =B15/'Apple Consolidated Statements'!B$11 -> 0.026029762 | C16: =C15/'Apple Consolidated Statements'!C$11 -> 0.10319503 | D16: =D15/'Apple Consolidated Statements'!D$11 -> 0.031799762 | E16: =E15/'Apple Consolidated Statements'!E$11 -> 0.0416742 | F16: =F15/'Apple Consolidated Statements'!F$11 -> 0.018915895 | G16: =G15/'Apple Consolidated Statements'!G$11 -> 0.0035305748 | H16: =H15/'Apple Consolidated Statements'!H$11 -> 0 | I16: =I15/'Apple Consolidated Statements'!I$11 -> 0 | ... AI16: =AI15/'Apple Consolidated Statements'!AI$11 -> 0.048848883
A17: =A7 -> Non-current Term Debt | B17: 0 | C17: =C7 -> 7 | D17: =D7 -> 304 | E17: =E7 -> 303 | F17: =F7 -> 949 | G17: =G7 -> 951 | H17: =H7 -> 954 | I17: =I7 -> 300 | J17: =J7 -> 300 | ... AI17: =AI7 -> 78328
A18: % of Revenue | B18: =B17/'Apple Consolidated Statements'!B$11 -> 0 | C18: =C17/'Apple Consolidated Statements'!C$11 -> 0.00087752794 | D18: =D17/'Apple Consolidated Statements'!D$11 -> 0.033083941 | E18: =E17/'Apple Consolidated Statements'!E$11 -> 0.027391069 | F18: =F17/'Apple Consolidated Statements'!F$11 -> 0.096511746 | G18: =G17/'Apple Consolidated Statements'!G$11 -> 0.13430306 | H18: =H17/'Apple Consolidated Statements'!H$11 -> 0.16057903 | I18: =I17/'Apple Consolidated Statements'!I$11 -> 0.048907727 | ... AI18: =AI17/'Apple Consolidated Statements'!AI$11 -> 0.18821562

Sheet Apple Capex
A1: Units: $ millions
B2: 1992 | C2: 1993 | D2: 1994 | E2: 1995 | F2: 1996 | G2: 1997 | H2: 1998 | I2: 1999 | J2: 2000 | K2: 2001 | L2: 2002 | M2: 2003 | N2: 2004 | O2: 2005 | P2: 2006 | Q2: 2007 | R2: 2008 | S2: 2009 | T2: 2010 | U2: 2011 | V2: 2012 | W2: 2013 | X2: 2014 | Y2: 2015 | Z2: 2016 | AA2: 2017 | AB2: 2018 | AC2: 2019 | AD2: 2020 | AE2: 2021 | AF2: 2022 | AG2: 2023 | AH2: 2024 | AI2: 2025
A3: ='Apple Consolidated Statements'!A172 -> Purchases of PP&E | B3: ='Apple Consolidated Statements'!B172 -> -194.853 | C3: ='Apple Consolidated Statements'!C172 -> -213.118 | D3: ='Apple Consolidated Statements'!D172 -> -159.587 | E3: ='Apple Consolidated Statements'!E172 -> -159 | F3: ='Apple Consolidated Statements'!F172 -> -67 | G3: ='Apple Consolidated Statements'!G172 -> -53 | H3: ='Apple Consolidated Statements'!H172 -> -46 | ... AI3: ='Apple Consolidated Statements'!AI172 -> -12715 | AK3: Average 33yr | AL3: Average 20yr | AM3: Average 10yr | AN3: Average 5yr
A4: % of Revenue | B4: =-B3/'Apple Consolidated Statements'!B11 -> 0.027496203 | C4: =-C3/'Apple Consolidated Statements'!C11 -> 0.026716714 | D4: =-D3/'Apple Consolidated Statements'!D11 -> 0.017367654 | E4: =-E3/'Apple Consolidated Statements'!E11 -> 0.014373531 | F4: =-F3/'Apple Consolidated Statements'!F11 -> 0.0068137903 | G4: =-G3/'Apple Consolidated Statements'!G11 -> 0.0074848185 | H4: =-H3/'Apple Consolidated Statements'!H11 -> 0.0077428042 | I4: =-I3/'Apple Consolidated Statements'!I11 -> 0.0076622106 | ... AI4: =-AI3/'Apple Consolidated Statements'!AI11 -> 0.030553079 | AK4: =AVERAGE(B4:AI4) -> 0.030458917 | AL4: =AVERAGE(O4:AI4) -> 0.037186422 | AM4: =AVERAGE(Y4:AI4) -> 0.038121904 | AN4: =AVERAGE(AD4:AI4) -> 0.027897763

Sheet Apple Company Profile
C1: Source URL
A2: Company Overview
A3: Founded | B3: April 1, 1976 | C3: https://www.apple.com/newsroom/2026/03/apple-to-celebrate-50-years-of-thinking-different/
A4: IPO | B4: December 12, 1980 | C4: https://investor.apple.com/faq/
A5: S&P 500 addition | B5: November 30, 1982 | C5: https://github.com/datasets/s-and-p-500-companies/blob/main/data/constituents.csv
A6: Ticker / Exchange | B6: AAPL / Nasdaq | C6: https://investor.apple.com/faq/
A7: Headquarters | B7: One Apple Park Way, Cupertino, CA 95014 | C7: https://investor.apple.com/faq/
A8: FY2025 employees | B8: 166000 | C8: https://www.sec.gov/Archives/edgar/data/320193/000032019325000079/aapl-20250927.htm
A9: FY2025 net sales ($mm) | B9: 416161 | C9: https://www.apple.com/newsroom/pdfs/fy2025-q4/FY25_Q4_Consolidated_Financial_Statements.pdf
A10: Customer markets | B10: Consumer; small & mid-sized business; education; enterprise; government | C10: https://www.sec.gov/Archives/edgar/data/320193/000032019325000079/aapl-20250927.htm
A11: Distribution | B11: Direct retail/online/direct sales force + third-party carriers and other resellers | C11: https://www.sec.gov/Archives/edgar/data/320193/000032019325000079/aapl-20250927.htm
A12: FY2025 direct / indirect sales mix | B12: 40% / 60% | C12: https://www.sec.gov/Archives/edgar/data/320193/000032019325000079/aapl-20250927.htm
A13: Reportable geographies | B13: Americas; Europe; Greater China; Japan; Rest of Asia Pacific | C13: https://www.sec.gov/Archives/edgar/data/320193/000032019325000079/aapl-20250927.htm
A15: New CEO | B15: John Ternus (September 1 2026) | C15: https://www.apple.com/newsroom/2026/04/tim-cook-to-become-apple-executive-chairman-john-ternus-to-become-apple-ceo/
A16: iPhone Duo Launch | B16: Price $2,000 - September 9 2026 | C16: https://www.reuters.com/business/retail-consumer/apple-expected-unveil-first-folding-phone-with-new-ceo-ternus-command-2026-09-09/
A18: Smartphone Business (iPhone)
A19: Category | B19: Smartphones | C19: https://www.sec.gov/Archives/edgar/data/320193/000032019325000079/aapl-20250927.htm
A20: Products / offering | B20: iPhone line; iOS operating system | C20: https://www.sec.gov/Archives/edgar/data/320193/000032019325000079/aapl-20250927.htm
A21: Customers | B21: Consumer; SMB; education; enterprise; government | C21: https://www.sec.gov/Archives/edgar/data/320193/000032019325000079/aapl-20250927.htm
A22: Sales channels | B22: Apple retail/online/direct sales + cellular carriers and resellers | C22: https://www.sec.gov/Archives/edgar/data/320193/000032019325000079/aapl-20250927.htm
A23: Geographic reach | B23: Americas; Europe; Greater China; Japan; Rest of Asia Pacific | C23: https://www.sec.gov/Archives/edgar/data/320193/000032019325000079/aapl-20250927.htm
A24: FY2025 revenue ($mm) | B24: 209586 | C24: https://www.apple.com/newsroom/pdfs/fy2025-q4/FY25_Q4_Consolidated_Financial_Statements.pdf
A25: Revenue contribution | B25: 0.50361759 | C25: https://www.apple.com/newsroom/pdfs/fy2025-q4/FY25_Q4_Consolidated_Financial_Statements.pdf
A26: Market share | B26: 0.2 | C26: https://counterpointresearch.com/en/insights/global-smartphone-shipments-grew-2-percent-YoY-in-2025
A27: Market position | B27: Global smartphone shipment leader in 2025 | C27: https://counterpointresearch.com/en/insights/global-smartphone-shipments-grew-2-percent-YoY-in-2025
A29: Mac / MacBook Business
A30: Category | B30: Personal computers | C30: https://www.sec.gov/Archives/edgar/data/320193/000032019325000079/aapl-20250927.htm
A31: Products / offering | B31: MacBook Air; MacBook Pro; iMac; Mac mini; Mac Studio; Mac Pro | C31: https://www.sec.gov/Archives/edgar/data/320193/000032019325000079/aapl-20250927.htm
A32: Customers | B32: Consumer; SMB; education; enterprise; government | C32: https://www.sec.gov/Archives/edgar/data/320193/000032019325000079/aapl-20250927.htm
A33: Sales channels | B33: Apple retail/online/direct sales + resellers | C33: https://www.sec.gov/Archives/edgar/data/320193/000032019325000079/aapl-20250927.htm
A34: Geographic reach | B34: Americas; Europe; Greater China; Japan; Rest of Asia Pacific | C34: https://www.sec.gov/Archives/edgar/data/320193/000032019325000079/aapl-20250927.htm
A35: FY2025 revenue ($mm) | B35: 33708 | C35: https://www.apple.com/newsroom/pdfs/fy2025-q4/FY25_Q4_Consolidated_Financial_Statements.pdf
A36: Revenue contribution | B36: 0.080997499 | C36: https://www.apple.com/newsroom/pdfs/fy2025-q4/FY25_Q4_Consolidated_Financial_Statements.pdf
A37: Market share | B37: Just under 10% | C37: https://www.idc.com/resource-center/blog/macbook-neo-apples-strategic-play-to-disrupt-the-pc-market/
A38: Market position | B38: Top-tier global PC vendor; below 10% global unit share in 2025 | C38: https://www.idc.com/resource-center/blog/macbook-neo-apples-strategic-play-to-disrupt-the-pc-market/
A40: iPad Business
A41: Category | B41: Tablets | C41: https://www.sec.gov/Archives/edgar/data/320193/000032019325000079/aapl-20250927.htm
A42: Products / offering | B42: iPad Pro; iPad Air; iPad; iPad mini | C42: https://www.sec.gov/Archives/edgar/data/320193/000032019325000079/aapl-20250927.htm
A43: Customers | B43: Consumer; SMB; education; enterprise; government | C43: https://www.sec.gov/Archives/edgar/data/320193/000032019325000079/aapl-20250927.htm
A44: Sales channels | B44: Apple retail/online/direct sales + resellers | C44: https://www.sec.gov/Archives/edgar/data/320193/000032019325000079/aapl-20250927.htm
A45: Geographic reach | B45: Americas; Europe; Greater China; Japan; Rest of Asia Pacific | C45: https://www.sec.gov/Archives/edgar/data/320193/000032019325000079/aapl-20250927.htm
A46: FY2025 revenue ($mm) | B46: 28023 | C46: https://www.apple.com/newsroom/pdfs/fy2025-q4/FY25_Q4_Consolidated_Financial_Statements.pdf
A47: Revenue contribution | B47: 0.06733692 | C47: https://www.apple.com/newsroom/pdfs/fy2025-q4/FY25_Q4_Consolidated_Financial_Statements.pdf
A48: Market share | B48: 0.419 | C48: https://www.idc.com/resource-center/blog/global-tablet-shipments-rise-1-9-in-4q25-as-seasonal-demand-offsets-cooling-replacement-cycle/
A49: Market position | B49: Global tablet shipment leader in 4Q25 | C49: https://www.idc.com/resource-center/blog/global-tablet-shipments-rise-1-9-in-4q25-as-seasonal-demand-offsets-cooling-replacement-cycle/
A51: Wearables, Home & Accessories Business
A52: Category | B52: Wearables; home devices; accessories | C52: https://www.sec.gov/Archives/edgar/data/320193/000032019325000079/aapl-20250927.htm
A53: Products / offering | B53: Apple Watch; AirPods; AirPods Max; Beats; Apple Vision Pro; Apple TV 4K; HomePod; accessories | C53: https://www.sec.gov/Archives/edgar/data/320193/000032019325000079/aapl-20250927.htm
A54: Customers | B54: Consumer; SMB; education; enterprise; government | C54: https://www.sec.gov/Archives/edgar/data/320193/000032019325000079/aapl-20250927.htm
A55: Sales channels | B55: Apple retail/online/direct sales + carriers and resellers | C55: https://www.sec.gov/Archives/edgar/data/320193/000032019325000079/aapl-20250927.htm
A56: Geographic reach | B56: Americas; Europe; Greater China; Japan; Rest of Asia Pacific | C56: https://www.sec.gov/Archives/edgar/data/320193/000032019325000079/aapl-20250927.htm
A57: FY2025 revenue ($mm) | B57: 35686 | C57: https://www.apple.com/newsroom/pdfs/fy2025-q4/FY25_Q4_Consolidated_Financial_Statements.pdf
A58: Revenue contribution | B58: 0.085750467 | C58: https://www.apple.com/newsroom/pdfs/fy2025-q4/FY25_Q4_Consolidated_Financial_Statements.pdf
A59: Wearables market share | B59: 0.209 | C59: https://www.idc.com/promo/wearablevendor/?source=content_type%3Areact%7Cfirst_level_url%3Aarticle%7Csection%3Amain_content%7Cbutton%3Abody_link
A60: Market position | B60: Largest global wearable-device company by unit share in 4Q25 | C60: https://www.idc.com/promo/wearablevendor/?source=content_type%3Areact%7Cfirst_level_url%3Aarticle%7Csection%3Amain_content%7Cbutton%3Abody_link
A62: Services Business
A63: Category | B63: Digital and support services | C63: https://www.sec.gov/Archives/edgar/data/320193/000032019325000079/aapl-20250927.htm
A64: Services / offering | B64: Advertising; AppleCare; cloud services; App Store/digital content; Apple Arcade; Fitness+; Apple Music; News+; Apple TV; Apple Card; Apple Pay | C64: https://www.sec.gov/Archives/edgar/data/320193/000032019325000079/aapl-20250927.htm
A65: Customers | B65: Apple device users plus customers of Apple service platforms | C65: https://www.sec.gov/Archives/edgar/data/320193/000032019325000079/aapl-20250927.htm
A66: Sales channels | B66: Apple service platforms and direct customer relationships | C66: https://www.sec.gov/Archives/edgar/data/320193/000032019325000079/aapl-20250927.htm
A67: Geographic reach | B67: Services sold in the same major markets as Apple products | C67: https://www.sec.gov/Archives/edgar/data/320193/000032019325000079/aapl-20250927.htm
A68: FY2025 revenue ($mm) | B68: 109158 | C68: https://www.apple.com/newsroom/pdfs/fy2025-q4/FY25_Q4_Consolidated_Financial_Statements.pdf
A69: Revenue contribution | B69: 0.26229752 | C69: https://www.apple.com/newsroom/pdfs/fy2025-q4/FY25_Q4_Consolidated_Financial_Statements.pdf
A70: Market share
A71: FY2025 growth driver | B71: Advertising, App Store and cloud services | C71: https://www.sec.gov/Archives/edgar/data/320193/000032019325000079/aapl-20250927.htm
A74: What about the chip story? What about the AI Story?
A75: Does Apple Manufacture its own products? Does it handle the distribution? Does it have it's own retail outlets (Direct To Consumer), and Online stores?
