Workbook

Sheet Vertical Analysis
A2: Fiscal Year | B2: 2010
A4: INCOME STATEMENT
A5: Net Sales / Revenue | B5: 65225
A6: Total COGS | B6: 39541
A7: Gross Profit | B7: =B5-B6 -> 25684
A9: Research & Development | B9: 1782
A10: Selling, General & Administrative | B10: 5517
A11: Total Operating Expenses | B11: =B9+B10 -> 7299
A12: Operating Income (EBIT) | B12: =B7-B11 -> 18385
A13: % Growth | B13: =IFERROR(B12/#REF!-1,"")
A15: Other Income/(Expense), Net | B15: 155
A16: Total Other Income/(Expense) | B16: =B15 -> 155
A19: Income Before Income Taxes | B19: =B12+B16 -> 18540
A20: Provision for Income Taxes | B20: 4527
A21: Net Income | B21: =B19-B20 -> 14013
A24: BALANCE SHEET
A25: Cash & Cash Equivalents (FY1992 source reports Cash + ST Investments combined) | B25: 11261
A26: Short-Term Investments / Marketable Securities | B26: 14359
A27: Accounts Receivable, Net | B27: 5510
A28: Inventories | B28: 1051
A29: Deferred Tax Assets | B29: 1636
A30: Vendor Non-Trade Receivables | B30: 4414
A31: Other Current Assets | B31: 3447
A32: Total Current Assets | B32: =B25+B26+B27+B28+B29+B30+B31 -> 41678
A34: Property, Plant & Equipment, Net | B34: 4768
A35: Long-Term Marketable Securities | B35: 25391
A36: Goodwill | B36: 741
A37: Acquired Intangible Assets, Net | B37: 342
A38: Other Assets (legacy) | B38: 2263
A39: Other Non-Current Assets | B39: 0
A40: Total Non-Current Assets | B40: =B34+B35+B36+B37+B38+B39 -> 33505
A41: Total Assets | B41: =B32+B40 -> 75183
A43: Short-Term Borrowings / Notes Payable | B43: 0
A44: Accounts Payable | B44: 12015
A45: Accrued Expenses | B45: 5723
A46: Deferred Revenue - Current | B46: 2984
A47: Other Current Liabilities | B47: 0
A48: Commercial Paper | B48: 0
A49: Current Debt / Term Debt | B49: 0
A50: Total Current Liabilities | B50: =SUM(B43:B49) -> 20722
A52: Long-Term Debt / Term Debt | B52: 0
A53: Deferred Revenue - Non-Current | B53: 1139
A54: Other Non-Current Liabilities | B54: 5531
A55: Total Non-Current Liabilities | B55: =SUM(B52:B54) -> 6670
A56: Total Liabilities | B56: =B50+B55 -> 27392
A58: Common Stock & Additional Paid-In Capital | B58: 10668
A59: Retained Earnings | B59: 37169
A60: Accumulated Deficit | B60: 0
A61: Accumulated Other Comprehensive Income/(Loss) | B61: -46
A62: Total Shareholders' Equity | B62: =SUM(B58:B61) -> 47791
A63: Total Liabilities & Shareholders' Equity | B63: =B56+B62 -> 75183
A67: VERTICAL ANALYSIS — APPLE INC. (FY2010–FY2025)
A68: All ratios calculated from the original financial statements above; original data unchanged.
A70: Financial statement line item | B70: 2010 | C70: 2011 | D70: 2012 | E70: 2013 | F70: 2014 | G70: 2015 | H70: 2016 | I70: 2017 | J70: 2018 | K70: 2019 | L70: 2020 | M70: 2021 | N70: 2022 | O70: 2023 | P70: 2024 | Q70: 2025
A71: INCOME STATEMENT
A72: Net Sales / Revenue | B72: =IFERROR(B5/B$5,"") -> 1 | C72: =IFERROR('Horizontal Analysis'!C5/'Horizontal Analysis'!C$5,"") -> 1 | D72: =IFERROR('Horizontal Analysis'!D5/'Horizontal Analysis'!D$5,"") -> 1 | E72: =IFERROR('Horizontal Analysis'!E5/'Horizontal Analysis'!E$5,"") -> 1 | F72: =IFERROR('Horizontal Analysis'!F5/'Horizontal Analysis'!F$5,"") -> 1 | G72: =IFERROR('Horizontal Analysis'!G5/'Horizontal Analysis'!G$5,"") -> 1 | H72: =IFERROR('Horizontal Analysis'!H5/'Horizontal Analysis'!H$5,"") -> 1 | I72: =IFERROR('Horizontal Analysis'!I5/'Horizontal Analysis'!I$5,"") -> 1 | J72: =IFERROR('Horizontal Analysis'!J5/'Horizontal Analysis'!J$5,"") -> 1 | ... Q72: =IFERROR('Horizontal Analysis'!Q5/'Horizontal Analysis'!Q$5,"") -> 1
A73: Total COGS | B73: =IFERROR(B6/B$5,"") -> 0.60622461 | C73: =IFERROR('Horizontal Analysis'!C6/'Horizontal Analysis'!C$5,"") -> 0.59521104 | D73: =IFERROR('Horizontal Analysis'!D6/'Horizontal Analysis'!D$5,"") -> 0.5612876 | E73: =IFERROR('Horizontal Analysis'!E6/'Horizontal Analysis'!E$5,"") -> 0.62375519 | F73: =IFERROR('Horizontal Analysis'!F6/'Horizontal Analysis'!F$5,"") -> 0.61411964 | G73: =IFERROR('Horizontal Analysis'!G6/'Horizontal Analysis'!G$5,"") -> 0.59940098 | H73: =IFERROR('Horizontal Analysis'!H6/'Horizontal Analysis'!H$5,"") -> 0.60924044 | I73: =IFERROR('Horizontal Analysis'!I6/'Horizontal Analysis'!I$5,"") -> 0.6153014 | J73: =IFERROR('Horizontal Analysis'!J6/'Horizontal Analysis'!J$5,"") -> 0.61656281 | ... Q73: =IFERROR('Horizontal Analysis'!Q6/'Horizontal Analysis'!Q$5,"") -> 0.53094836
A74: Gross Profit | B74: =IFERROR(B7/B$5,"") -> 0.39377539 | C74: =IFERROR('Horizontal Analysis'!C7/'Horizontal Analysis'!C$5,"") -> 0.40478896 | D74: =IFERROR('Horizontal Analysis'!D7/'Horizontal Analysis'!D$5,"") -> 0.4387124 | E74: =IFERROR('Horizontal Analysis'!E7/'Horizontal Analysis'!E$5,"") -> 0.37624481 | F74: =IFERROR('Horizontal Analysis'!F7/'Horizontal Analysis'!F$5,"") -> 0.38588036 | G74: =IFERROR('Horizontal Analysis'!G7/'Horizontal Analysis'!G$5,"") -> 0.40059902 | H74: =IFERROR('Horizontal Analysis'!H7/'Horizontal Analysis'!H$5,"") -> 0.39075956 | I74: =IFERROR('Horizontal Analysis'!I7/'Horizontal Analysis'!I$5,"") -> 0.3846986 | J74: =IFERROR('Horizontal Analysis'!J7/'Horizontal Analysis'!J$5,"") -> 0.38343719 | ... Q74: =IFERROR('Horizontal Analysis'!Q7/'Horizontal Analysis'!Q$5,"") -> 0.46905164
A76: Research & Development | B76: =IFERROR(B9/B$5,"") -> 0.027320813 | C76: =IFERROR('Horizontal Analysis'!C9/'Horizontal Analysis'!C$5,"") -> 0.022439006 | D76: =IFERROR('Horizontal Analysis'!D9/'Horizontal Analysis'!D$5,"") -> 0.02160273 | E76: =IFERROR('Horizontal Analysis'!E9/'Horizontal Analysis'!E$5,"") -> 0.026183371 | F76: =IFERROR('Horizontal Analysis'!F9/'Horizontal Analysis'!F$5,"") -> 0.03304795 | G76: =IFERROR('Horizontal Analysis'!G9/'Horizontal Analysis'!G$5,"") -> 0.034516398 | H76: =IFERROR('Horizontal Analysis'!H9/'Horizontal Analysis'!H$5,"") -> 0.046582483 | I76: =IFERROR('Horizontal Analysis'!I9/'Horizontal Analysis'!I$5,"") -> 0.050520429 | J76: =IFERROR('Horizontal Analysis'!J9/'Horizontal Analysis'!J$5,"") -> 0.053600407 | ... Q76: =IFERROR('Horizontal Analysis'!Q9/'Horizontal Analysis'!Q$5,"") -> 0.083020754
A77: Selling, General & Administrative | B77: =IFERROR(B10/B$5,"") -> 0.084584132 | C77: =IFERROR('Horizontal Analysis'!C10/'Horizontal Analysis'!C$5,"") -> 0.070199263 | D77: =IFERROR('Horizontal Analysis'!D10/'Horizontal Analysis'!D$5,"") -> 0.064150075 | E77: =IFERROR('Horizontal Analysis'!E10/'Horizontal Analysis'!E$5,"") -> 0.063366684 | F77: =IFERROR('Horizontal Analysis'!F10/'Horizontal Analysis'!F$5,"") -> 0.065609016 | G77: =IFERROR('Horizontal Analysis'!G10/'Horizontal Analysis'!G$5,"") -> 0.061309715 | H77: =IFERROR('Horizontal Analysis'!H10/'Horizontal Analysis'!H$5,"") -> 0.065822973 | I77: =IFERROR('Horizontal Analysis'!I10/'Horizontal Analysis'!I$5,"") -> 0.066573894 | J77: =IFERROR('Horizontal Analysis'!J10/'Horizontal Analysis'!J$5,"") -> 0.062896515 | ... Q77: =IFERROR('Horizontal Analysis'!Q10/'Horizontal Analysis'!Q$5,"") -> 0.066322889
A78: Total Operating Expenses | B78: =IFERROR(B11/B$5,"") -> 0.11190494 | C78: =IFERROR('Horizontal Analysis'!C11/'Horizontal Analysis'!C$5,"") -> 0.092638269 | D78: =IFERROR('Horizontal Analysis'!D11/'Horizontal Analysis'!D$5,"") -> 0.085752805 | E78: =IFERROR('Horizontal Analysis'!E11/'Horizontal Analysis'!E$5,"") -> 0.089550056 | F78: =IFERROR('Horizontal Analysis'!F11/'Horizontal Analysis'!F$5,"") -> 0.098656965 | G78: =IFERROR('Horizontal Analysis'!G11/'Horizontal Analysis'!G$5,"") -> 0.095826113 | H78: =IFERROR('Horizontal Analysis'!H11/'Horizontal Analysis'!H$5,"") -> 0.11240546 | I78: =IFERROR('Horizontal Analysis'!I11/'Horizontal Analysis'!I$5,"") -> 0.11709432 | J78: =IFERROR('Horizontal Analysis'!J11/'Horizontal Analysis'!J$5,"") -> 0.11649692 | ... Q78: =IFERROR('Horizontal Analysis'!Q11/'Horizontal Analysis'!Q$5,"") -> 0.14934364
A79: Operating Income (EBIT) | B79: =IFERROR(B12/B$5,"") -> 0.28187045 | C79: =IFERROR('Horizontal Analysis'!C12/'Horizontal Analysis'!C$5,"") -> 0.31215069 | D79: =IFERROR('Horizontal Analysis'!D12/'Horizontal Analysis'!D$5,"") -> 0.35295959 | E79: =IFERROR('Horizontal Analysis'!E12/'Horizontal Analysis'!E$5,"") -> 0.28669475 | F79: =IFERROR('Horizontal Analysis'!F12/'Horizontal Analysis'!F$5,"") -> 0.28722339 | G79: =IFERROR('Horizontal Analysis'!G12/'Horizontal Analysis'!G$5,"") -> 0.30477291 | H79: =IFERROR('Horizontal Analysis'!H12/'Horizontal Analysis'!H$5,"") -> 0.2783541 | I79: =IFERROR('Horizontal Analysis'!I12/'Horizontal Analysis'!I$5,"") -> 0.26760428 | J79: =IFERROR('Horizontal Analysis'!J12/'Horizontal Analysis'!J$5,"") -> 0.26694027 | ... Q79: =IFERROR('Horizontal Analysis'!Q12/'Horizontal Analysis'!Q$5,"") -> 0.319708
A82: Other Income/(Expense), Net | B82: =IFERROR(B15/B$5,"") -> 0.0023763894 | C82: =IFERROR('Horizontal Analysis'!C15/'Horizontal Analysis'!C$5,"") -> 0.0038337537 | D82: =IFERROR('Horizontal Analysis'!D15/'Horizontal Analysis'!D$5,"") -> 0.0033352928 | E82: =IFERROR('Horizontal Analysis'!E15/'Horizontal Analysis'!E$5,"") -> 0.0067637938 | F82: =IFERROR('Horizontal Analysis'!F15/'Horizontal Analysis'!F$5,"") -> 0.005361197 | G82: =IFERROR('Horizontal Analysis'!G15/'Horizontal Analysis'!G$5,"") -> 0.0054981495 | H82: =IFERROR('Horizontal Analysis'!H15/'Horizontal Analysis'!H$5,"") -> 0.0062511883 | I82: =IFERROR('Horizontal Analysis'!I15/'Horizontal Analysis'!I$5,"") -> 0.011974663 | J82: =IFERROR('Horizontal Analysis'!J15/'Horizontal Analysis'!J$5,"") -> 0.0075490879 | ... Q82: =IFERROR('Horizontal Analysis'!Q15/'Horizontal Analysis'!Q$5,"") -> -0.00077133609
A83: Total Other Income/(Expense) | B83: =IFERROR(B16/B$5,"") -> 0.0023763894 | C83: =IFERROR('Horizontal Analysis'!C16/'Horizontal Analysis'!C$5,"") -> 0.0038337537 | D83: =IFERROR('Horizontal Analysis'!D16/'Horizontal Analysis'!D$5,"") -> 0.0033352928 | E83: =IFERROR('Horizontal Analysis'!E16/'Horizontal Analysis'!E$5,"") -> 0.0067637938 | F83: =IFERROR('Horizontal Analysis'!F16/'Horizontal Analysis'!F$5,"") -> 0.005361197 | G83: =IFERROR('Horizontal Analysis'!G16/'Horizontal Analysis'!G$5,"") -> 0.0054981495 | H83: =IFERROR('Horizontal Analysis'!H16/'Horizontal Analysis'!H$5,"") -> 0.0062511883 | I83: =IFERROR('Horizontal Analysis'!I16/'Horizontal Analysis'!I$5,"") -> 0.011974663 | J83: =IFERROR('Horizontal Analysis'!J16/'Horizontal Analysis'!J$5,"") -> 0.0075490879 | ... Q83: =IFERROR('Horizontal Analysis'!Q16/'Horizontal Analysis'!Q$5,"") -> -0.00077133609
A86: Income Before Income Taxes | B86: =IFERROR(B19/B$5,"") -> 0.28424684 | C86: =IFERROR('Horizontal Analysis'!C19/'Horizontal Analysis'!C$5,"") -> 0.31598444 | D86: =IFERROR('Horizontal Analysis'!D19/'Horizontal Analysis'!D$5,"") -> 0.35629489 | E86: =IFERROR('Horizontal Analysis'!E19/'Horizontal Analysis'!E$5,"") -> 0.29345855 | F86: =IFERROR('Horizontal Analysis'!F19/'Horizontal Analysis'!F$5,"") -> 0.29258459 | G86: =IFERROR('Horizontal Analysis'!G19/'Horizontal Analysis'!G$5,"") -> 0.31027106 | H86: =IFERROR('Horizontal Analysis'!H19/'Horizontal Analysis'!H$5,"") -> 0.28460529 | I86: =IFERROR('Horizontal Analysis'!I19/'Horizontal Analysis'!I$5,"") -> 0.27957895 | J86: =IFERROR('Horizontal Analysis'!J19/'Horizontal Analysis'!J$5,"") -> 0.27448935 | ... Q86: =IFERROR('Horizontal Analysis'!Q19/'Horizontal Analysis'!Q$5,"") -> 0.31893666
A87: Provision for Income Taxes | B87: =IFERROR(B20/B$5,"") -> 0.069405903 | C87: =IFERROR('Horizontal Analysis'!C20/'Horizontal Analysis'!C$5,"") -> 0.076518028 | D87: =IFERROR('Horizontal Analysis'!D20/'Horizontal Analysis'!D$5,"") -> 0.08964398 | E87: =IFERROR('Horizontal Analysis'!E20/'Horizontal Analysis'!E$5,"") -> 0.076753847 | F87: =IFERROR('Horizontal Analysis'!F20/'Horizontal Analysis'!F$5,"") -> 0.076440822 | G87: =IFERROR('Horizontal Analysis'!G20/'Horizontal Analysis'!G$5,"") -> 0.08181332 | H87: =IFERROR('Horizontal Analysis'!H20/'Horizontal Analysis'!H$5,"") -> 0.072737306 | I87: =IFERROR('Horizontal Analysis'!I20/'Horizontal Analysis'!I$5,"") -> 0.068654737 | J87: =IFERROR('Horizontal Analysis'!J20/'Horizontal Analysis'!J$5,"") -> 0.050347333 | ... Q87: =IFERROR('Horizontal Analysis'!Q20/'Horizontal Analysis'!Q$5,"") -> 0.04978602
A88: Net Income | B88: =IFERROR(B21/B$5,"") -> 0.21484094 | C88: =IFERROR('Horizontal Analysis'!C21/'Horizontal Analysis'!C$5,"") -> 0.23946642 | D88: =IFERROR('Horizontal Analysis'!D21/'Horizontal Analysis'!D$5,"") -> 0.26665091 | E88: =IFERROR('Horizontal Analysis'!E21/'Horizontal Analysis'!E$5,"") -> 0.2167047 | F88: =IFERROR('Horizontal Analysis'!F21/'Horizontal Analysis'!F$5,"") -> 0.21614377 | G88: =IFERROR('Horizontal Analysis'!G21/'Horizontal Analysis'!G$5,"") -> 0.22845774 | H88: =IFERROR('Horizontal Analysis'!H21/'Horizontal Analysis'!H$5,"") -> 0.21186798 | I88: =IFERROR('Horizontal Analysis'!I21/'Horizontal Analysis'!I$5,"") -> 0.21092421 | J88: =IFERROR('Horizontal Analysis'!J21/'Horizontal Analysis'!J$5,"") -> 0.22414202 | ... Q88: =IFERROR('Horizontal Analysis'!Q21/'Horizontal Analysis'!Q$5,"") -> 0.26915064
A91: BALANCE SHEET
A92: Cash & Cash Equivalents (FY1992 source reports Cash + ST Investments combined) | B92: =IFERROR(B25/B$41,"") -> 0.1497812 | C92: =IFERROR('Horizontal Analysis'!C25/'Horizontal Analysis'!C$41,"") -> 0.084342319 | D92: =IFERROR('Horizontal Analysis'!D25/'Horizontal Analysis'!D$41,"") -> 0.061034624 | E92: =IFERROR('Horizontal Analysis'!E25/'Horizontal Analysis'!E$41,"") -> 0.068884058 | F92: =IFERROR('Horizontal Analysis'!F25/'Horizontal Analysis'!F$41,"") -> 0.059713853 | G92: =IFERROR('Horizontal Analysis'!G25/'Horizontal Analysis'!G$41,"") -> 0.072707493 | H92: =IFERROR('Horizontal Analysis'!H25/'Horizontal Analysis'!H$41,"") -> 0.063677002 | I92: =IFERROR('Horizontal Analysis'!I25/'Horizontal Analysis'!I$41,"") -> 0.054058015 | J92: =IFERROR('Horizontal Analysis'!J25/'Horizontal Analysis'!J$41,"") -> 0.070853784 | ... Q92: =IFERROR('Horizontal Analysis'!Q25/'Horizontal Analysis'!Q$41,"") -> 0.10002756
A93: Short-Term Investments / Marketable Securities | B93: =IFERROR(B26/B$41,"") -> 0.19098732 | C93: =IFERROR('Horizontal Analysis'!C26/'Horizontal Analysis'!C$41,"") -> 0.13866857 | D93: =IFERROR('Horizontal Analysis'!D26/'Horizontal Analysis'!D$41,"") -> 0.1044109 | E93: =IFERROR('Horizontal Analysis'!E26/'Horizontal Analysis'!E$41,"") -> 0.12699034 | F93: =IFERROR('Horizontal Analysis'!F26/'Horizontal Analysis'!F$41,"") -> 0.048451727 | G93: =IFERROR('Horizontal Analysis'!G26/'Horizontal Analysis'!G$41,"") -> 0.070507679 | H93: =IFERROR('Horizontal Analysis'!H26/'Horizontal Analysis'!H$41,"") -> 0.14508247 | I93: =IFERROR('Horizontal Analysis'!I26/'Horizontal Analysis'!I$41,"") -> 0.14358985 | J93: =IFERROR('Horizontal Analysis'!J26/'Horizontal Analysis'!J$41,"") -> 0.1104327 | ... Q93: =IFERROR('Horizontal Analysis'!Q26/'Horizontal Analysis'!Q$41,"") -> 0.052229562
A94: Accounts Receivable, Net | B94: =IFERROR(B27/B$41,"") -> 0.073287844 | C94: =IFERROR('Horizontal Analysis'!C27/'Horizontal Analysis'!C$41,"") -> 0.046136924 | D94: =IFERROR('Horizontal Analysis'!D27/'Horizontal Analysis'!D$41,"") -> 0.062079698 | E94: =IFERROR('Horizontal Analysis'!E27/'Horizontal Analysis'!E$41,"") -> 0.063294686 | F94: =IFERROR('Horizontal Analysis'!F27/'Horizontal Analysis'!F$41,"") -> 0.075310884 | G94: =IFERROR('Horizontal Analysis'!G27/'Horizontal Analysis'!G$41,"") -> 0.058004193 | H94: =IFERROR('Horizontal Analysis'!H27/'Horizontal Analysis'!H$41,"") -> 0.048973222 | I94: =IFERROR('Horizontal Analysis'!I27/'Horizontal Analysis'!I$41,"") -> 0.047623488 | J94: =IFERROR('Horizontal Analysis'!J27/'Horizontal Analysis'!J$41,"") -> 0.063397361 | ... Q94: =IFERROR('Horizontal Analysis'!Q27/'Horizontal Analysis'!Q$41,"") -> 0.11072511
A95: Inventories | B95: =IFERROR(B28/B$41,"") -> 0.013979224 | C95: =IFERROR('Horizontal Analysis'!C28/'Horizontal Analysis'!C$41,"") -> 0.006668328 | D95: =IFERROR('Horizontal Analysis'!D28/'Horizontal Analysis'!D$41,"") -> 0.0044926845 | E95: =IFERROR('Horizontal Analysis'!E28/'Horizontal Analysis'!E$41,"") -> 0.0085217391 | F95: =IFERROR('Horizontal Analysis'!F28/'Horizontal Analysis'!F$41,"") -> 0.0091054568 | G95: =IFERROR('Horizontal Analysis'!G28/'Horizontal Analysis'!G$41,"") -> 0.0080866431 | H95: =IFERROR('Horizontal Analysis'!H28/'Horizontal Analysis'!H$41,"") -> 0.0066275809 | I95: =IFERROR('Horizontal Analysis'!I28/'Horizontal Analysis'!I$41,"") -> 0.012935663 | J95: =IFERROR('Horizontal Analysis'!J28/'Horizontal Analysis'!J$41,"") -> 0.010816871 | ... Q95: =IFERROR('Horizontal Analysis'!Q28/'Horizontal Analysis'!Q$41,"") -> 0.015916891
A96: Deferred Tax Assets | B96: =IFERROR(B29/B$41,"") -> 0.021760238 | C96: =IFERROR('Horizontal Analysis'!C29/'Horizontal Analysis'!C$41,"") -> 0.017306717 | D96: =IFERROR('Horizontal Analysis'!D29/'Horizontal Analysis'!D$41,"") -> 0.014670802 | E96: =IFERROR('Horizontal Analysis'!E29/'Horizontal Analysis'!E$41,"") -> 0.016681159 | F96: =IFERROR('Horizontal Analysis'!F29/'Horizontal Analysis'!F$41,"") -> 0.018624994 | G96: =IFERROR('Horizontal Analysis'!G29/'Horizontal Analysis'!G$41,"") -> 0.019092602 | H96: =IFERROR('Horizontal Analysis'!H29/'Horizontal Analysis'!H$41,"") -> 0 | I96: =IFERROR('Horizontal Analysis'!I29/'Horizontal Analysis'!I$41,"") -> 0 | J96: =IFERROR('Horizontal Analysis'!J29/'Horizontal Analysis'!J$41,"") -> 0 | ... Q96: =IFERROR('Horizontal Analysis'!Q29/'Horizontal Analysis'!Q$41,"") -> 0
A97: Vendor Non-Trade Receivables | B97: =IFERROR(B30/B$41,"") -> 0.058710081 | C97: =IFERROR('Horizontal Analysis'!C30/'Horizontal Analysis'!C$41,"") -> 0.054549673 | D97: =IFERROR('Horizontal Analysis'!D30/'Horizontal Analysis'!D$41,"") -> 0.044086241 | E97: =IFERROR('Horizontal Analysis'!E30/'Horizontal Analysis'!E$41,"") -> 0.03642029 | F97: =IFERROR('Horizontal Analysis'!F30/'Horizontal Analysis'!F$41,"") -> 0.042093867 | G97: =IFERROR('Horizontal Analysis'!G30/'Horizontal Analysis'!G$41,"") -> 0.046454305 | H97: =IFERROR('Horizontal Analysis'!H30/'Horizontal Analysis'!H$41,"") -> 0.042106278 | I97: =IFERROR('Horizontal Analysis'!I30/'Horizontal Analysis'!I$41,"") -> 0.047423658 | J97: =IFERROR('Horizontal Analysis'!J30/'Horizontal Analysis'!J$41,"") -> 0.070569417 | ... Q97: =IFERROR('Horizontal Analysis'!Q30/'Horizontal Analysis'!Q$41,"") -> 0.092361395
A98: Other Current Assets | B98: =IFERROR(B31/B$41,"") -> 0.045848131 | C98: =IFERROR('Horizontal Analysis'!C31/'Horizontal Analysis'!C$41,"") -> 0.038918631 | D98: =IFERROR('Horizontal Analysis'!D31/'Horizontal Analysis'!D$41,"") -> 0.036679844 | E98: =IFERROR('Horizontal Analysis'!E31/'Horizontal Analysis'!E$41,"") -> 0.033246377 | F98: =IFERROR('Horizontal Analysis'!F31/'Horizontal Analysis'!F$41,"") -> 0.042296594 | G98: =IFERROR('Horizontal Analysis'!G31/'Horizontal Analysis'!G$41,"") -> 0.032838863 | H98: =IFERROR('Horizontal Analysis'!H31/'Horizontal Analysis'!H$41,"") -> 0.025748711 | I98: =IFERROR('Horizontal Analysis'!I31/'Horizontal Analysis'!I$41,"") -> 0.03713108 | J98: =IFERROR('Horizontal Analysis'!J31/'Horizontal Analysis'!J$41,"") -> 0.033049422 | ... Q98: =IFERROR('Horizontal Analysis'!Q31/'Horizontal Analysis'!Q$41,"") -> 0.040599486
A99: Total Current Assets | B99: =IFERROR(B32/B$41,"") -> 0.55435404 | C99: =IFERROR('Horizontal Analysis'!C32/'Horizontal Analysis'!C$41,"") -> 0.38659116 | D99: =IFERROR('Horizontal Analysis'!D32/'Horizontal Analysis'!D$41,"") -> 0.32745479 | E99: =IFERROR('Horizontal Analysis'!E32/'Horizontal Analysis'!E$41,"") -> 0.35403865 | F99: =IFERROR('Horizontal Analysis'!F32/'Horizontal Analysis'!F$41,"") -> 0.29559738 | G99: =IFERROR('Horizontal Analysis'!G32/'Horizontal Analysis'!G$41,"") -> 0.30769178 | H99: =IFERROR('Horizontal Analysis'!H32/'Horizontal Analysis'!H$41,"") -> 0.33221527 | I99: =IFERROR('Horizontal Analysis'!I32/'Horizontal Analysis'!I$41,"") -> 0.34276176 | J99: =IFERROR('Horizontal Analysis'!J32/'Horizontal Analysis'!J$41,"") -> 0.35911956 | ... Q99: =IFERROR('Horizontal Analysis'!Q32/'Horizontal Analysis'!Q$41,"") -> 0.41186
A101: Property, Plant & Equipment, Net | B101: =IFERROR(B34/B$41,"") -> 0.063418592 | C101: =IFERROR('Horizontal Analysis'!C34/'Horizontal Analysis'!C$41,"") -> 0.066829365 | D101: =IFERROR('Horizontal Analysis'!D34/'Horizontal Analysis'!D$41,"") -> 0.087763541 | E101: =IFERROR('Horizontal Analysis'!E34/'Horizontal Analysis'!E$41,"") -> 0.080178744 | F101: =IFERROR('Horizontal Analysis'!F34/'Horizontal Analysis'!F$41,"") -> 0.088958286 | G101: =IFERROR('Horizontal Analysis'!G34/'Horizontal Analysis'!G$41,"") -> 0.077358432 | H101: =IFERROR('Horizontal Analysis'!H34/'Horizontal Analysis'!H$41,"") -> 0.083963865 | I101: =IFERROR('Horizontal Analysis'!I34/'Horizontal Analysis'!I$41,"") -> 0.09001143 | J101: =IFERROR('Horizontal Analysis'!J34/'Horizontal Analysis'!J$41,"") -> 0.11293732 | ... Q101: =IFERROR('Horizontal Analysis'!Q34/'Horizontal Analysis'!Q$41,"") -> 0.13872025
A102: Long-Term Marketable Securities | B102: =IFERROR(B35/B$41,"") -> 0.33772262 | C102: =IFERROR('Horizontal Analysis'!C35/'Horizontal Analysis'!C$41,"") -> 0.47793694 | D102: =IFERROR('Horizontal Analysis'!D35/'Horizontal Analysis'!D$41,"") -> 0.52323019 | E102: =IFERROR('Horizontal Analysis'!E35/'Horizontal Analysis'!E$41,"") -> 0.51311594 | F102: =IFERROR('Horizontal Analysis'!F35/'Horizontal Analysis'!F$41,"") -> 0.56143272 | G102: =IFERROR('Horizontal Analysis'!G35/'Horizontal Analysis'!G$41,"") -> 0.56480847 | H102: =IFERROR('Horizontal Analysis'!H35/'Horizontal Analysis'!H$41,"") -> 0.52980235 | I102: =IFERROR('Horizontal Analysis'!I35/'Horizontal Analysis'!I$41,"") -> 0.51879601 | J102: =IFERROR('Horizontal Analysis'!J35/'Horizontal Analysis'!J$41,"") -> 0.46701483 | ... Q102: =IFERROR('Horizontal Analysis'!Q35/'Horizontal Analysis'!Q$41,"") -> 0.21635337
A103: Goodwill | B103: =IFERROR(B36/B$41,"") -> 0.0098559515 | C103: =IFERROR('Horizontal Analysis'!C36/'Horizontal Analysis'!C$41,"") -> 0.0076995128 | D103: =IFERROR('Horizontal Analysis'!D36/'Horizontal Analysis'!D$41,"") -> 0.0064465194 | E103: =IFERROR('Horizontal Analysis'!E36/'Horizontal Analysis'!E$41,"") -> 0.0076183575 | F103: =IFERROR('Horizontal Analysis'!F36/'Horizontal Analysis'!F$41,"") -> 0.019910369 | G103: =IFERROR('Horizontal Analysis'!G36/'Horizontal Analysis'!G$41,"") -> 0.017612289 | H103: =IFERROR('Horizontal Analysis'!H36/'Horizontal Analysis'!H$41,"") -> 0.016830077 | I103: =IFERROR('Horizontal Analysis'!I36/'Horizontal Analysis'!I$41,"") -> 0.015232376 | J103: =IFERROR('Horizontal Analysis'!J36/'Horizontal Analysis'!J$41,"") -> 0 | ... Q103: =IFERROR('Horizontal Analysis'!Q36/'Horizontal Analysis'!Q$41,"") -> 0
A104: Acquired Intangible Assets, Net | B104: =IFERROR(B37/B$41,"") -> 0.0045489007 | C104: =IFERROR('Horizontal Analysis'!C37/'Horizontal Analysis'!C$41,"") -> 0.030385577 | D104: =IFERROR('Horizontal Analysis'!D37/'Horizontal Analysis'!D$41,"") -> 0.023991276 | E104: =IFERROR('Horizontal Analysis'!E37/'Horizontal Analysis'!E$41,"") -> 0.020188406 | F104: =IFERROR('Horizontal Analysis'!F37/'Horizontal Analysis'!F$41,"") -> 0.017865847 | G104: =IFERROR('Horizontal Analysis'!G37/'Horizontal Analysis'!G$41,"") -> 0.013402002 | H104: =IFERROR('Horizontal Analysis'!H37/'Horizontal Analysis'!H$41,"") -> 0.0099662404 | I104: =IFERROR('Horizontal Analysis'!I37/'Horizontal Analysis'!I$41,"") -> 0.0061227915 | J104: =IFERROR('Horizontal Analysis'!J37/'Horizontal Analysis'!J$41,"") -> 0 | ... Q104: =IFERROR('Horizontal Analysis'!Q37/'Horizontal Analysis'!Q$41,"") -> 0
... A130: Total Liabilities & Shareholders' Equity | B130: =IFERROR(B63/B$41,"") -> 1 | C130: =IFERROR('Horizontal Analysis'!C63/'Horizontal Analysis'!C$41,"") -> 1 | D130: =IFERROR('Horizontal Analysis'!D63/'Horizontal Analysis'!D$41,"") -> 1 | E130: =IFERROR('Horizontal Analysis'!E63/'Horizontal Analysis'!E$41,"") -> 1 | F130: =IFERROR('Horizontal Analysis'!F63/'Horizontal Analysis'!F$41,"") -> 1 | G130: =IFERROR('Horizontal Analysis'!G63/'Horizontal Analysis'!G$41,"") -> 1 | H130: =IFERROR('Horizontal Analysis'!H63/'Horizontal Analysis'!H$41,"") -> 1 | I130: =IFERROR('Horizontal Analysis'!I63/'Horizontal Analysis'!I$41,"") -> 1 | J130: =IFERROR('Horizontal Analysis'!J63/'Horizontal Analysis'!J$41,"") -> 1 | ... Q130: =IFERROR('Horizontal Analysis'!Q63/'Horizontal Analysis'!Q$41,"") -> 1
A132: Methodology
A133: Income statement ÷ same-year revenue; balance sheet ÷ same-year total assets.

Sheet Horizontal Analysis
A2: Fiscal Year | B2: 2010 | C2: 2011 | D2: 2012 | E2: 2013 | F2: 2014 | G2: 2015 | H2: 2016 | I2: 2017 | J2: 2018 | K2: 2019 | L2: 2020 | M2: 2021 | N2: 2022 | O2: 2023 | P2: 2024 | Q2: 2025
A4: INCOME STATEMENT
A5: Net Sales / Revenue | B5: 65225 | C5: 108249 | D5: 156508 | E5: 170910 | F5: 182795 | G5: 233715 | H5: 215639 | I5: 229234 | J5: 265595 | K5: 260174 | L5: 274515 | M5: 365817 | N5: 394328 | O5: 383285 | P5: 391035 | Q5: 416161
A6: Total COGS | B6: 39541 | C6: 64431 | D6: 87846 | E6: 106606 | F6: 112258 | G6: 140089 | H6: 131376 | I6: 141048 | J6: 163756 | K6: 161782 | L6: 169559 | M6: 212981 | N6: 223546 | O6: 214137 | P6: 210352 | Q6: 220960
A7: Gross Profit | B7: =B5-B6 -> 25684 | C7: =C5-C6 -> 43818 | D7: =D5-D6 -> 68662 | E7: =E5-E6 -> 64304 | F7: =F5-F6 -> 70537 | G7: =G5-G6 -> 93626 | H7: =H5-H6 -> 84263 | I7: =I5-I6 -> 88186 | ... Q7: =Q5-Q6 -> 195201
A9: Research & Development | B9: 1782 | C9: 2429 | D9: 3381 | E9: 4475 | F9: 6041 | G9: 8067 | H9: 10045 | I9: 11581 | J9: 14236 | K9: 16217 | L9: 18752 | M9: 21914 | N9: 26251 | O9: 29915 | P9: 31370 | Q9: 34550
A10: Selling, General & Administrative | B10: 5517 | C10: 7599 | D10: 10040 | E10: 10830 | F10: 11993 | G10: 14329 | H10: 14194 | I10: 15261 | J10: 16705 | K10: 18245 | L10: 19916 | M10: 21973 | N10: 25094 | O10: 24932 | P10: 26097 | Q10: 27601
A11: Total Operating Expenses | B11: =B9+B10 -> 7299 | C11: =C9+C10 -> 10028 | D11: =D9+D10 -> 13421 | E11: =E9+E10 -> 15305 | F11: =F9+F10 -> 18034 | G11: =G9+G10 -> 22396 | H11: =H9+H10 -> 24239 | I11: =I9+I10 -> 26842 | ... Q11: =Q9+Q10 -> 62151
A12: Operating Income (EBIT) | B12: =B7-B11 -> 18385 | C12: =C7-C11 -> 33790 | D12: =D7-D11 -> 55241 | E12: =E7-E11 -> 48999 | F12: =F7-F11 -> 52503 | G12: =G7-G11 -> 71230 | H12: =H7-H11 -> 60024 | I12: =I7-I11 -> 61344 | ... Q12: =Q7-Q11 -> 133050
A13: % Growth | B13: =IFERROR(B12/#REF!-1,"") | C13: =IFERROR(C12/B12-1,"") -> 0.83791134 | D13: =IFERROR(D12/C12-1,"") -> 0.63483279 | E13: =IFERROR(E12/D12-1,"") -> -0.11299578 | F13: =IFERROR(F12/E12-1,"") -> 0.071511664 | G13: =IFERROR(G12/F12-1,"") -> 0.35668438 | H13: =IFERROR(H12/G12-1,"") -> -0.15732135 | I13: =IFERROR(I12/H12-1,"") -> 0.021991204 | J13: =IFERROR(J12/I12-1,"") -> 0.15574465 | ... Q13: =IFERROR(Q12/P12-1,"") -> 0.079811063
A15: Other Income/(Expense), Net | B15: 155 | C15: 415 | D15: 522 | E15: 1156 | F15: 980 | G15: 1285 | H15: 1348 | I15: 2745 | J15: 2005 | K15: 1807 | L15: 803 | M15: 258 | N15: -334 | O15: -565 | P15: 269 | Q15: -321
A16: Total Other Income/(Expense) | B16: =B15 -> 155 | C16: =C15 -> 415 | D16: =D15 -> 522 | E16: =E15 -> 1156 | F16: =F15 -> 980 | G16: =G15 -> 1285 | H16: =H15 -> 1348 | I16: =I15 -> 2745 | ... Q16: =Q15 -> -321
A19: Income Before Income Taxes | B19: =B12+B16 -> 18540 | C19: =C12+C16 -> 34205 | D19: =D12+D16 -> 55763 | E19: =E12+E16 -> 50155 | F19: =F12+F16 -> 53483 | G19: =G12+G16 -> 72515 | H19: =H12+H16 -> 61372 | I19: =I12+I16 -> 64089 | ... Q19: =Q12+Q16 -> 132729
A20: Provision for Income Taxes | B20: 4527 | C20: 8283 | D20: 14030 | E20: 13118 | F20: 13973 | G20: 19121 | H20: 15685 | I20: 15738 | J20: 13372 | K20: 10481 | L20: 9680 | M20: 14527 | N20: 19300 | O20: 16741 | P20: 29749 | Q20: 20719
A21: Net Income | B21: =B19-B20 -> 14013 | C21: =C19-C20 -> 25922 | D21: =D19-D20 -> 41733 | E21: =E19-E20 -> 37037 | F21: =F19-F20 -> 39510 | G21: =G19-G20 -> 53394 | H21: =H19-H20 -> 45687 | I21: =I19-I20 -> 48351 | ... Q21: =Q19-Q20 -> 112010
A24: BALANCE SHEET
A25: Cash & Cash Equivalents (FY1992 source reports Cash + ST Investments combined) | B25: 11261 | C25: 9815 | D25: 10746 | E25: 14259 | F25: 13844 | G25: 21120 | H25: 20484 | I25: 20289 | J25: 25913 | K25: 48844 | L25: 38016 | M25: 34940 | N25: 23646 | O25: 29965 | P25: 29943 | Q25: 35934
A26: Short-Term Investments / Marketable Securities | B26: 14359 | C26: 16137 | D26: 18383 | E26: 26287 | F26: 11233 | G26: 20481 | H26: 46671 | I26: 53892 | J26: 40388 | K26: 51713 | L26: 52927 | M26: 27699 | N26: 24658 | O26: 31590 | P26: 35228 | Q26: 18763
A27: Accounts Receivable, Net | B27: 5510 | C27: 5369 | D27: 10930 | E27: 13102 | F27: 17460 | G27: 16849 | H27: 15754 | I27: 17874 | J27: 23186 | K27: 22926 | L27: 16120 | M27: 26278 | N27: 28184 | O27: 29508 | P27: 33410 | Q27: 39777
A28: Inventories | B28: 1051 | C28: 776 | D28: 791 | E28: 1764 | F28: 2111 | G28: 2349 | H28: 2132 | I28: 4855 | J28: 3956 | K28: 4106 | L28: 4061 | M28: 6580 | N28: 4946 | O28: 6331 | P28: 7286 | Q28: 5718
A29: Deferred Tax Assets | B29: 1636 | C29: 2014 | D29: 2583 | E29: 3453 | F29: 4318 | G29: 5546 | H29: 0 | I29: 0 | J29: 0 | K29: 0 | L29: 0 | M29: 0 | N29: 0 | O29: 0 | P29: 0 | Q29: 0
A30: Vendor Non-Trade Receivables | B30: 4414 | C30: 6348 | D30: 7762 | E30: 7539 | F30: 9759 | G30: 13494 | H30: 13545 | I30: 17799 | J30: 25809 | K30: 22878 | L30: 21325 | M30: 25228 | N30: 32748 | O30: 31477 | P30: 32833 | Q30: 33180
A31: Other Current Assets | B31: 3447 | C31: 4529 | D31: 6458 | E31: 6882 | F31: 9806 | G31: 9539 | H31: 8283 | I31: 13936 | J31: 12087 | K31: 12352 | L31: 11264 | M31: 14111 | N31: 21223 | O31: 14695 | P31: 14287 | Q31: 14585
A32: Total Current Assets | B32: =B25+B26+B27+B28+B29+B30+B31 -> 41678 | C32: =C25+C26+C27+C28+C29+C30+C31 -> 44988 | D32: =D25+D26+D27+D28+D29+D30+D31 -> 57653 | E32: =E25+E26+E27+E28+E29+E30+E31 -> 73286 | F32: =F25+F26+F27+F28+F29+F30+F31 -> 68531 | G32: =G25+G26+G27+G28+G29+G30+G31 -> 89378 | H32: =H25+H26+H27+H28+H29+H30+H31 -> 106869 | I32: =I25+I26+I27+I28+I29+I30+I31 -> 128645 | ... Q32: =Q25+Q26+Q27+Q28+Q29+Q30+Q31 -> 147957
A34: Property, Plant & Equipment, Net | B34: 4768 | C34: 7777 | D34: 15452 | E34: 16597 | F34: 20624 | G34: 22471 | H34: 27010 | I34: 33783 | J34: 41304 | K34: 37378 | L34: 36766 | M34: 39440 | N34: 42117 | O34: 43715 | P34: 45680 | Q34: 49834
A35: Long-Term Marketable Securities | B35: 25391 | C35: 55618 | D35: 92122 | E35: 106215 | F35: 130162 | G35: 164065 | H35: 170430 | I35: 194714 | J35: 170799 | K35: 105341 | L35: 100887 | M35: 127877 | N35: 120805 | O35: 100544 | P35: 91479 | Q35: 77723
A36: Goodwill | B36: 741 | C36: 896 | D36: 1135 | E36: 1577 | F36: 4616 | G36: 5116 | H36: 5414 | I36: 5717 | J36: 0 | K36: 0 | L36: 0 | M36: 0 | N36: 0 | O36: 0 | P36: 0 | Q36: 0
A37: Acquired Intangible Assets, Net | B37: 342 | C37: 3536 | D37: 4224 | E37: 4179 | F37: 4142 | G37: 3893 | H37: 3206 | I37: 2298 | J37: 0 | K37: 0 | L37: 0 | M37: 0 | N37: 0 | O37: 0 | P37: 0 | Q37: 0
A38: Other Assets (legacy) | B38: 2263 | C38: 3556 | D38: 5478 | E38: 5146 | F38: 3764 | G38: 5556 | H38: 8757 | I38: 10162 | J38: 0 | K38: 0 | L38: 0 | M38: 0 | N38: 0 | O38: 0 | P38: 0 | Q38: 0
A39: Other Non-Current Assets | B39: 0 | C39: 0 | D39: 0 | E39: 0 | F39: 0 | G39: 0 | H39: 0 | I39: 0 | J39: 22283 | K39: 32978 | L39: 42522 | M39: 48849 | N39: 54428 | O39: 64758 | P39: 74834 | Q39: 83727
A40: Total Non-Current Assets | B40: =B34+B35+B36+B37+B38+B39 -> 33505 | C40: =C34+C35+C36+C37+C38+C39 -> 71383 | D40: =D34+D35+D36+D37+D38+D39 -> 118411 | E40: =E34+E35+E36+E37+E38+E39 -> 133714 | F40: =F34+F35+F36+F37+F38+F39 -> 163308 | G40: =G34+G35+G36+G37+G38+G39 -> 201101 | H40: =H34+H35+H36+H37+H38+H39 -> 214817 | I40: =I34+I35+I36+I37+I38+I39 -> 246674 | ... Q40: =Q34+Q35+Q36+Q37+Q38+Q39 -> 211284
A41: Total Assets | B41: =B32+B40 -> 75183 | C41: =C32+C40 -> 116371 | D41: =D32+D40 -> 176064 | E41: =E32+E40 -> 207000 | F41: =F32+F40 -> 231839 | G41: =G32+G40 -> 290479 | H41: =H32+H40 -> 321686 | I41: =I32+I40 -> 375319 | ... Q41: =Q32+Q40 -> 359241
A43: Short-Term Borrowings / Notes Payable | B43: 0 | C43: 0 | D43: 0 | E43: 0 | F43: 0 | G43: 0 | H43: 0 | I43: 0 | J43: 0 | K43: 0 | L43: 0 | M43: 0 | N43: 0 | O43: 0 | P43: 0 | Q43: 0
A44: Accounts Payable | B44: 12015 | C44: 14632 | D44: 21175 | E44: 22367 | F44: 30196 | G44: 35490 | H44: 37294 | I44: 49049 | J44: 55888 | K44: 46236 | L44: 42296 | M44: 54763 | N44: 64115 | O44: 62611 | P44: 68960 | Q44: 69860
A45: Accrued Expenses | B45: 5723 | C45: 9247 | D45: 11414 | E45: 13856 | F45: 18453 | G45: 25181 | H45: 22027 | I45: 25744 | J45: 0 | K45: 0 | L45: 0 | M45: 0 | N45: 0 | O45: 0 | P45: 0 | Q45: 0
A46: Deferred Revenue - Current | B46: 2984 | C46: 4091 | D46: 5953 | E46: 7435 | F46: 8491 | G46: 8940 | H46: 8080 | I46: 7548 | J46: 7543 | K46: 5522 | L46: 6643 | M46: 7612 | N46: 7912 | O46: 8061 | P46: 8249 | Q46: 9055
A47: Other Current Liabilities | B47: 0 | C47: 0 | D47: 0 | E47: 0 | F47: 0 | G47: 0 | H47: 0 | I47: 0 | J47: 32687 | K47: 37720 | L47: 42684 | M47: 47493 | N47: 60845 | O47: 58829 | P47: 78304 | Q47: 66387
A48: Commercial Paper | B48: 0 | C48: 0 | D48: 0 | E48: 0 | F48: 6308 | G48: 8499 | H48: 8105 | I48: 11977 | J48: 11964 | K48: 5980 | L48: 4996 | M48: 6000 | N48: 9982 | O48: 5985 | P48: 9967 | Q48: 7979
A49: Current Debt / Term Debt | B49: 0 | C49: 0 | D49: 0 | E49: 0 | F49: 0 | G49: 2500 | H49: 3500 | I49: 6496 | J49: 8784 | K49: 10260 | L49: 8773 | M49: 9613 | N49: 11128 | O49: 9822 | P49: 10912 | Q49: 12350
A50: Total Current Liabilities | B50: =SUM(B43:B49) -> 20722 | C50: =SUM(C43:C49) -> 27970 | D50: =SUM(D43:D49) -> 38542 | E50: =SUM(E43:E49) -> 43658 | F50: =SUM(F43:F49) -> 63448 | G50: =SUM(G43:G49) -> 80610 | H50: =SUM(H43:H49) -> 79006 | I50: =SUM(I43:I49) -> 100814 | ... Q50: =SUM(Q43:Q49) -> 165631
A52: Long-Term Debt / Term Debt | B52: 0 | C52: 0 | D52: 0 | E52: 16960 | F52: 28987 | G52: 53463 | H52: 75427 | I52: 97207 | J52: 93735 | K52: 91807 | L52: 98667 | M52: 109106 | N52: 98959 | O52: 95281 | P52: 85750 | Q52: 78328
A53: Deferred Revenue - Non-Current | B53: 1139 | C53: 1686 | D53: 2648 | E53: 2625 | F53: 3031 | G53: 3624 | H53: 2930 | I53: 2836 | J53: 2797 | K53: 0 | L53: 0 | M53: 0 | N53: 0 | O53: 0 | P53: 0 | Q53: 0
A54: Other Non-Current Liabilities | B54: 5531 | C54: 10100 | D54: 16664 | E54: 20208 | F54: 24826 | G54: 33427 | H54: 36074 | I54: 40415 | J54: 45180 | K54: 50503 | L54: 54490 | M54: 53325 | N54: 49142 | O54: 49848 | P54: 45888 | Q54: 41549
A55: Total Non-Current Liabilities | B55: =SUM(B52:B54) -> 6670 | C55: =SUM(C52:C54) -> 11786 | D55: =SUM(D52:D54) -> 19312 | E55: =SUM(E52:E54) -> 39793 | F55: =SUM(F52:F54) -> 56844 | G55: =SUM(G52:G54) -> 90514 | H55: =SUM(H52:H54) -> 114431 | I55: =SUM(I52:I54) -> 140458 | ... Q55: =SUM(Q52:Q54) -> 119877
A56: Total Liabilities | B56: =B50+B55 -> 27392 | C56: =C50+C55 -> 39756 | D56: =D50+D55 -> 57854 | E56: =E50+E55 -> 83451 | F56: =F50+F55 -> 120292 | G56: =G50+G55 -> 171124 | H56: =H50+H55 -> 193437 | I56: =I50+I55 -> 241272 | ... Q56: =Q50+Q55 -> 285508
A58: Common Stock & Additional Paid-In Capital | B58: 10668 | C58: 13331 | D58: 16422 | E58: 19764 | F58: 23313 | G58: 27416 | H58: 31251 | I58: 35867 | J58: 40201 | K58: 45174 | L58: 50779 | M58: 57365 | N58: 64849 | O58: 73812 | P58: 83276 | Q58: 93568
A59: Retained Earnings | B59: 37169 | C59: 62841 | D59: 101289 | E59: 104256 | F59: 87152 | G59: 92284 | H59: 96364 | I59: 98330 | J59: 70400 | K59: 45898 | L59: 14966 | M59: 5562 | N59: 0 | O59: 0 | P59: 0 | Q59: 0
A60: Accumulated Deficit | B60: 0 | C60: 0 | D60: 0 | E60: 0 | F60: 0 | G60: 0 | H60: 0 | I60: 0 | J60: 0 | K60: 0 | L60: 0 | M60: 0 | N60: -3068 | O60: -214 | P60: -19154 | Q60: -14264
A61: Accumulated Other Comprehensive Income/(Loss) | B61: -46 | C61: 443 | D61: 499 | E61: -471 | F61: 1082 | G61: -345 | H61: 634 | I61: -150 | J61: -3454 | K61: -584 | L61: -406 | M61: 163 | N61: -11109 | O61: -11452 | P61: -7172 | Q61: -5571
A62: Total Shareholders' Equity | B62: =SUM(B58:B61) -> 47791 | C62: =SUM(C58:C61) -> 76615 | D62: =SUM(D58:D61) -> 118210 | E62: =SUM(E58:E61) -> 123549 | F62: =SUM(F58:F61) -> 111547 | G62: =SUM(G58:G61) -> 119355 | H62: =SUM(H58:H61) -> 128249 | I62: =SUM(I58:I61) -> 134047 | ... Q62: =SUM(Q58:Q61) -> 73733
A63: Total Liabilities & Shareholders' Equity | B63: =B56+B62 -> 75183 | C63: =C56+C62 -> 116371 | D63: =D56+D62 -> 176064 | E63: =E56+E62 -> 207000 | F63: =F56+F62 -> 231839 | G63: =G56+G62 -> 290479 | H63: =H56+H62 -> 321686 | I63: =I56+I62 -> 375319 | ... Q63: =Q56+Q62 -> 359241
A67: HORIZONTAL ANALYSIS — APPLE INC. (FY2010–FY2025)
A68: All ratios calculated from the original financial statements above; original data unchanged.
A70: Financial statement line item | B70: 2010 | C70: 2011 | D70: 2012 | E70: 2013 | F70: 2014 | G70: 2015 | H70: 2016 | I70: 2017 | J70: 2018 | K70: 2019 | L70: 2020 | M70: 2021 | N70: 2022 | O70: 2023 | P70: 2024 | Q70: 2025
A71: INCOME STATEMENT
A72: Net Sales / Revenue | B72: ="" | C72: =IFERROR(IF(B5=0,"",(C5-B5)/ABS(B5)),"") -> 0.65962438 | D72: =IFERROR(IF(C5=0,"",(D5-C5)/ABS(C5)),"") -> 0.44581474 | E72: =IFERROR(IF(D5=0,"",(E5-D5)/ABS(D5)),"") -> 0.092020855 | F72: =IFERROR(IF(E5=0,"",(F5-E5)/ABS(E5)),"") -> 0.069539524 | G72: =IFERROR(IF(F5=0,"",(G5-F5)/ABS(F5)),"") -> 0.27856342 | H72: =IFERROR(IF(G5=0,"",(H5-G5)/ABS(G5)),"") -> -0.077342062 | I72: =IFERROR(IF(H5=0,"",(I5-H5)/ABS(H5)),"") -> 0.063045182 | J72: =IFERROR(IF(I5=0,"",(J5-I5)/ABS(I5)),"") -> 0.15861958 | ... Q72: =IFERROR(IF(P5=0,"",(Q5-P5)/ABS(P5)),"") -> 0.064255118
A73: Total COGS | B73: ="" | C73: =IFERROR(IF(B6=0,"",(C6-B6)/ABS(B6)),"") -> 0.62947321 | D73: =IFERROR(IF(C6=0,"",(D6-C6)/ABS(C6)),"") -> 0.36341202 | E73: =IFERROR(IF(D6=0,"",(E6-D6)/ABS(D6)),"") -> 0.21355554 | F73: =IFERROR(IF(E6=0,"",(F6-E6)/ABS(E6)),"") -> 0.053017654 | G73: =IFERROR(IF(F6=0,"",(G6-F6)/ABS(F6)),"") -> 0.24791997 | H73: =IFERROR(IF(G6=0,"",(H6-G6)/ABS(G6)),"") -> -0.062196175 | I73: =IFERROR(IF(H6=0,"",(I6-H6)/ABS(H6)),"") -> 0.073620753 | J73: =IFERROR(IF(I6=0,"",(J6-I6)/ABS(I6)),"") -> 0.16099484 | ... Q73: =IFERROR(IF(P6=0,"",(Q6-P6)/ABS(P6)),"") -> 0.050429756
A74: Gross Profit | B74: ="" | C74: =IFERROR(IF(B7=0,"",(C7-B7)/ABS(B7)),"") -> 0.70604267 | D74: =IFERROR(IF(C7=0,"",(D7-C7)/ABS(C7)),"") -> 0.56698161 | E74: =IFERROR(IF(D7=0,"",(E7-D7)/ABS(D7)),"") -> -0.063470333 | F74: =IFERROR(IF(E7=0,"",(F7-E7)/ABS(E7)),"") -> 0.096930207 | G74: =IFERROR(IF(F7=0,"",(G7-F7)/ABS(F7)),"") -> 0.32733175 | H74: =IFERROR(IF(G7=0,"",(H7-G7)/ABS(G7)),"") -> -0.10000427 | I74: =IFERROR(IF(H7=0,"",(I7-H7)/ABS(H7)),"") -> 0.046556614 | J74: =IFERROR(IF(I7=0,"",(J7-I7)/ABS(I7)),"") -> 0.15482049 | ... Q74: =IFERROR(IF(P7=0,"",(Q7-P7)/ABS(P7)),"") -> 0.080350669
A76: Research & Development | B76: ="" | C76: =IFERROR(IF(B9=0,"",(C9-B9)/ABS(B9)),"") -> 0.3630752 | D76: =IFERROR(IF(C9=0,"",(D9-C9)/ABS(C9)),"") -> 0.39193084 | E76: =IFERROR(IF(D9=0,"",(E9-D9)/ABS(D9)),"") -> 0.32357291 | F76: =IFERROR(IF(E9=0,"",(F9-E9)/ABS(E9)),"") -> 0.34994413 | G76: =IFERROR(IF(F9=0,"",(G9-F9)/ABS(F9)),"") -> 0.33537494 | H76: =IFERROR(IF(G9=0,"",(H9-G9)/ABS(G9)),"") -> 0.24519648 | I76: =IFERROR(IF(H9=0,"",(I9-H9)/ABS(H9)),"") -> 0.1529119 | J76: =IFERROR(IF(I9=0,"",(J9-I9)/ABS(I9)),"") -> 0.22925481 | ... Q76: =IFERROR(IF(P9=0,"",(Q9-P9)/ABS(P9)),"") -> 0.10137074
A77: Selling, General & Administrative | B77: ="" | C77: =IFERROR(IF(B10=0,"",(C10-B10)/ABS(B10)),"") -> 0.37737901 | D77: =IFERROR(IF(C10=0,"",(D10-C10)/ABS(C10)),"") -> 0.32122648 | E77: =IFERROR(IF(D10=0,"",(E10-D10)/ABS(D10)),"") -> 0.078685259 | F77: =IFERROR(IF(E10=0,"",(F10-E10)/ABS(E10)),"") -> 0.10738689 | G77: =IFERROR(IF(F10=0,"",(G10-F10)/ABS(F10)),"") -> 0.19478029 | H77: =IFERROR(IF(G10=0,"",(H10-G10)/ABS(G10)),"") -> -0.009421453 | I77: =IFERROR(IF(H10=0,"",(I10-H10)/ABS(H10)),"") -> 0.075172608 | J77: =IFERROR(IF(I10=0,"",(J10-I10)/ABS(I10)),"") -> 0.094620274 | ... Q77: =IFERROR(IF(P10=0,"",(Q10-P10)/ABS(P10)),"") -> 0.057631145
A78: Total Operating Expenses | B78: ="" | C78: =IFERROR(IF(B11=0,"",(C11-B11)/ABS(B11)),"") -> 0.37388683 | D78: =IFERROR(IF(C11=0,"",(D11-C11)/ABS(C11)),"") -> 0.33835261 | E78: =IFERROR(IF(D11=0,"",(E11-D11)/ABS(D11)),"") -> 0.14037702 | F78: =IFERROR(IF(E11=0,"",(F11-E11)/ABS(E11)),"") -> 0.17830774 | G78: =IFERROR(IF(F11=0,"",(G11-F11)/ABS(F11)),"") -> 0.24187646 | H78: =IFERROR(IF(G11=0,"",(H11-G11)/ABS(G11)),"") -> 0.082291481 | I78: =IFERROR(IF(H11=0,"",(I11-H11)/ABS(H11)),"") -> 0.10738892 | J78: =IFERROR(IF(I11=0,"",(J11-I11)/ABS(I11)),"") -> 0.15270844 | ... Q78: =IFERROR(IF(P11=0,"",(Q11-P11)/ABS(P11)),"") -> 0.081507648
A79: Operating Income (EBIT) | B79: ="" | C79: =IFERROR(IF(B12=0,"",(C12-B12)/ABS(B12)),"") -> 0.83791134 | D79: =IFERROR(IF(C12=0,"",(D12-C12)/ABS(C12)),"") -> 0.63483279 | E79: =IFERROR(IF(D12=0,"",(E12-D12)/ABS(D12)),"") -> -0.11299578 | F79: =IFERROR(IF(E12=0,"",(F12-E12)/ABS(E12)),"") -> 0.071511664 | G79: =IFERROR(IF(F12=0,"",(G12-F12)/ABS(F12)),"") -> 0.35668438 | H79: =IFERROR(IF(G12=0,"",(H12-G12)/ABS(G12)),"") -> -0.15732135 | I79: =IFERROR(IF(H12=0,"",(I12-H12)/ABS(H12)),"") -> 0.021991204 | J79: =IFERROR(IF(I12=0,"",(J12-I12)/ABS(I12)),"") -> 0.15574465 | ... Q79: =IFERROR(IF(P12=0,"",(Q12-P12)/ABS(P12)),"") -> 0.079811063
A82: Other Income/(Expense), Net | B82: ="" | C82: =IFERROR(IF(B15=0,"",(C15-B15)/ABS(B15)),"") -> 1.6774194 | D82: =IFERROR(IF(C15=0,"",(D15-C15)/ABS(C15)),"") -> 0.25783133 | E82: =IFERROR(IF(D15=0,"",(E15-D15)/ABS(D15)),"") -> 1.2145594 | F82: =IFERROR(IF(E15=0,"",(F15-E15)/ABS(E15)),"") -> -0.15224913 | G82: =IFERROR(IF(F15=0,"",(G15-F15)/ABS(F15)),"") -> 0.31122449 | H82: =IFERROR(IF(G15=0,"",(H15-G15)/ABS(G15)),"") -> 0.049027237 | I82: =IFERROR(IF(H15=0,"",(I15-H15)/ABS(H15)),"") -> 1.0363501 | J82: =IFERROR(IF(I15=0,"",(J15-I15)/ABS(I15)),"") -> -0.26958106 | ... Q82: =IFERROR(IF(P15=0,"",(Q15-P15)/ABS(P15)),"") -> -2.1933086
A83: Total Other Income/(Expense) | B83: ="" | C83: =IFERROR(IF(B16=0,"",(C16-B16)/ABS(B16)),"") -> 1.6774194 | D83: =IFERROR(IF(C16=0,"",(D16-C16)/ABS(C16)),"") -> 0.25783133 | E83: =IFERROR(IF(D16=0,"",(E16-D16)/ABS(D16)),"") -> 1.2145594 | F83: =IFERROR(IF(E16=0,"",(F16-E16)/ABS(E16)),"") -> -0.15224913 | G83: =IFERROR(IF(F16=0,"",(G16-F16)/ABS(F16)),"") -> 0.31122449 | H83: =IFERROR(IF(G16=0,"",(H16-G16)/ABS(G16)),"") -> 0.049027237 | I83: =IFERROR(IF(H16=0,"",(I16-H16)/ABS(H16)),"") -> 1.0363501 | J83: =IFERROR(IF(I16=0,"",(J16-I16)/ABS(I16)),"") -> -0.26958106 | ... Q83: =IFERROR(IF(P16=0,"",(Q16-P16)/ABS(P16)),"") -> -2.1933086
A86: Income Before Income Taxes | B86: ="" | C86: =IFERROR(IF(B19=0,"",(C19-B19)/ABS(B19)),"") -> 0.84492988 | D86: =IFERROR(IF(C19=0,"",(D19-C19)/ABS(C19)),"") -> 0.63025873 | E86: =IFERROR(IF(D19=0,"",(E19-D19)/ABS(D19)),"") -> -0.10056848 | F86: =IFERROR(IF(E19=0,"",(F19-E19)/ABS(E19)),"") -> 0.066354302 | G86: =IFERROR(IF(F19=0,"",(G19-F19)/ABS(F19)),"") -> 0.35585139 | H86: =IFERROR(IF(G19=0,"",(H19-G19)/ABS(G19)),"") -> -0.15366476 | I86: =IFERROR(IF(H19=0,"",(I19-H19)/ABS(H19)),"") -> 0.044271003 | J86: =IFERROR(IF(I19=0,"",(J19-I19)/ABS(I19)),"") -> 0.1375275 | ... Q86: =IFERROR(IF(P19=0,"",(Q19-P19)/ABS(P19)),"") -> 0.074859295
A87: Provision for Income Taxes | B87: ="" | C87: =IFERROR(IF(B20=0,"",(C20-B20)/ABS(B20)),"") -> 0.82968854 | D87: =IFERROR(IF(C20=0,"",(D20-C20)/ABS(C20)),"") -> 0.69383074 | E87: =IFERROR(IF(D20=0,"",(E20-D20)/ABS(D20)),"") -> -0.065003564 | F87: =IFERROR(IF(E20=0,"",(F20-E20)/ABS(E20)),"") -> 0.065177619 | G87: =IFERROR(IF(F20=0,"",(G20-F20)/ABS(F20)),"") -> 0.36842482 | H87: =IFERROR(IF(G20=0,"",(H20-G20)/ABS(G20)),"") -> -0.17969771 | I87: =IFERROR(IF(H20=0,"",(I20-H20)/ABS(H20)),"") -> 0.0033790245 | J87: =IFERROR(IF(I20=0,"",(J20-I20)/ABS(I20)),"") -> -0.15033676 | ... Q87: =IFERROR(IF(P20=0,"",(Q20-P20)/ABS(P20)),"") -> -0.30353961
A88: Net Income | B88: ="" | C88: =IFERROR(IF(B21=0,"",(C21-B21)/ABS(B21)),"") -> 0.84985371 | D88: =IFERROR(IF(C21=0,"",(D21-C21)/ABS(C21)),"") -> 0.60994522 | E88: =IFERROR(IF(D21=0,"",(E21-D21)/ABS(D21)),"") -> -0.11252486 | F88: =IFERROR(IF(E21=0,"",(F21-E21)/ABS(E21)),"") -> 0.066771067 | G88: =IFERROR(IF(F21=0,"",(G21-F21)/ABS(F21)),"") -> 0.35140471 | H88: =IFERROR(IF(G21=0,"",(H21-G21)/ABS(G21)),"") -> -0.14434206 | I88: =IFERROR(IF(H21=0,"",(I21-H21)/ABS(H21)),"") -> 0.058309804 | J88: =IFERROR(IF(I21=0,"",(J21-I21)/ABS(I21)),"") -> 0.23122583 | ... Q88: =IFERROR(IF(P21=0,"",(Q21-P21)/ABS(P21)),"") -> 0.19495178
A91: BALANCE SHEET
A92: Cash & Cash Equivalents (FY1992 source reports Cash + ST Investments combined) | B92: ="" | C92: =IFERROR(IF(B25=0,"",(C25-B25)/ABS(B25)),"") -> -0.12840778 | D92: =IFERROR(IF(C25=0,"",(D25-C25)/ABS(C25)),"") -> 0.094854814 | E92: =IFERROR(IF(D25=0,"",(E25-D25)/ABS(D25)),"") -> 0.32691234 | F92: =IFERROR(IF(E25=0,"",(F25-E25)/ABS(E25)),"") -> -0.029104425 | G92: =IFERROR(IF(F25=0,"",(G25-F25)/ABS(F25)),"") -> 0.52557064 | H92: =IFERROR(IF(G25=0,"",(H25-G25)/ABS(G25)),"") -> -0.030113636 | I92: =IFERROR(IF(H25=0,"",(I25-H25)/ABS(H25)),"") -> -0.0095196251 | J92: =IFERROR(IF(I25=0,"",(J25-I25)/ABS(I25)),"") -> 0.27719454 | ... Q92: =IFERROR(IF(P25=0,"",(Q25-P25)/ABS(P25)),"") -> 0.20008015
A93: Short-Term Investments / Marketable Securities | B93: ="" | C93: =IFERROR(IF(B26=0,"",(C26-B26)/ABS(B26)),"") -> 0.12382478 | D93: =IFERROR(IF(C26=0,"",(D26-C26)/ABS(C26)),"") -> 0.13918324 | E93: =IFERROR(IF(D26=0,"",(E26-D26)/ABS(D26)),"") -> 0.42996247 | F93: =IFERROR(IF(E26=0,"",(F26-E26)/ABS(E26)),"") -> -0.57267851 | G93: =IFERROR(IF(F26=0,"",(G26-F26)/ABS(F26)),"") -> 0.82328852 | H93: =IFERROR(IF(G26=0,"",(H26-G26)/ABS(G26)),"") -> 1.2787462 | I93: =IFERROR(IF(H26=0,"",(I26-H26)/ABS(H26)),"") -> 0.15472135 | J93: =IFERROR(IF(I26=0,"",(J26-I26)/ABS(I26)),"") -> -0.25057522 | ... Q93: =IFERROR(IF(P26=0,"",(Q26-P26)/ABS(P26)),"") -> -0.4673839
A94: Accounts Receivable, Net | B94: ="" | C94: =IFERROR(IF(B27=0,"",(C27-B27)/ABS(B27)),"") -> -0.025589837 | D94: =IFERROR(IF(C27=0,"",(D27-C27)/ABS(C27)),"") -> 1.0357608 | E94: =IFERROR(IF(D27=0,"",(E27-D27)/ABS(D27)),"") -> 0.19871912 | F94: =IFERROR(IF(E27=0,"",(F27-E27)/ABS(E27)),"") -> 0.33262097 | G94: =IFERROR(IF(F27=0,"",(G27-F27)/ABS(F27)),"") -> -0.034994273 | H94: =IFERROR(IF(G27=0,"",(H27-G27)/ABS(G27)),"") -> -0.06498902 | I94: =IFERROR(IF(H27=0,"",(I27-H27)/ABS(H27)),"") -> 0.134569 | J94: =IFERROR(IF(I27=0,"",(J27-I27)/ABS(I27)),"") -> 0.29719145 | ... Q94: =IFERROR(IF(P27=0,"",(Q27-P27)/ABS(P27)),"") -> 0.19057169
A95: Inventories | B95: ="" | C95: =IFERROR(IF(B28=0,"",(C28-B28)/ABS(B28)),"") -> -0.26165557 | D95: =IFERROR(IF(C28=0,"",(D28-C28)/ABS(C28)),"") -> 0.019329897 | E95: =IFERROR(IF(D28=0,"",(E28-D28)/ABS(D28)),"") -> 1.2300885 | F95: =IFERROR(IF(E28=0,"",(F28-E28)/ABS(E28)),"") -> 0.19671202 | G95: =IFERROR(IF(F28=0,"",(G28-F28)/ABS(F28)),"") -> 0.11274278 | H95: =IFERROR(IF(G28=0,"",(H28-G28)/ABS(G28)),"") -> -0.092379736 | I95: =IFERROR(IF(H28=0,"",(I28-H28)/ABS(H28)),"") -> 1.2772045 | J95: =IFERROR(IF(I28=0,"",(J28-I28)/ABS(I28)),"") -> -0.18516993 | ... Q95: =IFERROR(IF(P28=0,"",(Q28-P28)/ABS(P28)),"") -> -0.21520725
A96: Deferred Tax Assets | B96: ="" | C96: =IFERROR(IF(B29=0,"",(C29-B29)/ABS(B29)),"") -> 0.23105134 | D96: =IFERROR(IF(C29=0,"",(D29-C29)/ABS(C29)),"") -> 0.28252234 | E96: =IFERROR(IF(D29=0,"",(E29-D29)/ABS(D29)),"") -> 0.33681765 | F96: =IFERROR(IF(E29=0,"",(F29-E29)/ABS(E29)),"") -> 0.25050681 | G96: =IFERROR(IF(F29=0,"",(G29-F29)/ABS(F29)),"") -> 0.28439092 | H96: =IFERROR(IF(G29=0,"",(H29-G29)/ABS(G29)),"") -> -1 | I96: =IFERROR(IF(H29=0,"",(I29-H29)/ABS(H29)),"") | J96: =IFERROR(IF(I29=0,"",(J29-I29)/ABS(I29)),"") | ... Q96: =IFERROR(IF(P29=0,"",(Q29-P29)/ABS(P29)),"")
A97: Vendor Non-Trade Receivables | B97: ="" | C97: =IFERROR(IF(B30=0,"",(C30-B30)/ABS(B30)),"") -> 0.43815134 | D97: =IFERROR(IF(C30=0,"",(D30-C30)/ABS(C30)),"") -> 0.22274732 | E97: =IFERROR(IF(D30=0,"",(E30-D30)/ABS(D30)),"") -> -0.028729709 | F97: =IFERROR(IF(E30=0,"",(F30-E30)/ABS(E30)),"") -> 0.29446876 | G97: =IFERROR(IF(F30=0,"",(G30-F30)/ABS(F30)),"") -> 0.38272364 | H97: =IFERROR(IF(G30=0,"",(H30-G30)/ABS(G30)),"") -> 0.0037794575 | I97: =IFERROR(IF(H30=0,"",(I30-H30)/ABS(H30)),"") -> 0.31406423 | J97: =IFERROR(IF(I30=0,"",(J30-I30)/ABS(I30)),"") -> 0.45002528 | ... Q97: =IFERROR(IF(P30=0,"",(Q30-P30)/ABS(P30)),"") -> 0.010568635
A98: Other Current Assets | B98: ="" | C98: =IFERROR(IF(B31=0,"",(C31-B31)/ABS(B31)),"") -> 0.31389614 | D98: =IFERROR(IF(C31=0,"",(D31-C31)/ABS(C31)),"") -> 0.42592184 | E98: =IFERROR(IF(D31=0,"",(E31-D31)/ABS(D31)),"") -> 0.065655002 | F98: =IFERROR(IF(E31=0,"",(F31-E31)/ABS(E31)),"") -> 0.42487649 | G98: =IFERROR(IF(F31=0,"",(G31-F31)/ABS(F31)),"") -> -0.027228228 | H98: =IFERROR(IF(G31=0,"",(H31-G31)/ABS(G31)),"") -> -0.13166999 | I98: =IFERROR(IF(H31=0,"",(I31-H31)/ABS(H31)),"") -> 0.68248219 | J98: =IFERROR(IF(I31=0,"",(J31-I31)/ABS(I31)),"") -> -0.13267796 | ... Q98: =IFERROR(IF(P31=0,"",(Q31-P31)/ABS(P31)),"") -> 0.020858123
A99: Total Current Assets | B99: ="" | C99: =IFERROR(IF(B32=0,"",(C32-B32)/ABS(B32)),"") -> 0.079418398 | D99: =IFERROR(IF(C32=0,"",(D32-C32)/ABS(C32)),"") -> 0.28151952 | E99: =IFERROR(IF(D32=0,"",(E32-D32)/ABS(D32)),"") -> 0.27115675 | F99: =IFERROR(IF(E32=0,"",(F32-E32)/ABS(E32)),"") -> -0.064882788 | G99: =IFERROR(IF(F32=0,"",(G32-F32)/ABS(F32)),"") -> 0.3041981 | H99: =IFERROR(IF(G32=0,"",(H32-G32)/ABS(G32)),"") -> 0.19569693 | I99: =IFERROR(IF(H32=0,"",(I32-H32)/ABS(H32)),"") -> 0.20376349 | J99: =IFERROR(IF(I32=0,"",(J32-I32)/ABS(I32)),"") -> 0.02094135 | ... Q99: =IFERROR(IF(P32=0,"",(Q32-P32)/ABS(P32)),"") -> -0.032878611
A101: Property, Plant & Equipment, Net | B101: ="" | C101: =IFERROR(IF(B34=0,"",(C34-B34)/ABS(B34)),"") -> 0.63108221 | D101: =IFERROR(IF(C34=0,"",(D34-C34)/ABS(C34)),"") -> 0.9868844 | E101: =IFERROR(IF(D34=0,"",(E34-D34)/ABS(D34)),"") -> 0.07410044 | F101: =IFERROR(IF(E34=0,"",(F34-E34)/ABS(E34)),"") -> 0.24263421 | G101: =IFERROR(IF(F34=0,"",(G34-F34)/ABS(F34)),"") -> 0.089555857 | H101: =IFERROR(IF(G34=0,"",(H34-G34)/ABS(G34)),"") -> 0.20199368 | I101: =IFERROR(IF(H34=0,"",(I34-H34)/ABS(H34)),"") -> 0.25075898 | J101: =IFERROR(IF(I34=0,"",(J34-I34)/ABS(I34)),"") -> 0.22262676 | ... Q101: =IFERROR(IF(P34=0,"",(Q34-P34)/ABS(P34)),"") -> 0.090936953
A102: Long-Term Marketable Securities | B102: ="" | C102: =IFERROR(IF(B35=0,"",(C35-B35)/ABS(B35)),"") -> 1.1904612 | D102: =IFERROR(IF(C35=0,"",(D35-C35)/ABS(C35)),"") -> 0.65633428 | E102: =IFERROR(IF(D35=0,"",(E35-D35)/ABS(D35)),"") -> 0.15298192 | F102: =IFERROR(IF(E35=0,"",(F35-E35)/ABS(E35)),"") -> 0.2254578 | G102: =IFERROR(IF(F35=0,"",(G35-F35)/ABS(F35)),"") -> 0.26046772 | H102: =IFERROR(IF(G35=0,"",(H35-G35)/ABS(G35)),"") -> 0.038795599 | I102: =IFERROR(IF(H35=0,"",(I35-H35)/ABS(H35)),"") -> 0.14248665 | J102: =IFERROR(IF(I35=0,"",(J35-I35)/ABS(I35)),"") -> -0.12282116 | ... Q102: =IFERROR(IF(P35=0,"",(Q35-P35)/ABS(P35)),"") -> -0.15037331
A103: Goodwill | B103: ="" | C103: =IFERROR(IF(B36=0,"",(C36-B36)/ABS(B36)),"") -> 0.20917679 | D103: =IFERROR(IF(C36=0,"",(D36-C36)/ABS(C36)),"") -> 0.26674107 | E103: =IFERROR(IF(D36=0,"",(E36-D36)/ABS(D36)),"") -> 0.38942731 | F103: =IFERROR(IF(E36=0,"",(F36-E36)/ABS(E36)),"") -> 1.9270767 | G103: =IFERROR(IF(F36=0,"",(G36-F36)/ABS(F36)),"") -> 0.10831889 | H103: =IFERROR(IF(G36=0,"",(H36-G36)/ABS(G36)),"") -> 0.058248632 | I103: =IFERROR(IF(H36=0,"",(I36-H36)/ABS(H36)),"") -> 0.055966014 | J103: =IFERROR(IF(I36=0,"",(J36-I36)/ABS(I36)),"") -> -1 | ... Q103: =IFERROR(IF(P36=0,"",(Q36-P36)/ABS(P36)),"")
A104: Acquired Intangible Assets, Net | B104: ="" | C104: =IFERROR(IF(B37=0,"",(C37-B37)/ABS(B37)),"") -> 9.3391813 | D104: =IFERROR(IF(C37=0,"",(D37-C37)/ABS(C37)),"") -> 0.19457014 | E104: =IFERROR(IF(D37=0,"",(E37-D37)/ABS(D37)),"") -> -0.010653409 | F104: =IFERROR(IF(E37=0,"",(F37-E37)/ABS(E37)),"") -> -0.0088537928 | G104: =IFERROR(IF(F37=0,"",(G37-F37)/ABS(F37)),"") -> -0.060115886 | H104: =IFERROR(IF(G37=0,"",(H37-G37)/ABS(G37)),"") -> -0.17647059 | I104: =IFERROR(IF(H37=0,"",(I37-H37)/ABS(H37)),"") -> -0.28321896 | J104: =IFERROR(IF(I37=0,"",(J37-I37)/ABS(I37)),"") -> -1 | ... Q104: =IFERROR(IF(P37=0,"",(Q37-P37)/ABS(P37)),"")
... A130: Total Liabilities & Shareholders' Equity | B130: ="" | C130: =IFERROR(IF(B63=0,"",(C63-B63)/ABS(B63)),"") -> 0.54783661 | D130: =IFERROR(IF(C63=0,"",(D63-C63)/ABS(C63)),"") -> 0.51295426 | E130: =IFERROR(IF(D63=0,"",(E63-D63)/ABS(D63)),"") -> 0.17570883 | F130: =IFERROR(IF(E63=0,"",(F63-E63)/ABS(E63)),"") -> 0.11999517 | G130: =IFERROR(IF(F63=0,"",(G63-F63)/ABS(F63)),"") -> 0.25293415 | H130: =IFERROR(IF(G63=0,"",(H63-G63)/ABS(G63)),"") -> 0.1074329 | I130: =IFERROR(IF(H63=0,"",(I63-H63)/ABS(H63)),"") -> 0.16672469 | J130: =IFERROR(IF(I63=0,"",(J63-I63)/ABS(I63)),"") -> -0.025562255 | ... Q130: =IFERROR(IF(P63=0,"",(Q63-P63)/ABS(P63)),"") -> -0.015724149
A132: Methodology
A133: Year-over-year change ÷ absolute value of previous year's balance; 2010 has no prior year.

Sheet Common Size
A2: Fiscal Year | B2: 2010 | C2: 2011 | D2: 2012 | E2: 2013 | F2: 2014 | G2: 2015 | H2: 2016 | I2: 2017 | J2: 2018 | K2: 2019 | L2: 2020 | M2: 2021 | N2: 2022 | O2: 2023 | P2: 2024 | Q2: 2025
A4: INCOME STATEMENT
A5: Net Sales / Revenue | B5: 65225 | C5: 108249 | D5: 156508 | E5: 170910 | F5: 182795 | G5: 233715 | H5: 215639 | I5: 229234 | J5: 265595 | K5: 260174 | L5: 274515 | M5: 365817 | N5: 394328 | O5: 383285 | P5: 391035 | Q5: 416161
A6: Total COGS | B6: 39541 | C6: 64431 | D6: 87846 | E6: 106606 | F6: 112258 | G6: 140089 | H6: 131376 | I6: 141048 | J6: 163756 | K6: 161782 | L6: 169559 | M6: 212981 | N6: 223546 | O6: 214137 | P6: 210352 | Q6: 220960
A7: Gross Profit | B7: =B5-B6 -> 25684 | C7: =C5-C6 -> 43818 | D7: =D5-D6 -> 68662 | E7: =E5-E6 -> 64304 | F7: =F5-F6 -> 70537 | G7: =G5-G6 -> 93626 | H7: =H5-H6 -> 84263 | I7: =I5-I6 -> 88186 | ... Q7: =Q5-Q6 -> 195201
A9: Research & Development | B9: 1782 | C9: 2429 | D9: 3381 | E9: 4475 | F9: 6041 | G9: 8067 | H9: 10045 | I9: 11581 | J9: 14236 | K9: 16217 | L9: 18752 | M9: 21914 | N9: 26251 | O9: 29915 | P9: 31370 | Q9: 34550
A10: Selling, General & Administrative | B10: 5517 | C10: 7599 | D10: 10040 | E10: 10830 | F10: 11993 | G10: 14329 | H10: 14194 | I10: 15261 | J10: 16705 | K10: 18245 | L10: 19916 | M10: 21973 | N10: 25094 | O10: 24932 | P10: 26097 | Q10: 27601
A11: Total Operating Expenses | B11: =B9+B10 -> 7299 | C11: =C9+C10 -> 10028 | D11: =D9+D10 -> 13421 | E11: =E9+E10 -> 15305 | F11: =F9+F10 -> 18034 | G11: =G9+G10 -> 22396 | H11: =H9+H10 -> 24239 | I11: =I9+I10 -> 26842 | ... Q11: =Q9+Q10 -> 62151
A12: Operating Income (EBIT) | B12: =B7-B11 -> 18385 | C12: =C7-C11 -> 33790 | D12: =D7-D11 -> 55241 | E12: =E7-E11 -> 48999 | F12: =F7-F11 -> 52503 | G12: =G7-G11 -> 71230 | H12: =H7-H11 -> 60024 | I12: =I7-I11 -> 61344 | ... Q12: =Q7-Q11 -> 133050
A13: % Growth | B13: =IFERROR(B12/#REF!-1,"") | C13: =IFERROR(C12/B12-1,"") -> 0.83791134 | D13: =IFERROR(D12/C12-1,"") -> 0.63483279 | E13: =IFERROR(E12/D12-1,"") -> -0.11299578 | F13: =IFERROR(F12/E12-1,"") -> 0.071511664 | G13: =IFERROR(G12/F12-1,"") -> 0.35668438 | H13: =IFERROR(H12/G12-1,"") -> -0.15732135 | I13: =IFERROR(I12/H12-1,"") -> 0.021991204 | J13: =IFERROR(J12/I12-1,"") -> 0.15574465 | ... Q13: =IFERROR(Q12/P12-1,"") -> 0.079811063
A15: Other Income/(Expense), Net | B15: 155 | C15: 415 | D15: 522 | E15: 1156 | F15: 980 | G15: 1285 | H15: 1348 | I15: 2745 | J15: 2005 | K15: 1807 | L15: 803 | M15: 258 | N15: -334 | O15: -565 | P15: 269 | Q15: -321
A16: Total Other Income/(Expense) | B16: =B15 -> 155 | C16: =C15 -> 415 | D16: =D15 -> 522 | E16: =E15 -> 1156 | F16: =F15 -> 980 | G16: =G15 -> 1285 | H16: =H15 -> 1348 | I16: =I15 -> 2745 | ... Q16: =Q15 -> -321
A19: Income Before Income Taxes | B19: =B12+B16 -> 18540 | C19: =C12+C16 -> 34205 | D19: =D12+D16 -> 55763 | E19: =E12+E16 -> 50155 | F19: =F12+F16 -> 53483 | G19: =G12+G16 -> 72515 | H19: =H12+H16 -> 61372 | I19: =I12+I16 -> 64089 | ... Q19: =Q12+Q16 -> 132729
A20: Provision for Income Taxes | B20: 4527 | C20: 8283 | D20: 14030 | E20: 13118 | F20: 13973 | G20: 19121 | H20: 15685 | I20: 15738 | J20: 13372 | K20: 10481 | L20: 9680 | M20: 14527 | N20: 19300 | O20: 16741 | P20: 29749 | Q20: 20719
A21: Net Income | B21: =B19-B20 -> 14013 | C21: =C19-C20 -> 25922 | D21: =D19-D20 -> 41733 | E21: =E19-E20 -> 37037 | F21: =F19-F20 -> 39510 | G21: =G19-G20 -> 53394 | H21: =H19-H20 -> 45687 | I21: =I19-I20 -> 48351 | ... Q21: =Q19-Q20 -> 112010
A24: BALANCE SHEET
A25: Cash & Cash Equivalents (FY1992 source reports Cash + ST Investments combined) | B25: 11261 | C25: 9815 | D25: 10746 | E25: 14259 | F25: 13844 | G25: 21120 | H25: 20484 | I25: 20289 | J25: 25913 | K25: 48844 | L25: 38016 | M25: 34940 | N25: 23646 | O25: 29965 | P25: 29943 | Q25: 35934
A26: Short-Term Investments / Marketable Securities | B26: 14359 | C26: 16137 | D26: 18383 | E26: 26287 | F26: 11233 | G26: 20481 | H26: 46671 | I26: 53892 | J26: 40388 | K26: 51713 | L26: 52927 | M26: 27699 | N26: 24658 | O26: 31590 | P26: 35228 | Q26: 18763
A27: Accounts Receivable, Net | B27: 5510 | C27: 5369 | D27: 10930 | E27: 13102 | F27: 17460 | G27: 16849 | H27: 15754 | I27: 17874 | J27: 23186 | K27: 22926 | L27: 16120 | M27: 26278 | N27: 28184 | O27: 29508 | P27: 33410 | Q27: 39777
A28: Inventories | B28: 1051 | C28: 776 | D28: 791 | E28: 1764 | F28: 2111 | G28: 2349 | H28: 2132 | I28: 4855 | J28: 3956 | K28: 4106 | L28: 4061 | M28: 6580 | N28: 4946 | O28: 6331 | P28: 7286 | Q28: 5718
A29: Deferred Tax Assets | B29: 1636 | C29: 2014 | D29: 2583 | E29: 3453 | F29: 4318 | G29: 5546 | H29: 0 | I29: 0 | J29: 0 | K29: 0 | L29: 0 | M29: 0 | N29: 0 | O29: 0 | P29: 0 | Q29: 0
A30: Vendor Non-Trade Receivables | B30: 4414 | C30: 6348 | D30: 7762 | E30: 7539 | F30: 9759 | G30: 13494 | H30: 13545 | I30: 17799 | J30: 25809 | K30: 22878 | L30: 21325 | M30: 25228 | N30: 32748 | O30: 31477 | P30: 32833 | Q30: 33180
A31: Other Current Assets | B31: 3447 | C31: 4529 | D31: 6458 | E31: 6882 | F31: 9806 | G31: 9539 | H31: 8283 | I31: 13936 | J31: 12087 | K31: 12352 | L31: 11264 | M31: 14111 | N31: 21223 | O31: 14695 | P31: 14287 | Q31: 14585
A32: Total Current Assets | B32: =B25+B26+B27+B28+B29+B30+B31 -> 41678 | C32: =C25+C26+C27+C28+C29+C30+C31 -> 44988 | D32: =D25+D26+D27+D28+D29+D30+D31 -> 57653 | E32: =E25+E26+E27+E28+E29+E30+E31 -> 73286 | F32: =F25+F26+F27+F28+F29+F30+F31 -> 68531 | G32: =G25+G26+G27+G28+G29+G30+G31 -> 89378 | H32: =H25+H26+H27+H28+H29+H30+H31 -> 106869 | I32: =I25+I26+I27+I28+I29+I30+I31 -> 128645 | ... Q32: =Q25+Q26+Q27+Q28+Q29+Q30+Q31 -> 147957
A34: Property, Plant & Equipment, Net | B34: 4768 | C34: 7777 | D34: 15452 | E34: 16597 | F34: 20624 | G34: 22471 | H34: 27010 | I34: 33783 | J34: 41304 | K34: 37378 | L34: 36766 | M34: 39440 | N34: 42117 | O34: 43715 | P34: 45680 | Q34: 49834
A35: Long-Term Marketable Securities | B35: 25391 | C35: 55618 | D35: 92122 | E35: 106215 | F35: 130162 | G35: 164065 | H35: 170430 | I35: 194714 | J35: 170799 | K35: 105341 | L35: 100887 | M35: 127877 | N35: 120805 | O35: 100544 | P35: 91479 | Q35: 77723
A36: Goodwill | B36: 741 | C36: 896 | D36: 1135 | E36: 1577 | F36: 4616 | G36: 5116 | H36: 5414 | I36: 5717 | J36: 0 | K36: 0 | L36: 0 | M36: 0 | N36: 0 | O36: 0 | P36: 0 | Q36: 0
A37: Acquired Intangible Assets, Net | B37: 342 | C37: 3536 | D37: 4224 | E37: 4179 | F37: 4142 | G37: 3893 | H37: 3206 | I37: 2298 | J37: 0 | K37: 0 | L37: 0 | M37: 0 | N37: 0 | O37: 0 | P37: 0 | Q37: 0
A38: Other Assets (legacy) | B38: 2263 | C38: 3556 | D38: 5478 | E38: 5146 | F38: 3764 | G38: 5556 | H38: 8757 | I38: 10162 | J38: 0 | K38: 0 | L38: 0 | M38: 0 | N38: 0 | O38: 0 | P38: 0 | Q38: 0
A39: Other Non-Current Assets | B39: 0 | C39: 0 | D39: 0 | E39: 0 | F39: 0 | G39: 0 | H39: 0 | I39: 0 | J39: 22283 | K39: 32978 | L39: 42522 | M39: 48849 | N39: 54428 | O39: 64758 | P39: 74834 | Q39: 83727
A40: Total Non-Current Assets | B40: =B34+B35+B36+B37+B38+B39 -> 33505 | C40: =C34+C35+C36+C37+C38+C39 -> 71383 | D40: =D34+D35+D36+D37+D38+D39 -> 118411 | E40: =E34+E35+E36+E37+E38+E39 -> 133714 | F40: =F34+F35+F36+F37+F38+F39 -> 163308 | G40: =G34+G35+G36+G37+G38+G39 -> 201101 | H40: =H34+H35+H36+H37+H38+H39 -> 214817 | I40: =I34+I35+I36+I37+I38+I39 -> 246674 | ... Q40: =Q34+Q35+Q36+Q37+Q38+Q39 -> 211284
A41: Total Assets | B41: =B32+B40 -> 75183 | C41: =C32+C40 -> 116371 | D41: =D32+D40 -> 176064 | E41: =E32+E40 -> 207000 | F41: =F32+F40 -> 231839 | G41: =G32+G40 -> 290479 | H41: =H32+H40 -> 321686 | I41: =I32+I40 -> 375319 | ... Q41: =Q32+Q40 -> 359241
A43: Short-Term Borrowings / Notes Payable | B43: 0 | C43: 0 | D43: 0 | E43: 0 | F43: 0 | G43: 0 | H43: 0 | I43: 0 | J43: 0 | K43: 0 | L43: 0 | M43: 0 | N43: 0 | O43: 0 | P43: 0 | Q43: 0
A44: Accounts Payable | B44: 12015 | C44: 14632 | D44: 21175 | E44: 22367 | F44: 30196 | G44: 35490 | H44: 37294 | I44: 49049 | J44: 55888 | K44: 46236 | L44: 42296 | M44: 54763 | N44: 64115 | O44: 62611 | P44: 68960 | Q44: 69860
A45: Accrued Expenses | B45: 5723 | C45: 9247 | D45: 11414 | E45: 13856 | F45: 18453 | G45: 25181 | H45: 22027 | I45: 25744 | J45: 0 | K45: 0 | L45: 0 | M45: 0 | N45: 0 | O45: 0 | P45: 0 | Q45: 0
A46: Deferred Revenue - Current | B46: 2984 | C46: 4091 | D46: 5953 | E46: 7435 | F46: 8491 | G46: 8940 | H46: 8080 | I46: 7548 | J46: 7543 | K46: 5522 | L46: 6643 | M46: 7612 | N46: 7912 | O46: 8061 | P46: 8249 | Q46: 9055
A47: Other Current Liabilities | B47: 0 | C47: 0 | D47: 0 | E47: 0 | F47: 0 | G47: 0 | H47: 0 | I47: 0 | J47: 32687 | K47: 37720 | L47: 42684 | M47: 47493 | N47: 60845 | O47: 58829 | P47: 78304 | Q47: 66387
A48: Commercial Paper | B48: 0 | C48: 0 | D48: 0 | E48: 0 | F48: 6308 | G48: 8499 | H48: 8105 | I48: 11977 | J48: 11964 | K48: 5980 | L48: 4996 | M48: 6000 | N48: 9982 | O48: 5985 | P48: 9967 | Q48: 7979
A49: Current Debt / Term Debt | B49: 0 | C49: 0 | D49: 0 | E49: 0 | F49: 0 | G49: 2500 | H49: 3500 | I49: 6496 | J49: 8784 | K49: 10260 | L49: 8773 | M49: 9613 | N49: 11128 | O49: 9822 | P49: 10912 | Q49: 12350
A50: Total Current Liabilities | B50: =SUM(B43:B49) -> 20722 | C50: =SUM(C43:C49) -> 27970 | D50: =SUM(D43:D49) -> 38542 | E50: =SUM(E43:E49) -> 43658 | F50: =SUM(F43:F49) -> 63448 | G50: =SUM(G43:G49) -> 80610 | H50: =SUM(H43:H49) -> 79006 | I50: =SUM(I43:I49) -> 100814 | ... Q50: =SUM(Q43:Q49) -> 165631
A52: Long-Term Debt / Term Debt | B52: 0 | C52: 0 | D52: 0 | E52: 16960 | F52: 28987 | G52: 53463 | H52: 75427 | I52: 97207 | J52: 93735 | K52: 91807 | L52: 98667 | M52: 109106 | N52: 98959 | O52: 95281 | P52: 85750 | Q52: 78328
A53: Deferred Revenue - Non-Current | B53: 1139 | C53: 1686 | D53: 2648 | E53: 2625 | F53: 3031 | G53: 3624 | H53: 2930 | I53: 2836 | J53: 2797 | K53: 0 | L53: 0 | M53: 0 | N53: 0 | O53: 0 | P53: 0 | Q53: 0
A54: Other Non-Current Liabilities | B54: 5531 | C54: 10100 | D54: 16664 | E54: 20208 | F54: 24826 | G54: 33427 | H54: 36074 | I54: 40415 | J54: 45180 | K54: 50503 | L54: 54490 | M54: 53325 | N54: 49142 | O54: 49848 | P54: 45888 | Q54: 41549
A55: Total Non-Current Liabilities | B55: =SUM(B52:B54) -> 6670 | C55: =SUM(C52:C54) -> 11786 | D55: =SUM(D52:D54) -> 19312 | E55: =SUM(E52:E54) -> 39793 | F55: =SUM(F52:F54) -> 56844 | G55: =SUM(G52:G54) -> 90514 | H55: =SUM(H52:H54) -> 114431 | I55: =SUM(I52:I54) -> 140458 | ... Q55: =SUM(Q52:Q54) -> 119877
A56: Total Liabilities | B56: =B50+B55 -> 27392 | C56: =C50+C55 -> 39756 | D56: =D50+D55 -> 57854 | E56: =E50+E55 -> 83451 | F56: =F50+F55 -> 120292 | G56: =G50+G55 -> 171124 | H56: =H50+H55 -> 193437 | I56: =I50+I55 -> 241272 | ... Q56: =Q50+Q55 -> 285508
A58: Common Stock & Additional Paid-In Capital | B58: 10668 | C58: 13331 | D58: 16422 | E58: 19764 | F58: 23313 | G58: 27416 | H58: 31251 | I58: 35867 | J58: 40201 | K58: 45174 | L58: 50779 | M58: 57365 | N58: 64849 | O58: 73812 | P58: 83276 | Q58: 93568
A59: Retained Earnings | B59: 37169 | C59: 62841 | D59: 101289 | E59: 104256 | F59: 87152 | G59: 92284 | H59: 96364 | I59: 98330 | J59: 70400 | K59: 45898 | L59: 14966 | M59: 5562 | N59: 0 | O59: 0 | P59: 0 | Q59: 0
A60: Accumulated Deficit | B60: 0 | C60: 0 | D60: 0 | E60: 0 | F60: 0 | G60: 0 | H60: 0 | I60: 0 | J60: 0 | K60: 0 | L60: 0 | M60: 0 | N60: -3068 | O60: -214 | P60: -19154 | Q60: -14264
A61: Accumulated Other Comprehensive Income/(Loss) | B61: -46 | C61: 443 | D61: 499 | E61: -471 | F61: 1082 | G61: -345 | H61: 634 | I61: -150 | J61: -3454 | K61: -584 | L61: -406 | M61: 163 | N61: -11109 | O61: -11452 | P61: -7172 | Q61: -5571
A62: Total Shareholders' Equity | B62: =SUM(B58:B61) -> 47791 | C62: =SUM(C58:C61) -> 76615 | D62: =SUM(D58:D61) -> 118210 | E62: =SUM(E58:E61) -> 123549 | F62: =SUM(F58:F61) -> 111547 | G62: =SUM(G58:G61) -> 119355 | H62: =SUM(H58:H61) -> 128249 | I62: =SUM(I58:I61) -> 134047 | ... Q62: =SUM(Q58:Q61) -> 73733
A63: Total Liabilities & Shareholders' Equity | B63: =B56+B62 -> 75183 | C63: =C56+C62 -> 116371 | D63: =D56+D62 -> 176064 | E63: =E56+E62 -> 207000 | F63: =F56+F62 -> 231839 | G63: =G56+G62 -> 290479 | H63: =H56+H62 -> 321686 | I63: =I56+I62 -> 375319 | ... Q63: =Q56+Q62 -> 359241
A67: COMMON SIZE — APPLE INC. (FY2010–FY2025)
A68: All ratios calculated from the original financial statements above; original data unchanged.
A70: Financial statement line item | B70: 2010 | C70: 2011 | D70: 2012 | E70: 2013 | F70: 2014 | G70: 2015 | H70: 2016 | I70: 2017 | J70: 2018 | K70: 2019 | L70: 2020 | M70: 2021 | N70: 2022 | O70: 2023 | P70: 2024 | Q70: 2025
A71: INCOME STATEMENT
A72: Net Sales / Revenue | B72: =IFERROR(B5/B$5,"") -> 1 | C72: =IFERROR(C5/C$5,"") -> 1 | D72: =IFERROR(D5/D$5,"") -> 1 | E72: =IFERROR(E5/E$5,"") -> 1 | F72: =IFERROR(F5/F$5,"") -> 1 | G72: =IFERROR(G5/G$5,"") -> 1 | H72: =IFERROR(H5/H$5,"") -> 1 | I72: =IFERROR(I5/I$5,"") -> 1 | ... Q72: =IFERROR(Q5/Q$5,"") -> 1
A73: Total COGS | B73: =IFERROR(B6/B$5,"") -> 0.60622461 | C73: =IFERROR(C6/C$5,"") -> 0.59521104 | D73: =IFERROR(D6/D$5,"") -> 0.5612876 | E73: =IFERROR(E6/E$5,"") -> 0.62375519 | F73: =IFERROR(F6/F$5,"") -> 0.61411964 | G73: =IFERROR(G6/G$5,"") -> 0.59940098 | H73: =IFERROR(H6/H$5,"") -> 0.60924044 | I73: =IFERROR(I6/I$5,"") -> 0.6153014 | ... Q73: =IFERROR(Q6/Q$5,"") -> 0.53094836
A74: Gross Profit | B74: =IFERROR(B7/B$5,"") -> 0.39377539 | C74: =IFERROR(C7/C$5,"") -> 0.40478896 | D74: =IFERROR(D7/D$5,"") -> 0.4387124 | E74: =IFERROR(E7/E$5,"") -> 0.37624481 | F74: =IFERROR(F7/F$5,"") -> 0.38588036 | G74: =IFERROR(G7/G$5,"") -> 0.40059902 | H74: =IFERROR(H7/H$5,"") -> 0.39075956 | I74: =IFERROR(I7/I$5,"") -> 0.3846986 | ... Q74: =IFERROR(Q7/Q$5,"") -> 0.46905164
A76: Research & Development | B76: =IFERROR(B9/B$5,"") -> 0.027320813 | C76: =IFERROR(C9/C$5,"") -> 0.022439006 | D76: =IFERROR(D9/D$5,"") -> 0.02160273 | E76: =IFERROR(E9/E$5,"") -> 0.026183371 | F76: =IFERROR(F9/F$5,"") -> 0.03304795 | G76: =IFERROR(G9/G$5,"") -> 0.034516398 | H76: =IFERROR(H9/H$5,"") -> 0.046582483 | I76: =IFERROR(I9/I$5,"") -> 0.050520429 | ... Q76: =IFERROR(Q9/Q$5,"") -> 0.083020754
A77: Selling, General & Administrative | B77: =IFERROR(B10/B$5,"") -> 0.084584132 | C77: =IFERROR(C10/C$5,"") -> 0.070199263 | D77: =IFERROR(D10/D$5,"") -> 0.064150075 | E77: =IFERROR(E10/E$5,"") -> 0.063366684 | F77: =IFERROR(F10/F$5,"") -> 0.065609016 | G77: =IFERROR(G10/G$5,"") -> 0.061309715 | H77: =IFERROR(H10/H$5,"") -> 0.065822973 | I77: =IFERROR(I10/I$5,"") -> 0.066573894 | ... Q77: =IFERROR(Q10/Q$5,"") -> 0.066322889
A78: Total Operating Expenses | B78: =IFERROR(B11/B$5,"") -> 0.11190494 | C78: =IFERROR(C11/C$5,"") -> 0.092638269 | D78: =IFERROR(D11/D$5,"") -> 0.085752805 | E78: =IFERROR(E11/E$5,"") -> 0.089550056 | F78: =IFERROR(F11/F$5,"") -> 0.098656965 | G78: =IFERROR(G11/G$5,"") -> 0.095826113 | H78: =IFERROR(H11/H$5,"") -> 0.11240546 | I78: =IFERROR(I11/I$5,"") -> 0.11709432 | ... Q78: =IFERROR(Q11/Q$5,"") -> 0.14934364
A79: Operating Income (EBIT) | B79: =IFERROR(B12/B$5,"") -> 0.28187045 | C79: =IFERROR(C12/C$5,"") -> 0.31215069 | D79: =IFERROR(D12/D$5,"") -> 0.35295959 | E79: =IFERROR(E12/E$5,"") -> 0.28669475 | F79: =IFERROR(F12/F$5,"") -> 0.28722339 | G79: =IFERROR(G12/G$5,"") -> 0.30477291 | H79: =IFERROR(H12/H$5,"") -> 0.2783541 | I79: =IFERROR(I12/I$5,"") -> 0.26760428 | ... Q79: =IFERROR(Q12/Q$5,"") -> 0.319708
A82: Other Income/(Expense), Net | B82: =IFERROR(B15/B$5,"") -> 0.0023763894 | C82: =IFERROR(C15/C$5,"") -> 0.0038337537 | D82: =IFERROR(D15/D$5,"") -> 0.0033352928 | E82: =IFERROR(E15/E$5,"") -> 0.0067637938 | F82: =IFERROR(F15/F$5,"") -> 0.005361197 | G82: =IFERROR(G15/G$5,"") -> 0.0054981495 | H82: =IFERROR(H15/H$5,"") -> 0.0062511883 | I82: =IFERROR(I15/I$5,"") -> 0.011974663 | ... Q82: =IFERROR(Q15/Q$5,"") -> -0.00077133609
A83: Total Other Income/(Expense) | B83: =IFERROR(B16/B$5,"") -> 0.0023763894 | C83: =IFERROR(C16/C$5,"") -> 0.0038337537 | D83: =IFERROR(D16/D$5,"") -> 0.0033352928 | E83: =IFERROR(E16/E$5,"") -> 0.0067637938 | F83: =IFERROR(F16/F$5,"") -> 0.005361197 | G83: =IFERROR(G16/G$5,"") -> 0.0054981495 | H83: =IFERROR(H16/H$5,"") -> 0.0062511883 | I83: =IFERROR(I16/I$5,"") -> 0.011974663 | ... Q83: =IFERROR(Q16/Q$5,"") -> -0.00077133609
A86: Income Before Income Taxes | B86: =IFERROR(B19/B$5,"") -> 0.28424684 | C86: =IFERROR(C19/C$5,"") -> 0.31598444 | D86: =IFERROR(D19/D$5,"") -> 0.35629489 | E86: =IFERROR(E19/E$5,"") -> 0.29345855 | F86: =IFERROR(F19/F$5,"") -> 0.29258459 | G86: =IFERROR(G19/G$5,"") -> 0.31027106 | H86: =IFERROR(H19/H$5,"") -> 0.28460529 | I86: =IFERROR(I19/I$5,"") -> 0.27957895 | ... Q86: =IFERROR(Q19/Q$5,"") -> 0.31893666
A87: Provision for Income Taxes | B87: =IFERROR(B20/B$5,"") -> 0.069405903 | C87: =IFERROR(C20/C$5,"") -> 0.076518028 | D87: =IFERROR(D20/D$5,"") -> 0.08964398 | E87: =IFERROR(E20/E$5,"") -> 0.076753847 | F87: =IFERROR(F20/F$5,"") -> 0.076440822 | G87: =IFERROR(G20/G$5,"") -> 0.08181332 | H87: =IFERROR(H20/H$5,"") -> 0.072737306 | I87: =IFERROR(I20/I$5,"") -> 0.068654737 | ... Q87: =IFERROR(Q20/Q$5,"") -> 0.04978602
A88: Net Income | B88: =IFERROR(B21/B$5,"") -> 0.21484094 | C88: =IFERROR(C21/C$5,"") -> 0.23946642 | D88: =IFERROR(D21/D$5,"") -> 0.26665091 | E88: =IFERROR(E21/E$5,"") -> 0.2167047 | F88: =IFERROR(F21/F$5,"") -> 0.21614377 | G88: =IFERROR(G21/G$5,"") -> 0.22845774 | H88: =IFERROR(H21/H$5,"") -> 0.21186798 | I88: =IFERROR(I21/I$5,"") -> 0.21092421 | ... Q88: =IFERROR(Q21/Q$5,"") -> 0.26915064
A91: BALANCE SHEET
A92: Cash & Cash Equivalents (FY1992 source reports Cash + ST Investments combined) | B92: =IFERROR(B25/B$41,"") -> 0.1497812 | C92: =IFERROR(C25/C$41,"") -> 0.084342319 | D92: =IFERROR(D25/D$41,"") -> 0.061034624 | E92: =IFERROR(E25/E$41,"") -> 0.068884058 | F92: =IFERROR(F25/F$41,"") -> 0.059713853 | G92: =IFERROR(G25/G$41,"") -> 0.072707493 | H92: =IFERROR(H25/H$41,"") -> 0.063677002 | I92: =IFERROR(I25/I$41,"") -> 0.054058015 | ... Q92: =IFERROR(Q25/Q$41,"") -> 0.10002756
A93: Short-Term Investments / Marketable Securities | B93: =IFERROR(B26/B$41,"") -> 0.19098732 | C93: =IFERROR(C26/C$41,"") -> 0.13866857 | D93: =IFERROR(D26/D$41,"") -> 0.1044109 | E93: =IFERROR(E26/E$41,"") -> 0.12699034 | F93: =IFERROR(F26/F$41,"") -> 0.048451727 | G93: =IFERROR(G26/G$41,"") -> 0.070507679 | H93: =IFERROR(H26/H$41,"") -> 0.14508247 | I93: =IFERROR(I26/I$41,"") -> 0.14358985 | ... Q93: =IFERROR(Q26/Q$41,"") -> 0.052229562
A94: Accounts Receivable, Net | B94: =IFERROR(B27/B$41,"") -> 0.073287844 | C94: =IFERROR(C27/C$41,"") -> 0.046136924 | D94: =IFERROR(D27/D$41,"") -> 0.062079698 | E94: =IFERROR(E27/E$41,"") -> 0.063294686 | F94: =IFERROR(F27/F$41,"") -> 0.075310884 | G94: =IFERROR(G27/G$41,"") -> 0.058004193 | H94: =IFERROR(H27/H$41,"") -> 0.048973222 | I94: =IFERROR(I27/I$41,"") -> 0.047623488 | ... Q94: =IFERROR(Q27/Q$41,"") -> 0.11072511
A95: Inventories | B95: =IFERROR(B28/B$41,"") -> 0.013979224 | C95: =IFERROR(C28/C$41,"") -> 0.006668328 | D95: =IFERROR(D28/D$41,"") -> 0.0044926845 | E95: =IFERROR(E28/E$41,"") -> 0.0085217391 | F95: =IFERROR(F28/F$41,"") -> 0.0091054568 | G95: =IFERROR(G28/G$41,"") -> 0.0080866431 | H95: =IFERROR(H28/H$41,"") -> 0.0066275809 | I95: =IFERROR(I28/I$41,"") -> 0.012935663 | ... Q95: =IFERROR(Q28/Q$41,"") -> 0.015916891
A96: Deferred Tax Assets | B96: =IFERROR(B29/B$41,"") -> 0.021760238 | C96: =IFERROR(C29/C$41,"") -> 0.017306717 | D96: =IFERROR(D29/D$41,"") -> 0.014670802 | E96: =IFERROR(E29/E$41,"") -> 0.016681159 | F96: =IFERROR(F29/F$41,"") -> 0.018624994 | G96: =IFERROR(G29/G$41,"") -> 0.019092602 | H96: =IFERROR(H29/H$41,"") -> 0 | I96: =IFERROR(I29/I$41,"") -> 0 | ... Q96: =IFERROR(Q29/Q$41,"") -> 0
A97: Vendor Non-Trade Receivables | B97: =IFERROR(B30/B$41,"") -> 0.058710081 | C97: =IFERROR(C30/C$41,"") -> 0.054549673 | D97: =IFERROR(D30/D$41,"") -> 0.044086241 | E97: =IFERROR(E30/E$41,"") -> 0.03642029 | F97: =IFERROR(F30/F$41,"") -> 0.042093867 | G97: =IFERROR(G30/G$41,"") -> 0.046454305 | H97: =IFERROR(H30/H$41,"") -> 0.042106278 | I97: =IFERROR(I30/I$41,"") -> 0.047423658 | ... Q97: =IFERROR(Q30/Q$41,"") -> 0.092361395
A98: Other Current Assets | B98: =IFERROR(B31/B$41,"") -> 0.045848131 | C98: =IFERROR(C31/C$41,"") -> 0.038918631 | D98: =IFERROR(D31/D$41,"") -> 0.036679844 | E98: =IFERROR(E31/E$41,"") -> 0.033246377 | F98: =IFERROR(F31/F$41,"") -> 0.042296594 | G98: =IFERROR(G31/G$41,"") -> 0.032838863 | H98: =IFERROR(H31/H$41,"") -> 0.025748711 | I98: =IFERROR(I31/I$41,"") -> 0.03713108 | ... Q98: =IFERROR(Q31/Q$41,"") -> 0.040599486
A99: Total Current Assets | B99: =IFERROR(B32/B$41,"") -> 0.55435404 | C99: =IFERROR(C32/C$41,"") -> 0.38659116 | D99: =IFERROR(D32/D$41,"") -> 0.32745479 | E99: =IFERROR(E32/E$41,"") -> 0.35403865 | F99: =IFERROR(F32/F$41,"") -> 0.29559738 | G99: =IFERROR(G32/G$41,"") -> 0.30769178 | H99: =IFERROR(H32/H$41,"") -> 0.33221527 | I99: =IFERROR(I32/I$41,"") -> 0.34276176 | ... Q99: =IFERROR(Q32/Q$41,"") -> 0.41186
A101: Property, Plant & Equipment, Net | B101: =IFERROR(B34/B$41,"") -> 0.063418592 | C101: =IFERROR(C34/C$41,"") -> 0.066829365 | D101: =IFERROR(D34/D$41,"") -> 0.087763541 | E101: =IFERROR(E34/E$41,"") -> 0.080178744 | F101: =IFERROR(F34/F$41,"") -> 0.088958286 | G101: =IFERROR(G34/G$41,"") -> 0.077358432 | H101: =IFERROR(H34/H$41,"") -> 0.083963865 | I101: =IFERROR(I34/I$41,"") -> 0.09001143 | ... Q101: =IFERROR(Q34/Q$41,"") -> 0.13872025
A102: Long-Term Marketable Securities | B102: =IFERROR(B35/B$41,"") -> 0.33772262 | C102: =IFERROR(C35/C$41,"") -> 0.47793694 | D102: =IFERROR(D35/D$41,"") -> 0.52323019 | E102: =IFERROR(E35/E$41,"") -> 0.51311594 | F102: =IFERROR(F35/F$41,"") -> 0.56143272 | G102: =IFERROR(G35/G$41,"") -> 0.56480847 | H102: =IFERROR(H35/H$41,"") -> 0.52980235 | I102: =IFERROR(I35/I$41,"") -> 0.51879601 | ... Q102: =IFERROR(Q35/Q$41,"") -> 0.21635337
A103: Goodwill | B103: =IFERROR(B36/B$41,"") -> 0.0098559515 | C103: =IFERROR(C36/C$41,"") -> 0.0076995128 | D103: =IFERROR(D36/D$41,"") -> 0.0064465194 | E103: =IFERROR(E36/E$41,"") -> 0.0076183575 | F103: =IFERROR(F36/F$41,"") -> 0.019910369 | G103: =IFERROR(G36/G$41,"") -> 0.017612289 | H103: =IFERROR(H36/H$41,"") -> 0.016830077 | I103: =IFERROR(I36/I$41,"") -> 0.015232376 | ... Q103: =IFERROR(Q36/Q$41,"") -> 0
A104: Acquired Intangible Assets, Net | B104: =IFERROR(B37/B$41,"") -> 0.0045489007 | C104: =IFERROR(C37/C$41,"") -> 0.030385577 | D104: =IFERROR(D37/D$41,"") -> 0.023991276 | E104: =IFERROR(E37/E$41,"") -> 0.020188406 | F104: =IFERROR(F37/F$41,"") -> 0.017865847 | G104: =IFERROR(G37/G$41,"") -> 0.013402002 | H104: =IFERROR(H37/H$41,"") -> 0.0099662404 | I104: =IFERROR(I37/I$41,"") -> 0.0061227915 | ... Q104: =IFERROR(Q37/Q$41,"") -> 0
... A130: Total Liabilities & Shareholders' Equity | B130: =IFERROR(B63/B$41,"") -> 1 | C130: =IFERROR(C63/C$41,"") -> 1 | D130: =IFERROR(D63/D$41,"") -> 1 | E130: =IFERROR(E63/E$41,"") -> 1 | F130: =IFERROR(F63/F$41,"") -> 1 | G130: =IFERROR(G63/G$41,"") -> 1 | H130: =IFERROR(H63/H$41,"") -> 1 | I130: =IFERROR(I63/I$41,"") -> 1 | ... Q130: =IFERROR(Q63/Q$41,"") -> 1
A132: Methodology
A133: Income statement ÷ revenue; balance sheet ÷ total assets, for each year.

Sheet Index Analysis
A2: Fiscal Year | B2: 2010 | C2: 2011 | D2: 2012 | E2: 2013 | F2: 2014 | G2: 2015 | H2: 2016 | I2: 2017 | J2: 2018 | K2: 2019 | L2: 2020 | M2: 2021 | N2: 2022 | O2: 2023 | P2: 2024 | Q2: 2025
A4: INCOME STATEMENT
A5: Net Sales / Revenue | B5: 65225 | C5: 108249 | D5: 156508 | E5: 170910 | F5: 182795 | G5: 233715 | H5: 215639 | I5: 229234 | J5: 265595 | K5: 260174 | L5: 274515 | M5: 365817 | N5: 394328 | O5: 383285 | P5: 391035 | Q5: 416161
A6: Total COGS | B6: 39541 | C6: 64431 | D6: 87846 | E6: 106606 | F6: 112258 | G6: 140089 | H6: 131376 | I6: 141048 | J6: 163756 | K6: 161782 | L6: 169559 | M6: 212981 | N6: 223546 | O6: 214137 | P6: 210352 | Q6: 220960
A7: Gross Profit | B7: =B5-B6 -> 25684 | C7: =C5-C6 -> 43818 | D7: =D5-D6 -> 68662 | E7: =E5-E6 -> 64304 | F7: =F5-F6 -> 70537 | G7: =G5-G6 -> 93626 | H7: =H5-H6 -> 84263 | I7: =I5-I6 -> 88186 | ... Q7: =Q5-Q6 -> 195201
A9: Research & Development | B9: 1782 | C9: 2429 | D9: 3381 | E9: 4475 | F9: 6041 | G9: 8067 | H9: 10045 | I9: 11581 | J9: 14236 | K9: 16217 | L9: 18752 | M9: 21914 | N9: 26251 | O9: 29915 | P9: 31370 | Q9: 34550
A10: Selling, General & Administrative | B10: 5517 | C10: 7599 | D10: 10040 | E10: 10830 | F10: 11993 | G10: 14329 | H10: 14194 | I10: 15261 | J10: 16705 | K10: 18245 | L10: 19916 | M10: 21973 | N10: 25094 | O10: 24932 | P10: 26097 | Q10: 27601
A11: Total Operating Expenses | B11: =B9+B10 -> 7299 | C11: =C9+C10 -> 10028 | D11: =D9+D10 -> 13421 | E11: =E9+E10 -> 15305 | F11: =F9+F10 -> 18034 | G11: =G9+G10 -> 22396 | H11: =H9+H10 -> 24239 | I11: =I9+I10 -> 26842 | ... Q11: =Q9+Q10 -> 62151
A12: Operating Income (EBIT) | B12: =B7-B11 -> 18385 | C12: =C7-C11 -> 33790 | D12: =D7-D11 -> 55241 | E12: =E7-E11 -> 48999 | F12: =F7-F11 -> 52503 | G12: =G7-G11 -> 71230 | H12: =H7-H11 -> 60024 | I12: =I7-I11 -> 61344 | ... Q12: =Q7-Q11 -> 133050
A13: % Growth | B13: =IFERROR(B12/#REF!-1,"") | C13: =IFERROR(C12/B12-1,"") -> 0.83791134 | D13: =IFERROR(D12/C12-1,"") -> 0.63483279 | E13: =IFERROR(E12/D12-1,"") -> -0.11299578 | F13: =IFERROR(F12/E12-1,"") -> 0.071511664 | G13: =IFERROR(G12/F12-1,"") -> 0.35668438 | H13: =IFERROR(H12/G12-1,"") -> -0.15732135 | I13: =IFERROR(I12/H12-1,"") -> 0.021991204 | J13: =IFERROR(J12/I12-1,"") -> 0.15574465 | ... Q13: =IFERROR(Q12/P12-1,"") -> 0.079811063
A15: Other Income/(Expense), Net | B15: 155 | C15: 415 | D15: 522 | E15: 1156 | F15: 980 | G15: 1285 | H15: 1348 | I15: 2745 | J15: 2005 | K15: 1807 | L15: 803 | M15: 258 | N15: -334 | O15: -565 | P15: 269 | Q15: -321
A16: Total Other Income/(Expense) | B16: =B15 -> 155 | C16: =C15 -> 415 | D16: =D15 -> 522 | E16: =E15 -> 1156 | F16: =F15 -> 980 | G16: =G15 -> 1285 | H16: =H15 -> 1348 | I16: =I15 -> 2745 | ... Q16: =Q15 -> -321
A19: Income Before Income Taxes | B19: =B12+B16 -> 18540 | C19: =C12+C16 -> 34205 | D19: =D12+D16 -> 55763 | E19: =E12+E16 -> 50155 | F19: =F12+F16 -> 53483 | G19: =G12+G16 -> 72515 | H19: =H12+H16 -> 61372 | I19: =I12+I16 -> 64089 | ... Q19: =Q12+Q16 -> 132729
A20: Provision for Income Taxes | B20: 4527 | C20: 8283 | D20: 14030 | E20: 13118 | F20: 13973 | G20: 19121 | H20: 15685 | I20: 15738 | J20: 13372 | K20: 10481 | L20: 9680 | M20: 14527 | N20: 19300 | O20: 16741 | P20: 29749 | Q20: 20719
A21: Net Income | B21: =B19-B20 -> 14013 | C21: =C19-C20 -> 25922 | D21: =D19-D20 -> 41733 | E21: =E19-E20 -> 37037 | F21: =F19-F20 -> 39510 | G21: =G19-G20 -> 53394 | H21: =H19-H20 -> 45687 | I21: =I19-I20 -> 48351 | ... Q21: =Q19-Q20 -> 112010
A24: BALANCE SHEET
A25: Cash & Cash Equivalents (FY1992 source reports Cash + ST Investments combined) | B25: 11261 | C25: 9815 | D25: 10746 | E25: 14259 | F25: 13844 | G25: 21120 | H25: 20484 | I25: 20289 | J25: 25913 | K25: 48844 | L25: 38016 | M25: 34940 | N25: 23646 | O25: 29965 | P25: 29943 | Q25: 35934
A26: Short-Term Investments / Marketable Securities | B26: 14359 | C26: 16137 | D26: 18383 | E26: 26287 | F26: 11233 | G26: 20481 | H26: 46671 | I26: 53892 | J26: 40388 | K26: 51713 | L26: 52927 | M26: 27699 | N26: 24658 | O26: 31590 | P26: 35228 | Q26: 18763
A27: Accounts Receivable, Net | B27: 5510 | C27: 5369 | D27: 10930 | E27: 13102 | F27: 17460 | G27: 16849 | H27: 15754 | I27: 17874 | J27: 23186 | K27: 22926 | L27: 16120 | M27: 26278 | N27: 28184 | O27: 29508 | P27: 33410 | Q27: 39777
A28: Inventories | B28: 1051 | C28: 776 | D28: 791 | E28: 1764 | F28: 2111 | G28: 2349 | H28: 2132 | I28: 4855 | J28: 3956 | K28: 4106 | L28: 4061 | M28: 6580 | N28: 4946 | O28: 6331 | P28: 7286 | Q28: 5718
A29: Deferred Tax Assets | B29: 1636 | C29: 2014 | D29: 2583 | E29: 3453 | F29: 4318 | G29: 5546 | H29: 0 | I29: 0 | J29: 0 | K29: 0 | L29: 0 | M29: 0 | N29: 0 | O29: 0 | P29: 0 | Q29: 0
A30: Vendor Non-Trade Receivables | B30: 4414 | C30: 6348 | D30: 7762 | E30: 7539 | F30: 9759 | G30: 13494 | H30: 13545 | I30: 17799 | J30: 25809 | K30: 22878 | L30: 21325 | M30: 25228 | N30: 32748 | O30: 31477 | P30: 32833 | Q30: 33180
A31: Other Current Assets | B31: 3447 | C31: 4529 | D31: 6458 | E31: 6882 | F31: 9806 | G31: 9539 | H31: 8283 | I31: 13936 | J31: 12087 | K31: 12352 | L31: 11264 | M31: 14111 | N31: 21223 | O31: 14695 | P31: 14287 | Q31: 14585
A32: Total Current Assets | B32: =B25+B26+B27+B28+B29+B30+B31 -> 41678 | C32: =C25+C26+C27+C28+C29+C30+C31 -> 44988 | D32: =D25+D26+D27+D28+D29+D30+D31 -> 57653 | E32: =E25+E26+E27+E28+E29+E30+E31 -> 73286 | F32: =F25+F26+F27+F28+F29+F30+F31 -> 68531 | G32: =G25+G26+G27+G28+G29+G30+G31 -> 89378 | H32: =H25+H26+H27+H28+H29+H30+H31 -> 106869 | I32: =I25+I26+I27+I28+I29+I30+I31 -> 128645 | ... Q32: =Q25+Q26+Q27+Q28+Q29+Q30+Q31 -> 147957
A34: Property, Plant & Equipment, Net | B34: 4768 | C34: 7777 | D34: 15452 | E34: 16597 | F34: 20624 | G34: 22471 | H34: 27010 | I34: 33783 | J34: 41304 | K34: 37378 | L34: 36766 | M34: 39440 | N34: 42117 | O34: 43715 | P34: 45680 | Q34: 49834
A35: Long-Term Marketable Securities | B35: 25391 | C35: 55618 | D35: 92122 | E35: 106215 | F35: 130162 | G35: 164065 | H35: 170430 | I35: 194714 | J35: 170799 | K35: 105341 | L35: 100887 | M35: 127877 | N35: 120805 | O35: 100544 | P35: 91479 | Q35: 77723
A36: Goodwill | B36: 741 | C36: 896 | D36: 1135 | E36: 1577 | F36: 4616 | G36: 5116 | H36: 5414 | I36: 5717 | J36: 0 | K36: 0 | L36: 0 | M36: 0 | N36: 0 | O36: 0 | P36: 0 | Q36: 0
A37: Acquired Intangible Assets, Net | B37: 342 | C37: 3536 | D37: 4224 | E37: 4179 | F37: 4142 | G37: 3893 | H37: 3206 | I37: 2298 | J37: 0 | K37: 0 | L37: 0 | M37: 0 | N37: 0 | O37: 0 | P37: 0 | Q37: 0
A38: Other Assets (legacy) | B38: 2263 | C38: 3556 | D38: 5478 | E38: 5146 | F38: 3764 | G38: 5556 | H38: 8757 | I38: 10162 | J38: 0 | K38: 0 | L38: 0 | M38: 0 | N38: 0 | O38: 0 | P38: 0 | Q38: 0
A39: Other Non-Current Assets | B39: 0 | C39: 0 | D39: 0 | E39: 0 | F39: 0 | G39: 0 | H39: 0 | I39: 0 | J39: 22283 | K39: 32978 | L39: 42522 | M39: 48849 | N39: 54428 | O39: 64758 | P39: 74834 | Q39: 83727
A40: Total Non-Current Assets | B40: =B34+B35+B36+B37+B38+B39 -> 33505 | C40: =C34+C35+C36+C37+C38+C39 -> 71383 | D40: =D34+D35+D36+D37+D38+D39 -> 118411 | E40: =E34+E35+E36+E37+E38+E39 -> 133714 | F40: =F34+F35+F36+F37+F38+F39 -> 163308 | G40: =G34+G35+G36+G37+G38+G39 -> 201101 | H40: =H34+H35+H36+H37+H38+H39 -> 214817 | I40: =I34+I35+I36+I37+I38+I39 -> 246674 | ... Q40: =Q34+Q35+Q36+Q37+Q38+Q39 -> 211284
A41: Total Assets | B41: =B32+B40 -> 75183 | C41: =C32+C40 -> 116371 | D41: =D32+D40 -> 176064 | E41: =E32+E40 -> 207000 | F41: =F32+F40 -> 231839 | G41: =G32+G40 -> 290479 | H41: =H32+H40 -> 321686 | I41: =I32+I40 -> 375319 | ... Q41: =Q32+Q40 -> 359241
A43: Short-Term Borrowings / Notes Payable | B43: 0 | C43: 0 | D43: 0 | E43: 0 | F43: 0 | G43: 0 | H43: 0 | I43: 0 | J43: 0 | K43: 0 | L43: 0 | M43: 0 | N43: 0 | O43: 0 | P43: 0 | Q43: 0
A44: Accounts Payable | B44: 12015 | C44: 14632 | D44: 21175 | E44: 22367 | F44: 30196 | G44: 35490 | H44: 37294 | I44: 49049 | J44: 55888 | K44: 46236 | L44: 42296 | M44: 54763 | N44: 64115 | O44: 62611 | P44: 68960 | Q44: 69860
A45: Accrued Expenses | B45: 5723 | C45: 9247 | D45: 11414 | E45: 13856 | F45: 18453 | G45: 25181 | H45: 22027 | I45: 25744 | J45: 0 | K45: 0 | L45: 0 | M45: 0 | N45: 0 | O45: 0 | P45: 0 | Q45: 0
A46: Deferred Revenue - Current | B46: 2984 | C46: 4091 | D46: 5953 | E46: 7435 | F46: 8491 | G46: 8940 | H46: 8080 | I46: 7548 | J46: 7543 | K46: 5522 | L46: 6643 | M46: 7612 | N46: 7912 | O46: 8061 | P46: 8249 | Q46: 9055
A47: Other Current Liabilities | B47: 0 | C47: 0 | D47: 0 | E47: 0 | F47: 0 | G47: 0 | H47: 0 | I47: 0 | J47: 32687 | K47: 37720 | L47: 42684 | M47: 47493 | N47: 60845 | O47: 58829 | P47: 78304 | Q47: 66387
A48: Commercial Paper | B48: 0 | C48: 0 | D48: 0 | E48: 0 | F48: 6308 | G48: 8499 | H48: 8105 | I48: 11977 | J48: 11964 | K48: 5980 | L48: 4996 | M48: 6000 | N48: 9982 | O48: 5985 | P48: 9967 | Q48: 7979
A49: Current Debt / Term Debt | B49: 0 | C49: 0 | D49: 0 | E49: 0 | F49: 0 | G49: 2500 | H49: 3500 | I49: 6496 | J49: 8784 | K49: 10260 | L49: 8773 | M49: 9613 | N49: 11128 | O49: 9822 | P49: 10912 | Q49: 12350
A50: Total Current Liabilities | B50: =SUM(B43:B49) -> 20722 | C50: =SUM(C43:C49) -> 27970 | D50: =SUM(D43:D49) -> 38542 | E50: =SUM(E43:E49) -> 43658 | F50: =SUM(F43:F49) -> 63448 | G50: =SUM(G43:G49) -> 80610 | H50: =SUM(H43:H49) -> 79006 | I50: =SUM(I43:I49) -> 100814 | ... Q50: =SUM(Q43:Q49) -> 165631
A52: Long-Term Debt / Term Debt | B52: 0 | C52: 0 | D52: 0 | E52: 16960 | F52: 28987 | G52: 53463 | H52: 75427 | I52: 97207 | J52: 93735 | K52: 91807 | L52: 98667 | M52: 109106 | N52: 98959 | O52: 95281 | P52: 85750 | Q52: 78328
A53: Deferred Revenue - Non-Current | B53: 1139 | C53: 1686 | D53: 2648 | E53: 2625 | F53: 3031 | G53: 3624 | H53: 2930 | I53: 2836 | J53: 2797 | K53: 0 | L53: 0 | M53: 0 | N53: 0 | O53: 0 | P53: 0 | Q53: 0
A54: Other Non-Current Liabilities | B54: 5531 | C54: 10100 | D54: 16664 | E54: 20208 | F54: 24826 | G54: 33427 | H54: 36074 | I54: 40415 | J54: 45180 | K54: 50503 | L54: 54490 | M54: 53325 | N54: 49142 | O54: 49848 | P54: 45888 | Q54: 41549
A55: Total Non-Current Liabilities | B55: =SUM(B52:B54) -> 6670 | C55: =SUM(C52:C54) -> 11786 | D55: =SUM(D52:D54) -> 19312 | E55: =SUM(E52:E54) -> 39793 | F55: =SUM(F52:F54) -> 56844 | G55: =SUM(G52:G54) -> 90514 | H55: =SUM(H52:H54) -> 114431 | I55: =SUM(I52:I54) -> 140458 | ... Q55: =SUM(Q52:Q54) -> 119877
A56: Total Liabilities | B56: =B50+B55 -> 27392 | C56: =C50+C55 -> 39756 | D56: =D50+D55 -> 57854 | E56: =E50+E55 -> 83451 | F56: =F50+F55 -> 120292 | G56: =G50+G55 -> 171124 | H56: =H50+H55 -> 193437 | I56: =I50+I55 -> 241272 | ... Q56: =Q50+Q55 -> 285508
A58: Common Stock & Additional Paid-In Capital | B58: 10668 | C58: 13331 | D58: 16422 | E58: 19764 | F58: 23313 | G58: 27416 | H58: 31251 | I58: 35867 | J58: 40201 | K58: 45174 | L58: 50779 | M58: 57365 | N58: 64849 | O58: 73812 | P58: 83276 | Q58: 93568
A59: Retained Earnings | B59: 37169 | C59: 62841 | D59: 101289 | E59: 104256 | F59: 87152 | G59: 92284 | H59: 96364 | I59: 98330 | J59: 70400 | K59: 45898 | L59: 14966 | M59: 5562 | N59: 0 | O59: 0 | P59: 0 | Q59: 0
A60: Accumulated Deficit | B60: 0 | C60: 0 | D60: 0 | E60: 0 | F60: 0 | G60: 0 | H60: 0 | I60: 0 | J60: 0 | K60: 0 | L60: 0 | M60: 0 | N60: -3068 | O60: -214 | P60: -19154 | Q60: -14264
A61: Accumulated Other Comprehensive Income/(Loss) | B61: -46 | C61: 443 | D61: 499 | E61: -471 | F61: 1082 | G61: -345 | H61: 634 | I61: -150 | J61: -3454 | K61: -584 | L61: -406 | M61: 163 | N61: -11109 | O61: -11452 | P61: -7172 | Q61: -5571
A62: Total Shareholders' Equity | B62: =SUM(B58:B61) -> 47791 | C62: =SUM(C58:C61) -> 76615 | D62: =SUM(D58:D61) -> 118210 | E62: =SUM(E58:E61) -> 123549 | F62: =SUM(F58:F61) -> 111547 | G62: =SUM(G58:G61) -> 119355 | H62: =SUM(H58:H61) -> 128249 | I62: =SUM(I58:I61) -> 134047 | ... Q62: =SUM(Q58:Q61) -> 73733
A63: Total Liabilities & Shareholders' Equity | B63: =B56+B62 -> 75183 | C63: =C56+C62 -> 116371 | D63: =D56+D62 -> 176064 | E63: =E56+E62 -> 207000 | F63: =F56+F62 -> 231839 | G63: =G56+G62 -> 290479 | H63: =H56+H62 -> 321686 | I63: =I56+I62 -> 375319 | ... Q63: =Q56+Q62 -> 359241
A67: INDEX ANALYSIS — APPLE INC. (FY2010–FY2025)
A68: All ratios calculated from the original financial statements above; original data unchanged.
A70: Financial statement line item | B70: 2010 | C70: 2011 | D70: 2012 | E70: 2013 | F70: 2014 | G70: 2015 | H70: 2016 | I70: 2017 | J70: 2018 | K70: 2019 | L70: 2020 | M70: 2021 | N70: 2022 | O70: 2023 | P70: 2024 | Q70: 2025
A71: INCOME STATEMENT
A72: Net Sales / Revenue | B72: =IFERROR(IF($B5=0,"",B5/$B5),"") -> 1 | C72: =IFERROR(IF($B5=0,"",C5/$B5),"") -> 1.6596244 | D72: =IFERROR(IF($B5=0,"",D5/$B5),"") -> 2.3995094 | E72: =IFERROR(IF($B5=0,"",E5/$B5),"") -> 2.6203143 | F72: =IFERROR(IF($B5=0,"",F5/$B5),"") -> 2.8025297 | G72: =IFERROR(IF($B5=0,"",G5/$B5),"") -> 3.583212 | H72: =IFERROR(IF($B5=0,"",H5/$B5),"") -> 3.306079 | I72: =IFERROR(IF($B5=0,"",I5/$B5),"") -> 3.5145113 | ... Q72: =IFERROR(IF($B5=0,"",Q5/$B5),"") -> 6.380391
A73: Total COGS | B73: =IFERROR(IF($B6=0,"",B6/$B6),"") -> 1 | C73: =IFERROR(IF($B6=0,"",C6/$B6),"") -> 1.6294732 | D73: =IFERROR(IF($B6=0,"",D6/$B6),"") -> 2.2216434 | E73: =IFERROR(IF($B6=0,"",E6/$B6),"") -> 2.6960876 | F73: =IFERROR(IF($B6=0,"",F6/$B6),"") -> 2.8390278 | G73: =IFERROR(IF($B6=0,"",G6/$B6),"") -> 3.5428795 | H73: =IFERROR(IF($B6=0,"",H6/$B6),"") -> 3.322526 | I73: =IFERROR(IF($B6=0,"",I6/$B6),"") -> 3.5671328 | ... Q73: =IFERROR(IF($B6=0,"",Q6/$B6),"") -> 5.5881237
A74: Gross Profit | B74: =IFERROR(IF($B7=0,"",B7/$B7),"") -> 1 | C74: =IFERROR(IF($B7=0,"",C7/$B7),"") -> 1.7060427 | D74: =IFERROR(IF($B7=0,"",D7/$B7),"") -> 2.6733375 | E74: =IFERROR(IF($B7=0,"",E7/$B7),"") -> 2.5036599 | F74: =IFERROR(IF($B7=0,"",F7/$B7),"") -> 2.7463401 | G74: =IFERROR(IF($B7=0,"",G7/$B7),"") -> 3.6453045 | H74: =IFERROR(IF($B7=0,"",H7/$B7),"") -> 3.2807584 | I74: =IFERROR(IF($B7=0,"",I7/$B7),"") -> 3.4334995 | ... Q74: =IFERROR(IF($B7=0,"",Q7/$B7),"") -> 7.6001012
A76: Research & Development | B76: =IFERROR(IF($B9=0,"",B9/$B9),"") -> 1 | C76: =IFERROR(IF($B9=0,"",C9/$B9),"") -> 1.3630752 | D76: =IFERROR(IF($B9=0,"",D9/$B9),"") -> 1.8973064 | E76: =IFERROR(IF($B9=0,"",E9/$B9),"") -> 2.5112233 | F76: =IFERROR(IF($B9=0,"",F9/$B9),"") -> 3.3900112 | G76: =IFERROR(IF($B9=0,"",G9/$B9),"") -> 4.526936 | H76: =IFERROR(IF($B9=0,"",H9/$B9),"") -> 5.6369248 | I76: =IFERROR(IF($B9=0,"",I9/$B9),"") -> 6.4988777 | ... Q76: =IFERROR(IF($B9=0,"",Q9/$B9),"") -> 19.388328
A77: Selling, General & Administrative | B77: =IFERROR(IF($B10=0,"",B10/$B10),"") -> 1 | C77: =IFERROR(IF($B10=0,"",C10/$B10),"") -> 1.377379 | D77: =IFERROR(IF($B10=0,"",D10/$B10),"") -> 1.8198296 | E77: =IFERROR(IF($B10=0,"",E10/$B10),"") -> 1.9630234 | F77: =IFERROR(IF($B10=0,"",F10/$B10),"") -> 2.1738264 | G77: =IFERROR(IF($B10=0,"",G10/$B10),"") -> 2.5972449 | H77: =IFERROR(IF($B10=0,"",H10/$B10),"") -> 2.5727751 | I77: =IFERROR(IF($B10=0,"",I10/$B10),"") -> 2.7661773 | ... Q77: =IFERROR(IF($B10=0,"",Q10/$B10),"") -> 5.0029001
A78: Total Operating Expenses | B78: =IFERROR(IF($B11=0,"",B11/$B11),"") -> 1 | C78: =IFERROR(IF($B11=0,"",C11/$B11),"") -> 1.3738868 | D78: =IFERROR(IF($B11=0,"",D11/$B11),"") -> 1.838745 | E78: =IFERROR(IF($B11=0,"",E11/$B11),"") -> 2.0968626 | F78: =IFERROR(IF($B11=0,"",F11/$B11),"") -> 2.4707494 | G78: =IFERROR(IF($B11=0,"",G11/$B11),"") -> 3.0683655 | H78: =IFERROR(IF($B11=0,"",H11/$B11),"") -> 3.3208659 | I78: =IFERROR(IF($B11=0,"",I11/$B11),"") -> 3.6774901 | ... Q78: =IFERROR(IF($B11=0,"",Q11/$B11),"") -> 8.5150021
A79: Operating Income (EBIT) | B79: =IFERROR(IF($B12=0,"",B12/$B12),"") -> 1 | C79: =IFERROR(IF($B12=0,"",C12/$B12),"") -> 1.8379113 | D79: =IFERROR(IF($B12=0,"",D12/$B12),"") -> 3.0046777 | E79: =IFERROR(IF($B12=0,"",E12/$B12),"") -> 2.6651618 | F79: =IFERROR(IF($B12=0,"",F12/$B12),"") -> 2.855752 | G79: =IFERROR(IF($B12=0,"",G12/$B12),"") -> 3.8743541 | H79: =IFERROR(IF($B12=0,"",H12/$B12),"") -> 3.2648355 | I79: =IFERROR(IF($B12=0,"",I12/$B12),"") -> 3.3366331 | ... Q79: =IFERROR(IF($B12=0,"",Q12/$B12),"") -> 7.2368779
A82: Other Income/(Expense), Net | B82: =IFERROR(IF($B15=0,"",B15/$B15),"") -> 1 | C82: =IFERROR(IF($B15=0,"",C15/$B15),"") -> 2.6774194 | D82: =IFERROR(IF($B15=0,"",D15/$B15),"") -> 3.3677419 | E82: =IFERROR(IF($B15=0,"",E15/$B15),"") -> 7.4580645 | F82: =IFERROR(IF($B15=0,"",F15/$B15),"") -> 6.3225806 | G82: =IFERROR(IF($B15=0,"",G15/$B15),"") -> 8.2903226 | H82: =IFERROR(IF($B15=0,"",H15/$B15),"") -> 8.6967742 | I82: =IFERROR(IF($B15=0,"",I15/$B15),"") -> 17.709677 | ... Q82: =IFERROR(IF($B15=0,"",Q15/$B15),"") -> -2.0709677
A83: Total Other Income/(Expense) | B83: =IFERROR(IF($B16=0,"",B16/$B16),"") -> 1 | C83: =IFERROR(IF($B16=0,"",C16/$B16),"") -> 2.6774194 | D83: =IFERROR(IF($B16=0,"",D16/$B16),"") -> 3.3677419 | E83: =IFERROR(IF($B16=0,"",E16/$B16),"") -> 7.4580645 | F83: =IFERROR(IF($B16=0,"",F16/$B16),"") -> 6.3225806 | G83: =IFERROR(IF($B16=0,"",G16/$B16),"") -> 8.2903226 | H83: =IFERROR(IF($B16=0,"",H16/$B16),"") -> 8.6967742 | I83: =IFERROR(IF($B16=0,"",I16/$B16),"") -> 17.709677 | ... Q83: =IFERROR(IF($B16=0,"",Q16/$B16),"") -> -2.0709677
A86: Income Before Income Taxes | B86: =IFERROR(IF($B19=0,"",B19/$B19),"") -> 1 | C86: =IFERROR(IF($B19=0,"",C19/$B19),"") -> 1.8449299 | D86: =IFERROR(IF($B19=0,"",D19/$B19),"") -> 3.0077131 | E86: =IFERROR(IF($B19=0,"",E19/$B19),"") -> 2.7052319 | F86: =IFERROR(IF($B19=0,"",F19/$B19),"") -> 2.8847357 | G86: =IFERROR(IF($B19=0,"",G19/$B19),"") -> 3.9112729 | H86: =IFERROR(IF($B19=0,"",H19/$B19),"") -> 3.3102481 | I86: =IFERROR(IF($B19=0,"",I19/$B19),"") -> 3.4567961 | ... Q86: =IFERROR(IF($B19=0,"",Q19/$B19),"") -> 7.1590615
A87: Provision for Income Taxes | B87: =IFERROR(IF($B20=0,"",B20/$B20),"") -> 1 | C87: =IFERROR(IF($B20=0,"",C20/$B20),"") -> 1.8296885 | D87: =IFERROR(IF($B20=0,"",D20/$B20),"") -> 3.0991827 | E87: =IFERROR(IF($B20=0,"",E20/$B20),"") -> 2.8977248 | F87: =IFERROR(IF($B20=0,"",F20/$B20),"") -> 3.0865916 | G87: =IFERROR(IF($B20=0,"",G20/$B20),"") -> 4.2237685 | H87: =IFERROR(IF($B20=0,"",H20/$B20),"") -> 3.464767 | I87: =IFERROR(IF($B20=0,"",I20/$B20),"") -> 3.4764745 | ... Q87: =IFERROR(IF($B20=0,"",Q20/$B20),"") -> 4.5767617
A88: Net Income | B88: =IFERROR(IF($B21=0,"",B21/$B21),"") -> 1 | C88: =IFERROR(IF($B21=0,"",C21/$B21),"") -> 1.8498537 | D88: =IFERROR(IF($B21=0,"",D21/$B21),"") -> 2.9781631 | E88: =IFERROR(IF($B21=0,"",E21/$B21),"") -> 2.6430457 | F88: =IFERROR(IF($B21=0,"",F21/$B21),"") -> 2.8195247 | G88: =IFERROR(IF($B21=0,"",G21/$B21),"") -> 3.810319 | H88: =IFERROR(IF($B21=0,"",H21/$B21),"") -> 3.2603297 | I88: =IFERROR(IF($B21=0,"",I21/$B21),"") -> 3.4504389 | ... Q88: =IFERROR(IF($B21=0,"",Q21/$B21),"") -> 7.9932919
A91: BALANCE SHEET
A92: Cash & Cash Equivalents (FY1992 source reports Cash + ST Investments combined) | B92: =IFERROR(IF($B25=0,"",B25/$B25),"") -> 1 | C92: =IFERROR(IF($B25=0,"",C25/$B25),"") -> 0.87159222 | D92: =IFERROR(IF($B25=0,"",D25/$B25),"") -> 0.95426694 | E92: =IFERROR(IF($B25=0,"",E25/$B25),"") -> 1.2662286 | F92: =IFERROR(IF($B25=0,"",F25/$B25),"") -> 1.2293757 | G92: =IFERROR(IF($B25=0,"",G25/$B25),"") -> 1.8754995 | H92: =IFERROR(IF($B25=0,"",H25/$B25),"") -> 1.8190214 | I92: =IFERROR(IF($B25=0,"",I25/$B25),"") -> 1.801705 | ... Q92: =IFERROR(IF($B25=0,"",Q25/$B25),"") -> 3.1910132
A93: Short-Term Investments / Marketable Securities | B93: =IFERROR(IF($B26=0,"",B26/$B26),"") -> 1 | C93: =IFERROR(IF($B26=0,"",C26/$B26),"") -> 1.1238248 | D93: =IFERROR(IF($B26=0,"",D26/$B26),"") -> 1.2802424 | E93: =IFERROR(IF($B26=0,"",E26/$B26),"") -> 1.8306985 | F93: =IFERROR(IF($B26=0,"",F26/$B26),"") -> 0.78229682 | G93: =IFERROR(IF($B26=0,"",G26/$B26),"") -> 1.4263528 | H93: =IFERROR(IF($B26=0,"",H26/$B26),"") -> 3.250296 | I93: =IFERROR(IF($B26=0,"",I26/$B26),"") -> 3.7531862 | ... Q93: =IFERROR(IF($B26=0,"",Q26/$B26),"") -> 1.3067066
A94: Accounts Receivable, Net | B94: =IFERROR(IF($B27=0,"",B27/$B27),"") -> 1 | C94: =IFERROR(IF($B27=0,"",C27/$B27),"") -> 0.97441016 | D94: =IFERROR(IF($B27=0,"",D27/$B27),"") -> 1.9836661 | E94: =IFERROR(IF($B27=0,"",E27/$B27),"") -> 2.3778584 | F94: =IFERROR(IF($B27=0,"",F27/$B27),"") -> 3.168784 | G94: =IFERROR(IF($B27=0,"",G27/$B27),"") -> 3.0578947 | H94: =IFERROR(IF($B27=0,"",H27/$B27),"") -> 2.8591652 | I94: =IFERROR(IF($B27=0,"",I27/$B27),"") -> 3.2439201 | ... Q94: =IFERROR(IF($B27=0,"",Q27/$B27),"") -> 7.2190563
A95: Inventories | B95: =IFERROR(IF($B28=0,"",B28/$B28),"") -> 1 | C95: =IFERROR(IF($B28=0,"",C28/$B28),"") -> 0.73834443 | D95: =IFERROR(IF($B28=0,"",D28/$B28),"") -> 0.75261656 | E95: =IFERROR(IF($B28=0,"",E28/$B28),"") -> 1.6784015 | F95: =IFERROR(IF($B28=0,"",F28/$B28),"") -> 2.0085633 | G95: =IFERROR(IF($B28=0,"",G28/$B28),"") -> 2.2350143 | H95: =IFERROR(IF($B28=0,"",H28/$B28),"") -> 2.0285442 | I95: =IFERROR(IF($B28=0,"",I28/$B28),"") -> 4.6194101 | ... Q95: =IFERROR(IF($B28=0,"",Q28/$B28),"") -> 5.4405328
A96: Deferred Tax Assets | B96: =IFERROR(IF($B29=0,"",B29/$B29),"") -> 1 | C96: =IFERROR(IF($B29=0,"",C29/$B29),"") -> 1.2310513 | D96: =IFERROR(IF($B29=0,"",D29/$B29),"") -> 1.5788509 | E96: =IFERROR(IF($B29=0,"",E29/$B29),"") -> 2.1106357 | F96: =IFERROR(IF($B29=0,"",F29/$B29),"") -> 2.6393643 | G96: =IFERROR(IF($B29=0,"",G29/$B29),"") -> 3.3899756 | H96: =IFERROR(IF($B29=0,"",H29/$B29),"") -> 0 | I96: =IFERROR(IF($B29=0,"",I29/$B29),"") -> 0 | ... Q96: =IFERROR(IF($B29=0,"",Q29/$B29),"") -> 0
A97: Vendor Non-Trade Receivables | B97: =IFERROR(IF($B30=0,"",B30/$B30),"") -> 1 | C97: =IFERROR(IF($B30=0,"",C30/$B30),"") -> 1.4381513 | D97: =IFERROR(IF($B30=0,"",D30/$B30),"") -> 1.7584957 | E97: =IFERROR(IF($B30=0,"",E30/$B30),"") -> 1.7079746 | F97: =IFERROR(IF($B30=0,"",F30/$B30),"") -> 2.2109198 | G97: =IFERROR(IF($B30=0,"",G30/$B30),"") -> 3.0570911 | H97: =IFERROR(IF($B30=0,"",H30/$B30),"") -> 3.0686452 | I97: =IFERROR(IF($B30=0,"",I30/$B30),"") -> 4.0323969 | ... Q97: =IFERROR(IF($B30=0,"",Q30/$B30),"") -> 7.5169914
A98: Other Current Assets | B98: =IFERROR(IF($B31=0,"",B31/$B31),"") -> 1 | C98: =IFERROR(IF($B31=0,"",C31/$B31),"") -> 1.3138961 | D98: =IFERROR(IF($B31=0,"",D31/$B31),"") -> 1.8735132 | E98: =IFERROR(IF($B31=0,"",E31/$B31),"") -> 1.9965187 | F98: =IFERROR(IF($B31=0,"",F31/$B31),"") -> 2.8447926 | G98: =IFERROR(IF($B31=0,"",G31/$B31),"") -> 2.7673339 | H98: =IFERROR(IF($B31=0,"",H31/$B31),"") -> 2.4029591 | I98: =IFERROR(IF($B31=0,"",I31/$B31),"") -> 4.0429359 | ... Q98: =IFERROR(IF($B31=0,"",Q31/$B31),"") -> 4.2312155
A99: Total Current Assets | B99: =IFERROR(IF($B32=0,"",B32/$B32),"") -> 1 | C99: =IFERROR(IF($B32=0,"",C32/$B32),"") -> 1.0794184 | D99: =IFERROR(IF($B32=0,"",D32/$B32),"") -> 1.3832957 | E99: =IFERROR(IF($B32=0,"",E32/$B32),"") -> 1.7583857 | F99: =IFERROR(IF($B32=0,"",F32/$B32),"") -> 1.6442968 | G99: =IFERROR(IF($B32=0,"",G32/$B32),"") -> 2.1444887 | H99: =IFERROR(IF($B32=0,"",H32/$B32),"") -> 2.5641585 | I99: =IFERROR(IF($B32=0,"",I32/$B32),"") -> 3.0866404 | ... Q99: =IFERROR(IF($B32=0,"",Q32/$B32),"") -> 3.5500024
A101: Property, Plant & Equipment, Net | B101: =IFERROR(IF($B34=0,"",B34/$B34),"") -> 1 | C101: =IFERROR(IF($B34=0,"",C34/$B34),"") -> 1.6310822 | D101: =IFERROR(IF($B34=0,"",D34/$B34),"") -> 3.2407718 | E101: =IFERROR(IF($B34=0,"",E34/$B34),"") -> 3.4809144 | F101: =IFERROR(IF($B34=0,"",F34/$B34),"") -> 4.3255034 | G101: =IFERROR(IF($B34=0,"",G34/$B34),"") -> 4.7128775 | H101: =IFERROR(IF($B34=0,"",H34/$B34),"") -> 5.664849 | I101: =IFERROR(IF($B34=0,"",I34/$B34),"") -> 7.0853607 | ... Q101: =IFERROR(IF($B34=0,"",Q34/$B34),"") -> 10.451762
A102: Long-Term Marketable Securities | B102: =IFERROR(IF($B35=0,"",B35/$B35),"") -> 1 | C102: =IFERROR(IF($B35=0,"",C35/$B35),"") -> 2.1904612 | D102: =IFERROR(IF($B35=0,"",D35/$B35),"") -> 3.628136 | E102: =IFERROR(IF($B35=0,"",E35/$B35),"") -> 4.1831751 | F102: =IFERROR(IF($B35=0,"",F35/$B35),"") -> 5.1263046 | G102: =IFERROR(IF($B35=0,"",G35/$B35),"") -> 6.4615415 | H102: =IFERROR(IF($B35=0,"",H35/$B35),"") -> 6.7122209 | I102: =IFERROR(IF($B35=0,"",I35/$B35),"") -> 7.6686227 | ... Q102: =IFERROR(IF($B35=0,"",Q35/$B35),"") -> 3.0610453
A103: Goodwill | B103: =IFERROR(IF($B36=0,"",B36/$B36),"") -> 1 | C103: =IFERROR(IF($B36=0,"",C36/$B36),"") -> 1.2091768 | D103: =IFERROR(IF($B36=0,"",D36/$B36),"") -> 1.5317139 | E103: =IFERROR(IF($B36=0,"",E36/$B36),"") -> 2.1282051 | F103: =IFERROR(IF($B36=0,"",F36/$B36),"") -> 6.2294197 | G103: =IFERROR(IF($B36=0,"",G36/$B36),"") -> 6.9041835 | H103: =IFERROR(IF($B36=0,"",H36/$B36),"") -> 7.3063428 | I103: =IFERROR(IF($B36=0,"",I36/$B36),"") -> 7.7152497 | ... Q103: =IFERROR(IF($B36=0,"",Q36/$B36),"") -> 0
A104: Acquired Intangible Assets, Net | B104: =IFERROR(IF($B37=0,"",B37/$B37),"") -> 1 | C104: =IFERROR(IF($B37=0,"",C37/$B37),"") -> 10.339181 | D104: =IFERROR(IF($B37=0,"",D37/$B37),"") -> 12.350877 | E104: =IFERROR(IF($B37=0,"",E37/$B37),"") -> 12.219298 | F104: =IFERROR(IF($B37=0,"",F37/$B37),"") -> 12.111111 | G104: =IFERROR(IF($B37=0,"",G37/$B37),"") -> 11.383041 | H104: =IFERROR(IF($B37=0,"",H37/$B37),"") -> 9.374269 | I104: =IFERROR(IF($B37=0,"",I37/$B37),"") -> 6.7192982 | ... Q104: =IFERROR(IF($B37=0,"",Q37/$B37),"") -> 0
... A130: Total Liabilities & Shareholders' Equity | B130: =IFERROR(IF($B63=0,"",B63/$B63),"") -> 1 | C130: =IFERROR(IF($B63=0,"",C63/$B63),"") -> 1.5478366 | D130: =IFERROR(IF($B63=0,"",D63/$B63),"") -> 2.341806 | E130: =IFERROR(IF($B63=0,"",E63/$B63),"") -> 2.753282 | F130: =IFERROR(IF($B63=0,"",F63/$B63),"") -> 3.0836625 | G130: =IFERROR(IF($B63=0,"",G63/$B63),"") -> 3.8636261 | H130: =IFERROR(IF($B63=0,"",H63/$B63),"") -> 4.2787066 | I130: =IFERROR(IF($B63=0,"",I63/$B63),"") -> 4.9920727 | ... Q130: =IFERROR(IF($B63=0,"",Q63/$B63),"") -> 4.7782211
A132: Methodology
A133: Each year's amount ÷ FY2010 amount (FY2010 = 100%); zero base produces blank.

Sheet Financial Analyst
A1: Fiscal Year | B1: 2010 | C1: 2011 | D1: 2012 | E1: 2013 | F1: 2014 | G1: 2015 | H1: 2016 | I1: 2017 | J1: 2018 | K1: 2019 | L1: 2020 | M1: 2021 | N1: 2022 | O1: 2023 | P1: 2024 | Q1: 2025
A3: INCOME STATEMENT
A4: Net Sales / Revenue | B4: 65225 | C4: 108249 | D4: 156508 | E4: 170910 | F4: 182795 | G4: 233715 | H4: 215639 | I4: 229234 | J4: 265595 | K4: 260174 | L4: 274515 | M4: 365817 | N4: 394328 | O4: 383285 | P4: 391035 | Q4: 416161
A5: Total COGS | B5: 39541 | C5: 64431 | D5: 87846 | E5: 106606 | F5: 112258 | G5: 140089 | H5: 131376 | I5: 141048 | J5: 163756 | K5: 161782 | L5: 169559 | M5: 212981 | N5: 223546 | O5: 214137 | P5: 210352 | Q5: 220960
A6: Gross Profit | B6: =B4-B5 -> 25684 | C6: =C4-C5 -> 43818 | D6: =D4-D5 -> 68662 | E6: =E4-E5 -> 64304 | F6: =F4-F5 -> 70537 | G6: =G4-G5 -> 93626 | H6: =H4-H5 -> 84263 | I6: =I4-I5 -> 88186 | ... Q6: =Q4-Q5 -> 195201
A8: Research & Development | B8: 1782 | C8: 2429 | D8: 3381 | E8: 4475 | F8: 6041 | G8: 8067 | H8: 10045 | I8: 11581 | J8: 14236 | K8: 16217 | L8: 18752 | M8: 21914 | N8: 26251 | O8: 29915 | P8: 31370 | Q8: 34550
A9: Selling, General & Administrative | B9: 5517 | C9: 7599 | D9: 10040 | E9: 10830 | F9: 11993 | G9: 14329 | H9: 14194 | I9: 15261 | J9: 16705 | K9: 18245 | L9: 19916 | M9: 21973 | N9: 25094 | O9: 24932 | P9: 26097 | Q9: 27601
A10: Total Operating Expenses | B10: =B8+B9 -> 7299 | C10: =C8+C9 -> 10028 | D10: =D8+D9 -> 13421 | E10: =E8+E9 -> 15305 | F10: =F8+F9 -> 18034 | G10: =G8+G9 -> 22396 | H10: =H8+H9 -> 24239 | I10: =I8+I9 -> 26842 | ... Q10: =Q8+Q9 -> 62151
A11: Operating Income (EBIT) | B11: =B6-B10 -> 18385 | C11: =C6-C10 -> 33790 | D11: =D6-D10 -> 55241 | E11: =E6-E10 -> 48999 | F11: =F6-F10 -> 52503 | G11: =G6-G10 -> 71230 | H11: =H6-H10 -> 60024 | I11: =I6-I10 -> 61344 | ... Q11: =Q6-Q10 -> 133050
A12: % Growth | B12: =IFERROR(B11/#REF!-1,"") | C12: =IFERROR(C11/B11-1,"") -> 0.83791134 | D12: =IFERROR(D11/C11-1,"") -> 0.63483279 | E12: =IFERROR(E11/D11-1,"") -> -0.11299578 | F12: =IFERROR(F11/E11-1,"") -> 0.071511664 | G12: =IFERROR(G11/F11-1,"") -> 0.35668438 | H12: =IFERROR(H11/G11-1,"") -> -0.15732135 | I12: =IFERROR(I11/H11-1,"") -> 0.021991204 | J12: =IFERROR(J11/I11-1,"") -> 0.15574465 | ... Q12: =IFERROR(Q11/P11-1,"") -> 0.079811063
A14: Other Income/(Expense), Net | B14: 155 | C14: 415 | D14: 522 | E14: 1156 | F14: 980 | G14: 1285 | H14: 1348 | I14: 2745 | J14: 2005 | K14: 1807 | L14: 803 | M14: 258 | N14: -334 | O14: -565 | P14: 269 | Q14: -321
A15: Total Other Income/(Expense) | B15: =B14 -> 155 | C15: =C14 -> 415 | D15: =D14 -> 522 | E15: =E14 -> 1156 | F15: =F14 -> 980 | G15: =G14 -> 1285 | H15: =H14 -> 1348 | I15: =I14 -> 2745 | ... Q15: =Q14 -> -321
A18: Income Before Income Taxes | B18: =B11+B15 -> 18540 | C18: =C11+C15 -> 34205 | D18: =D11+D15 -> 55763 | E18: =E11+E15 -> 50155 | F18: =F11+F15 -> 53483 | G18: =G11+G15 -> 72515 | H18: =H11+H15 -> 61372 | I18: =I11+I15 -> 64089 | ... Q18: =Q11+Q15 -> 132729
A19: Provision for Income Taxes | B19: 4527 | C19: 8283 | D19: 14030 | E19: 13118 | F19: 13973 | G19: 19121 | H19: 15685 | I19: 15738 | J19: 13372 | K19: 10481 | L19: 9680 | M19: 14527 | N19: 19300 | O19: 16741 | P19: 29749 | Q19: 20719
A20: Net Income | B20: =B18-B19 -> 14013 | C20: =C18-C19 -> 25922 | D20: =D18-D19 -> 41733 | E20: =E18-E19 -> 37037 | F20: =F18-F19 -> 39510 | G20: =G18-G19 -> 53394 | H20: =H18-H19 -> 45687 | I20: =I18-I19 -> 48351 | ... Q20: =Q18-Q19 -> 112010
A23: Shares Used - Basic (000s) | B23: 909461 | C23: 924258 | D23: 934818 | E23: 925331 | F23: 6085572 | G23: 5753421 | H23: 5470820 | I23: 5217242 | J23: 4955377 | K23: 4617834 | L23: 17352119 | M23: 16701272 | N23: 16215963 | O23: 15744231 | P23: 15343783 | Q23: 14948500
A24: Shares Used - Diluted (000s) | B24: 924712 | C24: 936645 | D24: 945355 | E24: 931662 | F24: 6122663 | G24: 5793069 | H24: 5500281 | I24: 5251692 | J24: 5000109 | K24: 4648913 | L24: 17528214 | M24: 16864919 | N24: 16325819 | O24: 15812547 | P24: 15408095 | Q24: 15004697
A25: Cash Dividends Declared per Share | B25: 0 | C25: 0 | D25: 0.38 | E25: 1.64 | F25: 1.82 | G25: 1.98 | H25: 2.18 | I25: 2.4 | J25: 0 | K25: 0 | L25: 0 | M25: 0 | N25: 0 | O25: 0 | P25: 0 | Q25: 0
A28: BALANCE SHEET
A29: Cash & Cash Equivalents (FY1992 source reports Cash + ST Investments combined) | B29: 11261 | C29: 9815 | D29: 10746 | E29: 14259 | F29: 13844 | G29: 21120 | H29: 20484 | I29: 20289 | J29: 25913 | K29: 48844 | L29: 38016 | M29: 34940 | N29: 23646 | O29: 29965 | P29: 29943 | Q29: 35934
A30: Short-Term Investments / Marketable Securities | B30: 14359 | C30: 16137 | D30: 18383 | E30: 26287 | F30: 11233 | G30: 20481 | H30: 46671 | I30: 53892 | J30: 40388 | K30: 51713 | L30: 52927 | M30: 27699 | N30: 24658 | O30: 31590 | P30: 35228 | Q30: 18763
A31: Accounts Receivable, Net | B31: 5510 | C31: 5369 | D31: 10930 | E31: 13102 | F31: 17460 | G31: 16849 | H31: 15754 | I31: 17874 | J31: 23186 | K31: 22926 | L31: 16120 | M31: 26278 | N31: 28184 | O31: 29508 | P31: 33410 | Q31: 39777
A32: Inventories | B32: 1051 | C32: 776 | D32: 791 | E32: 1764 | F32: 2111 | G32: 2349 | H32: 2132 | I32: 4855 | J32: 3956 | K32: 4106 | L32: 4061 | M32: 6580 | N32: 4946 | O32: 6331 | P32: 7286 | Q32: 5718
A33: Deferred Tax Assets | B33: 1636 | C33: 2014 | D33: 2583 | E33: 3453 | F33: 4318 | G33: 5546 | H33: 0 | I33: 0 | J33: 0 | K33: 0 | L33: 0 | M33: 0 | N33: 0 | O33: 0 | P33: 0 | Q33: 0
A34: Vendor Non-Trade Receivables | B34: 4414 | C34: 6348 | D34: 7762 | E34: 7539 | F34: 9759 | G34: 13494 | H34: 13545 | I34: 17799 | J34: 25809 | K34: 22878 | L34: 21325 | M34: 25228 | N34: 32748 | O34: 31477 | P34: 32833 | Q34: 33180
A35: Other Current Assets | B35: 3447 | C35: 4529 | D35: 6458 | E35: 6882 | F35: 9806 | G35: 9539 | H35: 8283 | I35: 13936 | J35: 12087 | K35: 12352 | L35: 11264 | M35: 14111 | N35: 21223 | O35: 14695 | P35: 14287 | Q35: 14585
A36: Total Current Assets | B36: =B29+B30+B31+B32+B33+B34+B35 -> 41678 | C36: =C29+C30+C31+C32+C33+C34+C35 -> 44988 | D36: =D29+D30+D31+D32+D33+D34+D35 -> 57653 | E36: =E29+E30+E31+E32+E33+E34+E35 -> 73286 | F36: =F29+F30+F31+F32+F33+F34+F35 -> 68531 | G36: =G29+G30+G31+G32+G33+G34+G35 -> 89378 | H36: =H29+H30+H31+H32+H33+H34+H35 -> 106869 | I36: =I29+I30+I31+I32+I33+I34+I35 -> 128645 | ... Q36: =Q29+Q30+Q31+Q32+Q33+Q34+Q35 -> 147957
A38: Property, Plant & Equipment, Net | B38: 4768 | C38: 7777 | D38: 15452 | E38: 16597 | F38: 20624 | G38: 22471 | H38: 27010 | I38: 33783 | J38: 41304 | K38: 37378 | L38: 36766 | M38: 39440 | N38: 42117 | O38: 43715 | P38: 45680 | Q38: 49834
A39: Long-Term Marketable Securities | B39: 25391 | C39: 55618 | D39: 92122 | E39: 106215 | F39: 130162 | G39: 164065 | H39: 170430 | I39: 194714 | J39: 170799 | K39: 105341 | L39: 100887 | M39: 127877 | N39: 120805 | O39: 100544 | P39: 91479 | Q39: 77723
A40: Goodwill | B40: 741 | C40: 896 | D40: 1135 | E40: 1577 | F40: 4616 | G40: 5116 | H40: 5414 | I40: 5717 | J40: 0 | K40: 0 | L40: 0 | M40: 0 | N40: 0 | O40: 0 | P40: 0 | Q40: 0
A41: Acquired Intangible Assets, Net | B41: 342 | C41: 3536 | D41: 4224 | E41: 4179 | F41: 4142 | G41: 3893 | H41: 3206 | I41: 2298 | J41: 0 | K41: 0 | L41: 0 | M41: 0 | N41: 0 | O41: 0 | P41: 0 | Q41: 0
A42: Other Assets (legacy) | B42: 2263 | C42: 3556 | D42: 5478 | E42: 5146 | F42: 3764 | G42: 5556 | H42: 8757 | I42: 10162 | J42: 0 | K42: 0 | L42: 0 | M42: 0 | N42: 0 | O42: 0 | P42: 0 | Q42: 0
A43: Other Non-Current Assets | B43: 0 | C43: 0 | D43: 0 | E43: 0 | F43: 0 | G43: 0 | H43: 0 | I43: 0 | J43: 22283 | K43: 32978 | L43: 42522 | M43: 48849 | N43: 54428 | O43: 64758 | P43: 74834 | Q43: 83727
A44: Total Non-Current Assets | B44: =B38+B39+B40+B41+B42+B43 -> 33505 | C44: =C38+C39+C40+C41+C42+C43 -> 71383 | D44: =D38+D39+D40+D41+D42+D43 -> 118411 | E44: =E38+E39+E40+E41+E42+E43 -> 133714 | F44: =F38+F39+F40+F41+F42+F43 -> 163308 | G44: =G38+G39+G40+G41+G42+G43 -> 201101 | H44: =H38+H39+H40+H41+H42+H43 -> 214817 | I44: =I38+I39+I40+I41+I42+I43 -> 246674 | ... Q44: =Q38+Q39+Q40+Q41+Q42+Q43 -> 211284
A45: Total Assets | B45: =B36+B44 -> 75183 | C45: =C36+C44 -> 116371 | D45: =D36+D44 -> 176064 | E45: =E36+E44 -> 207000 | F45: =F36+F44 -> 231839 | G45: =G36+G44 -> 290479 | H45: =H36+H44 -> 321686 | I45: =I36+I44 -> 375319 | ... Q45: =Q36+Q44 -> 359241
A47: Short-Term Borrowings / Notes Payable | B47: 0 | C47: 0 | D47: 0 | E47: 0 | F47: 0 | G47: 0 | H47: 0 | I47: 0 | J47: 0 | K47: 0 | L47: 0 | M47: 0 | N47: 0 | O47: 0 | P47: 0 | Q47: 0
A48: Accounts Payable | B48: 12015 | C48: 14632 | D48: 21175 | E48: 22367 | F48: 30196 | G48: 35490 | H48: 37294 | I48: 49049 | J48: 55888 | K48: 46236 | L48: 42296 | M48: 54763 | N48: 64115 | O48: 62611 | P48: 68960 | Q48: 69860
A49: Accrued Expenses | B49: 5723 | C49: 9247 | D49: 11414 | E49: 13856 | F49: 18453 | G49: 25181 | H49: 22027 | I49: 25744 | J49: 0 | K49: 0 | L49: 0 | M49: 0 | N49: 0 | O49: 0 | P49: 0 | Q49: 0
A50: Deferred Revenue - Current | B50: 2984 | C50: 4091 | D50: 5953 | E50: 7435 | F50: 8491 | G50: 8940 | H50: 8080 | I50: 7548 | J50: 7543 | K50: 5522 | L50: 6643 | M50: 7612 | N50: 7912 | O50: 8061 | P50: 8249 | Q50: 9055
A51: Other Current Liabilities | B51: 0 | C51: 0 | D51: 0 | E51: 0 | F51: 0 | G51: 0 | H51: 0 | I51: 0 | J51: 32687 | K51: 37720 | L51: 42684 | M51: 47493 | N51: 60845 | O51: 58829 | P51: 78304 | Q51: 66387
A52: Commercial Paper | B52: 0 | C52: 0 | D52: 0 | E52: 0 | F52: 6308 | G52: 8499 | H52: 8105 | I52: 11977 | J52: 11964 | K52: 5980 | L52: 4996 | M52: 6000 | N52: 9982 | O52: 5985 | P52: 9967 | Q52: 7979
A53: Current Debt / Term Debt | B53: 0 | C53: 0 | D53: 0 | E53: 0 | F53: 0 | G53: 2500 | H53: 3500 | I53: 6496 | J53: 8784 | K53: 10260 | L53: 8773 | M53: 9613 | N53: 11128 | O53: 9822 | P53: 10912 | Q53: 12350
A54: Total Current Liabilities | B54: =SUM(B47:B53) -> 20722 | C54: =SUM(C47:C53) -> 27970 | D54: =SUM(D47:D53) -> 38542 | E54: =SUM(E47:E53) -> 43658 | F54: =SUM(F47:F53) -> 63448 | G54: =SUM(G47:G53) -> 80610 | H54: =SUM(H47:H53) -> 79006 | I54: =SUM(I47:I53) -> 100814 | ... Q54: =SUM(Q47:Q53) -> 165631
A56: Long-Term Debt / Term Debt | B56: 0 | C56: 0 | D56: 0 | E56: 16960 | F56: 28987 | G56: 53463 | H56: 75427 | I56: 97207 | J56: 93735 | K56: 91807 | L56: 98667 | M56: 109106 | N56: 98959 | O56: 95281 | P56: 85750 | Q56: 78328
A57: Deferred Revenue - Non-Current | B57: 1139 | C57: 1686 | D57: 2648 | E57: 2625 | F57: 3031 | G57: 3624 | H57: 2930 | I57: 2836 | J57: 2797 | K57: 0 | L57: 0 | M57: 0 | N57: 0 | O57: 0 | P57: 0 | Q57: 0
A58: Other Non-Current Liabilities | B58: 5531 | C58: 10100 | D58: 16664 | E58: 20208 | F58: 24826 | G58: 33427 | H58: 36074 | I58: 40415 | J58: 45180 | K58: 50503 | L58: 54490 | M58: 53325 | N58: 49142 | O58: 49848 | P58: 45888 | Q58: 41549
A59: Total Non-Current Liabilities | B59: =SUM(B56:B58) -> 6670 | C59: =SUM(C56:C58) -> 11786 | D59: =SUM(D56:D58) -> 19312 | E59: =SUM(E56:E58) -> 39793 | F59: =SUM(F56:F58) -> 56844 | G59: =SUM(G56:G58) -> 90514 | H59: =SUM(H56:H58) -> 114431 | I59: =SUM(I56:I58) -> 140458 | ... Q59: =SUM(Q56:Q58) -> 119877
A60: Total Liabilities | B60: =B54+B59 -> 27392 | C60: =C54+C59 -> 39756 | D60: =D54+D59 -> 57854 | E60: =E54+E59 -> 83451 | F60: =F54+F59 -> 120292 | G60: =G54+G59 -> 171124 | H60: =H54+H59 -> 193437 | I60: =I54+I59 -> 241272 | ... Q60: =Q54+Q59 -> 285508
A62: Common Stock & Additional Paid-In Capital | B62: 10668 | C62: 13331 | D62: 16422 | E62: 19764 | F62: 23313 | G62: 27416 | H62: 31251 | I62: 35867 | J62: 40201 | K62: 45174 | L62: 50779 | M62: 57365 | N62: 64849 | O62: 73812 | P62: 83276 | Q62: 93568
A63: Retained Earnings | B63: 37169 | C63: 62841 | D63: 101289 | E63: 104256 | F63: 87152 | G63: 92284 | H63: 96364 | I63: 98330 | J63: 70400 | K63: 45898 | L63: 14966 | M63: 5562 | N63: 0 | O63: 0 | P63: 0 | Q63: 0
A64: Accumulated Deficit | B64: 0 | C64: 0 | D64: 0 | E64: 0 | F64: 0 | G64: 0 | H64: 0 | I64: 0 | J64: 0 | K64: 0 | L64: 0 | M64: 0 | N64: -3068 | O64: -214 | P64: -19154 | Q64: -14264
A65: Accumulated Other Comprehensive Income/(Loss) | B65: -46 | C65: 443 | D65: 499 | E65: -471 | F65: 1082 | G65: -345 | H65: 634 | I65: -150 | J65: -3454 | K65: -584 | L65: -406 | M65: 163 | N65: -11109 | O65: -11452 | P65: -7172 | Q65: -5571
A66: Total Shareholders' Equity | B66: =SUM(B62:B65) -> 47791 | C66: =SUM(C62:C65) -> 76615 | D66: =SUM(D62:D65) -> 118210 | E66: =SUM(E62:E65) -> 123549 | F66: =SUM(F62:F65) -> 111547 | G66: =SUM(G62:G65) -> 119355 | H66: =SUM(H62:H65) -> 128249 | I66: =SUM(I62:I65) -> 134047 | ... Q66: =SUM(Q62:Q65) -> 73733
A67: Total Liabilities & Shareholders' Equity | B67: =B60+B66 -> 75183 | C67: =C60+C66 -> 116371 | D67: =D60+D66 -> 176064 | E67: =E60+E66 -> 207000 | F67: =F60+F66 -> 231839 | G67: =G60+G66 -> 290479 | H67: =H60+H66 -> 321686 | I67: =I60+I66 -> 375319 | ... Q67: =Q60+Q66 -> 359241
A72: PROFITABILITY & GROWTH RATIOS
A73: Revenue growth rate | B73: ="" | C73: =IFERROR(C4/B4-1,"") -> 0.65962438 | D73: =IFERROR(D4/C4-1,"") -> 0.44581474 | E73: =IFERROR(E4/D4-1,"") -> 0.092020855 | F73: =IFERROR(F4/E4-1,"") -> 0.069539524 | G73: =IFERROR(G4/F4-1,"") -> 0.27856342 | H73: =IFERROR(H4/G4-1,"") -> -0.077342062 | I73: =IFERROR(I4/H4-1,"") -> 0.063045182 | J73: =IFERROR(J4/I4-1,"") -> 0.15861958 | ... Q73: =IFERROR(Q4/P4-1,"") -> 0.064255118
A74: Gross profit margin | B74: =IFERROR(B6/B4,"") -> 0.39377539 | C74: =IFERROR(C6/C4,"") -> 0.40478896 | D74: =IFERROR(D6/D4,"") -> 0.4387124 | E74: =IFERROR(E6/E4,"") -> 0.37624481 | F74: =IFERROR(F6/F4,"") -> 0.38588036 | G74: =IFERROR(G6/G4,"") -> 0.40059902 | H74: =IFERROR(H6/H4,"") -> 0.39075956 | I74: =IFERROR(I6/I4,"") -> 0.3846986 | ... Q74: =IFERROR(Q6/Q4,"") -> 0.46905164
A75: EBIT margin | B75: =IFERROR(B11/B4,"") -> 0.28187045 | C75: =IFERROR(C11/C4,"") -> 0.31215069 | D75: =IFERROR(D11/D4,"") -> 0.35295959 | E75: =IFERROR(E11/E4,"") -> 0.28669475 | F75: =IFERROR(F11/F4,"") -> 0.28722339 | G75: =IFERROR(G11/G4,"") -> 0.30477291 | H75: =IFERROR(H11/H4,"") -> 0.2783541 | I75: =IFERROR(I11/I4,"") -> 0.26760428 | ... Q75: =IFERROR(Q11/Q4,"") -> 0.319708
A76: Net profit margin | B76: =IFERROR(B20/B4,"") -> 0.21484094 | C76: =IFERROR(C20/C4,"") -> 0.23946642 | D76: =IFERROR(D20/D4,"") -> 0.26665091 | E76: =IFERROR(E20/E4,"") -> 0.2167047 | F76: =IFERROR(F20/F4,"") -> 0.21614377 | G76: =IFERROR(G20/G4,"") -> 0.22845774 | H76: =IFERROR(H20/H4,"") -> 0.21186798 | I76: =IFERROR(I20/I4,"") -> 0.21092421 | ... Q76: =IFERROR(Q20/Q4,"") -> 0.26915064
A77: Return on equity (ROE) | B77: ="" | C77: =IFERROR(C20/AVERAGE(B66:C66),"") -> 0.41673231 | D77: =IFERROR(D20/AVERAGE(C66:D66),"") -> 0.42841524 | E77: =IFERROR(E20/AVERAGE(D66:E66),"") -> 0.30639604 | F77: =IFERROR(F20/AVERAGE(E66:F66),"") -> 0.33611801 | G77: =IFERROR(G20/AVERAGE(F66:G66),"") -> 0.46248192 | H77: =IFERROR(H20/AVERAGE(G66:H66),"") -> 0.36903281 | I77: =IFERROR(I20/AVERAGE(H66:I66),"") -> 0.36867508 | J77: =IFERROR(J20/AVERAGE(I66:J66),"") -> 0.49363583 | ... Q77: =IFERROR(Q20/AVERAGE(P66:Q66),"") -> 1.7142245
A78: Return on assets (ROA) | B78: ="" | C78: =IFERROR(C20/AVERAGE(B45:C45),"") -> 0.27064953 | D78: =IFERROR(D20/AVERAGE(C45:D45),"") -> 0.28541727 | E78: =IFERROR(E20/AVERAGE(D45:E45),"") -> 0.19337239 | F78: =IFERROR(F20/AVERAGE(E45:F45),"") -> 0.18006604 | G78: =IFERROR(G20/AVERAGE(F45:G45),"") -> 0.20445016 | H78: =IFERROR(H20/AVERAGE(G45:H45),"") -> 0.14926368 | I78: =IFERROR(I20/AVERAGE(H45:I45),"") -> 0.13873932 | J78: =IFERROR(J20/AVERAGE(I45:J45),"") -> 0.16066792 | ... Q78: =IFERROR(Q20/AVERAGE(P45:Q45),"") -> 0.30932547
A79: R&D as % of revenue | B79: =IFERROR(B8/B4,"") -> 0.027320813 | C79: =IFERROR(C8/C4,"") -> 0.022439006 | D79: =IFERROR(D8/D4,"") -> 0.02160273 | E79: =IFERROR(E8/E4,"") -> 0.026183371 | F79: =IFERROR(F8/F4,"") -> 0.03304795 | G79: =IFERROR(G8/G4,"") -> 0.034516398 | H79: =IFERROR(H8/H4,"") -> 0.046582483 | I79: =IFERROR(I8/I4,"") -> 0.050520429 | ... Q79: =IFERROR(Q8/Q4,"") -> 0.083020754
A80: Effective tax rate | B80: =IFERROR(B19/B18,"") -> 0.24417476 | C80: =IFERROR(C19/C18,"") -> 0.24215758 | D80: =IFERROR(D19/D18,"") -> 0.25160052 | E80: =IFERROR(E19/E18,"") -> 0.2615492 | F80: =IFERROR(F19/F18,"") -> 0.26126059 | G80: =IFERROR(G19/G18,"") -> 0.26368338 | H80: =IFERROR(H19/H18,"") -> 0.25557257 | I80: =IFERROR(I19/I18,"") -> 0.24556476 | ... Q80: =IFERROR(Q19/Q18,"") -> 0.15610002
A83: LIQUIDITY RATIOS
A84: Current ratio | B84: =IFERROR(B36/B54,"") -> 2.0112923 | C84: =IFERROR(C36/C54,"") -> 1.6084376 | D84: =IFERROR(D36/D54,"") -> 1.4958487 | E84: =IFERROR(E36/E54,"") -> 1.6786385 | F84: =IFERROR(F36/F54,"") -> 1.0801128 | G84: =IFERROR(G36/G54,"") -> 1.1087706 | H84: =IFERROR(H36/H54,"") -> 1.3526694 | I84: =IFERROR(I36/I54,"") -> 1.2760628 | ... Q84: =IFERROR(Q36/Q54,"") -> 0.89329292
A85: Quick ratio (cash + short-term investments + trade receivables) | B85: =IFERROR((B29+B30+B31)/B54,"") -> 1.5022681 | C85: =IFERROR((C29+C30+C31)/C54,"") -> 1.1198069 | D85: =IFERROR((D29+D30+D31)/D54,"") -> 1.0393597 | E85: =IFERROR((E29+E30+E31)/E54,"") -> 1.228824 | F85: =IFERROR((F29+F30+F31)/F54,"") -> 0.67042302 | G85: =IFERROR((G29+G30+G31)/G54,"") -> 0.72509614 | H85: =IFERROR((H29+H30+H31)/H54,"") -> 1.0494013 | I85: =IFERROR((I29+I30+I31)/I54,"") -> 0.91311723 | ... Q85: =IFERROR((Q29+Q30+Q31)/Q54,"") -> 0.57038839
A86: Cash ratio | B86: =IFERROR((B29+B30)/B54,"") -> 1.2363671 | C86: =IFERROR((C29+C30)/C54,"") -> 0.92785127 | D86: =IFERROR((D29+D30)/D54,"") -> 0.75577292 | E86: =IFERROR((E29+E30)/E54,"") -> 0.92871868 | F86: =IFERROR((F29+F30)/F54,"") -> 0.39523704 | G86: =IFERROR((G29+G30)/G54,"") -> 0.51607741 | H86: =IFERROR((H29+H30)/H54,"") -> 0.84999873 | I86: =IFERROR((I29+I30)/I54,"") -> 0.73582042 | ... Q86: =IFERROR((Q29+Q30)/Q54,"") -> 0.33023407
A87: Net working capital ($ millions) | B87: =IFERROR(B36-B54,"") -> 20956 | C87: =IFERROR(C36-C54,"") -> 17018 | D87: =IFERROR(D36-D54,"") -> 19111 | E87: =IFERROR(E36-E54,"") -> 29628 | F87: =IFERROR(F36-F54,"") -> 5083 | G87: =IFERROR(G36-G54,"") -> 8768 | H87: =IFERROR(H36-H54,"") -> 27863 | I87: =IFERROR(I36-I54,"") -> 27831 | ... Q87: =IFERROR(Q36-Q54,"") -> -17674
A90: EFFICIENCY RATIOS
A91: Inventory turnover | B91: ="" | C91: =IFERROR(C5/AVERAGE(B32:C32),"") -> 70.53202 | D91: =IFERROR(D5/AVERAGE(C32:D32),"") -> 112.11997 | E91: =IFERROR(E5/AVERAGE(D32:E32),"") -> 83.448924 | F91: =IFERROR(F5/AVERAGE(E32:F32),"") -> 57.939613 | G91: =IFERROR(G5/AVERAGE(F32:G32),"") -> 62.820179 | H91: =IFERROR(H5/AVERAGE(G32:H32),"") -> 58.636911 | I91: =IFERROR(I5/AVERAGE(H32:I32),"") -> 40.37441 | J91: =IFERROR(J5/AVERAGE(I32:J32),"") -> 37.170809 | ... Q91: =IFERROR(Q5/AVERAGE(P32:Q32),"") -> 33.98339
A92: Accounts receivable turnover | B92: ="" | C92: =IFERROR(C4/AVERAGE(B31:C31),"") -> 19.900542 | D92: =IFERROR(D4/AVERAGE(C31:D31),"") -> 19.204614 | E92: =IFERROR(E4/AVERAGE(D31:E31),"") -> 14.223535 | F92: =IFERROR(F4/AVERAGE(E31:F31),"") -> 11.962241 | G92: =IFERROR(G4/AVERAGE(F31:G31),"") -> 13.624122 | H92: =IFERROR(H4/AVERAGE(G31:H31),"") -> 13.228169 | I92: =IFERROR(I4/AVERAGE(H31:I31),"") -> 13.63352 | J92: =IFERROR(J4/AVERAGE(I31:J31),"") -> 12.936922 | ... Q92: =IFERROR(Q4/AVERAGE(P31:Q31),"") -> 11.372539
A93: Accounts payable turnover | B93: ="" | C93: =IFERROR(C5/AVERAGE(B48:C48),"") -> 4.8358915 | D93: =IFERROR(D5/AVERAGE(C48:D48),"") -> 4.9066384 | E93: =IFERROR(E5/AVERAGE(D48:E48),"") -> 4.8966974 | F93: =IFERROR(F5/AVERAGE(E48:F48),"") -> 4.2713696 | G93: =IFERROR(G5/AVERAGE(F48:G48),"") -> 4.2654142 | H93: =IFERROR(H5/AVERAGE(G48:H48),"") -> 3.6100242 | I93: =IFERROR(I5/AVERAGE(H48:I48),"") -> 3.2671554 | J93: =IFERROR(J5/AVERAGE(I48:J48),"") -> 3.1210345 | ... Q93: =IFERROR(Q5/AVERAGE(P48:Q48),"") -> 3.183403
A94: Inventory processing period (360 days) | B94: ="" | C94: =IFERROR(360*AVERAGE(B32:C32)/C5,"") -> 5.1040648 | D94: =IFERROR(360*AVERAGE(C32:D32)/D5,"") -> 3.2108463 | E94: =IFERROR(360*AVERAGE(D32:E32)/E5,"") -> 4.3140161 | F94: =IFERROR(360*AVERAGE(E32:F32)/F5,"") -> 6.2133656 | G94: =IFERROR(360*AVERAGE(F32:G32)/G5,"") -> 5.7306427 | H94: =IFERROR(360*AVERAGE(G32:H32)/H5,"") -> 6.1394775 | I94: =IFERROR(360*AVERAGE(H32:I32)/I5,"") -> 8.9165391 | J94: =IFERROR(360*AVERAGE(I32:J32)/J5,"") -> 9.6850192 | ... Q94: =IFERROR(360*AVERAGE(P32:Q32)/Q5,"") -> 10.593411
A95: Receivables collection period (360 days) | B95: ="" | C95: =IFERROR(360*AVERAGE(B31:C31)/C4,"") -> 18.089959 | D95: =IFERROR(360*AVERAGE(C31:D31)/D4,"") -> 18.745495 | E95: =IFERROR(360*AVERAGE(D31:E31)/E4,"") -> 25.310163 | F95: =IFERROR(360*AVERAGE(E31:F31)/F4,"") -> 30.094696 | G95: =IFERROR(360*AVERAGE(F31:G31)/G4,"") -> 26.423721 | H95: =IFERROR(360*AVERAGE(G31:H31)/H4,"") -> 27.21465 | I95: =IFERROR(360*AVERAGE(H31:I31)/I4,"") -> 26.405507 | J95: =IFERROR(360*AVERAGE(I31:J31)/J4,"") -> 27.827331 | ... Q95: =IFERROR(360*AVERAGE(P31:Q31)/Q4,"") -> 31.655201
A96: Payables payment period (360 days) | B96: ="" | C96: =IFERROR(360*AVERAGE(B48:C48)/C5,"") -> 74.443358 | D96: =IFERROR(360*AVERAGE(C48:D48)/D5,"") -> 73.369988 | E96: =IFERROR(360*AVERAGE(D48:E48)/E5,"") -> 73.518939 | F96: =IFERROR(360*AVERAGE(E48:F48)/F5,"") -> 84.2821 | G96: =IFERROR(360*AVERAGE(F48:G48)/G5,"") -> 84.399774 | H96: =IFERROR(360*AVERAGE(G48:H48)/H5,"") -> 99.722324 | I96: =IFERROR(360*AVERAGE(H48:I48)/I5,"") -> 110.1876 | J96: =IFERROR(360*AVERAGE(I48:J48)/J5,"") -> 115.34637 | ... Q96: =IFERROR(360*AVERAGE(P48:Q48)/Q5,"") -> 113.08653
A97: Cash conversion cycle (360 days) | B97: ="" | C97: =IFERROR(360*AVERAGE(B32:C32)/C5+360*AVERAGE(B31:C31)/C4-360*AVERAGE(B48:C48)/C5,"") -> -51.249334 | D97: =IFERROR(360*AVERAGE(C32:D32)/D5+360*AVERAGE(C31:D31)/D4-360*AVERAGE(C48:D48)/D5,"") -> -51.413647 | E97: =IFERROR(360*AVERAGE(D32:E32)/E5+360*AVERAGE(D31:E31)/E4-360*AVERAGE(D48:E48)/E5,"") -> -43.89476 | F97: =IFERROR(360*AVERAGE(E32:F32)/F5+360*AVERAGE(E31:F31)/F4-360*AVERAGE(E48:F48)/F5,"") -> -47.974038 | G97: =IFERROR(360*AVERAGE(F32:G32)/G5+360*AVERAGE(F31:G31)/G4-360*AVERAGE(F48:G48)/G5,"") -> -52.245411 | H97: =IFERROR(360*AVERAGE(G32:H32)/H5+360*AVERAGE(G31:H31)/H4-360*AVERAGE(G48:H48)/H5,"") -> -66.368196 | I97: =IFERROR(360*AVERAGE(H32:I32)/I5+360*AVERAGE(H31:I31)/I4-360*AVERAGE(H48:I48)/I5,"") -> -74.86555 | J97: =IFERROR(360*AVERAGE(I32:J32)/J5+360*AVERAGE(I31:J31)/J4-360*AVERAGE(I48:J48)/J5,"") -> -77.834019 | ... Q97: =IFERROR(360*AVERAGE(P32:Q32)/Q5+360*AVERAGE(P31:Q31)/Q4-360*AVERAGE(P48:Q48)/Q5,"") -> -70.83792
A98: Total asset turnover | B98: ="" | C98: =IFERROR(C4/AVERAGE(B45:C45),"") -> 1.1302192 | D98: =IFERROR(D4/AVERAGE(C45:D45),"") -> 1.070378 | E98: =IFERROR(E4/AVERAGE(D45:E45),"") -> 0.89233131 | F98: =IFERROR(F4/AVERAGE(E45:F45),"") -> 0.83308457 | G98: =IFERROR(G4/AVERAGE(F45:G45),"") -> 0.89491459 | H98: =IFERROR(H4/AVERAGE(G45:H45),"") -> 0.70451267 | I98: =IFERROR(I4/AVERAGE(H45:I45),"") -> 0.6577686 | J98: =IFERROR(J4/AVERAGE(I45:J45),"") -> 0.71681304 | ... Q98: =IFERROR(Q4/AVERAGE(P45:Q45),"") -> 1.1492652
A101: LEVERAGE & SOLVENCY RATIOS
A102: Total liabilities / total assets | B102: =IFERROR(B60/B45,"") -> 0.36433768 | C102: =IFERROR(C60/C45,"") -> 0.34163151 | D102: =IFERROR(D60/D45,"") -> 0.32859642 | E102: =IFERROR(E60/E45,"") -> 0.40314493 | F102: =IFERROR(F60/F45,"") -> 0.51886007 | G102: =IFERROR(G60/G45,"") -> 0.58910971 | H102: =IFERROR(H60/H45,"") -> 0.60132241 | I102: =IFERROR(I60/I45,"") -> 0.64284515 | ... Q102: =IFERROR(Q60/Q45,"") -> 0.79475338
A103: Debt-to-equity (interest-bearing debt) | B103: =IFERROR((B47+B52+B53+B56)/B66,"") -> 0 | C103: =IFERROR((C47+C52+C53+C56)/C66,"") -> 0 | D103: =IFERROR((D47+D52+D53+D56)/D66,"") -> 0 | E103: =IFERROR((E47+E52+E53+E56)/E66,"") -> 0.13727347 | F103: =IFERROR((F47+F52+F53+F56)/F66,"") -> 0.31641371 | G103: =IFERROR((G47+G52+G53+G56)/G66,"") -> 0.5400863 | H103: =IFERROR((H47+H52+H53+H56)/H66,"") -> 0.67861738 | I103: =IFERROR((I47+I52+I53+I56)/I66,"") -> 0.86298089 | ... Q103: =IFERROR((Q47+Q52+Q53+Q56)/Q66,"") -> 1.3380305
A104: Debt-to-assets (interest-bearing debt) | B104: =IFERROR((B47+B52+B53+B56)/B45,"") -> 0 | C104: =IFERROR((C47+C52+C53+C56)/C45,"") -> 0 | D104: =IFERROR((D47+D52+D53+D56)/D45,"") -> 0 | E104: =IFERROR((E47+E52+E53+E56)/E45,"") -> 0.081932367 | F104: =IFERROR((F47+F52+F53+F56)/F45,"") -> 0.15223927 | G104: =IFERROR((G47+G52+G53+G56)/G45,"") -> 0.22191621 | H104: =IFERROR((H47+H52+H53+H56)/H45,"") -> 0.27054954 | I104: =IFERROR((I47+I52+I53+I56)/I45,"") -> 0.30821781 | ... Q104: =IFERROR((Q47+Q52+Q53+Q56)/Q45,"") -> 0.27462623
A105: Equity multiplier | B105: =IFERROR(B45/B66,"") -> 1.5731623 | C105: =IFERROR(C45/C66,"") -> 1.5189062 | D105: =IFERROR(D45/D66,"") -> 1.4894171 | E105: =IFERROR(E45/E66,"") -> 1.6754486 | F105: =IFERROR(F45/F66,"") -> 2.0783974 | G105: =IFERROR(G45/G66,"") -> 2.4337397 | H105: =IFERROR(H45/H66,"") -> 2.5082925 | I105: =IFERROR(I45/I66,"") -> 2.799906 | ... Q105: =IFERROR(Q45/Q66,"") -> 4.8721875
A106: Long-term debt / total capitalization | B106: =IFERROR(B56/(B56+B66),"") -> 0 | C106: =IFERROR(C56/(C56+C66),"") -> 0 | D106: =IFERROR(D56/(D56+D66),"") -> 0 | E106: =IFERROR(E56/(E56+E66),"") -> 0.12070401 | F106: =IFERROR(F56/(F56+F66),"") -> 0.20626325 | G106: =IFERROR(G56/(G56+G66),"") -> 0.30936014 | H106: =IFERROR(H56/(H56+H66),"") -> 0.37032836 | I106: =IFERROR(I56/(I56+I66),"") -> 0.42034732 | ... Q106: =IFERROR(Q56/(Q56+Q66),"") -> 0.51510907
A135: Method: balance-sheet average ratios use prior/current fiscal-year values; FY2010 unavailable. Days use 360.

Sheet Investment Ratios
A1: Fiscal Year | B1: 2010 | C1: 2011 | D1: 2012 | E1: 2013 | F1: 2014 | G1: 2015 | H1: 2016 | I1: 2017 | J1: 2018 | K1: 2019 | L1: 2020 | M1: 2021 | N1: 2022 | O1: 2023 | P1: 2024 | Q1: 2025
A3: INCOME STATEMENT
A4: Net Sales / Revenue | B4: 65225 | C4: 108249 | D4: 156508 | E4: 170910 | F4: 182795 | G4: 233715 | H4: 215639 | I4: 229234 | J4: 265595 | K4: 260174 | L4: 274515 | M4: 365817 | N4: 394328 | O4: 383285 | P4: 391035 | Q4: 416161
A5: Total COGS | B5: 39541 | C5: 64431 | D5: 87846 | E5: 106606 | F5: 112258 | G5: 140089 | H5: 131376 | I5: 141048 | J5: 163756 | K5: 161782 | L5: 169559 | M5: 212981 | N5: 223546 | O5: 214137 | P5: 210352 | Q5: 220960
A6: Gross Profit | B6: =B4-B5 -> 25684 | C6: =C4-C5 -> 43818 | D6: =D4-D5 -> 68662 | E6: =E4-E5 -> 64304 | F6: =F4-F5 -> 70537 | G6: =G4-G5 -> 93626 | H6: =H4-H5 -> 84263 | I6: =I4-I5 -> 88186 | ... Q6: =Q4-Q5 -> 195201
A8: Research & Development | B8: 1782 | C8: 2429 | D8: 3381 | E8: 4475 | F8: 6041 | G8: 8067 | H8: 10045 | I8: 11581 | J8: 14236 | K8: 16217 | L8: 18752 | M8: 21914 | N8: 26251 | O8: 29915 | P8: 31370 | Q8: 34550
A9: Selling, General & Administrative | B9: 5517 | C9: 7599 | D9: 10040 | E9: 10830 | F9: 11993 | G9: 14329 | H9: 14194 | I9: 15261 | J9: 16705 | K9: 18245 | L9: 19916 | M9: 21973 | N9: 25094 | O9: 24932 | P9: 26097 | Q9: 27601
A10: Total Operating Expenses | B10: =B8+B9 -> 7299 | C10: =C8+C9 -> 10028 | D10: =D8+D9 -> 13421 | E10: =E8+E9 -> 15305 | F10: =F8+F9 -> 18034 | G10: =G8+G9 -> 22396 | H10: =H8+H9 -> 24239 | I10: =I8+I9 -> 26842 | ... Q10: =Q8+Q9 -> 62151
A11: Operating Income (EBIT) | B11: =B6-B10 -> 18385 | C11: =C6-C10 -> 33790 | D11: =D6-D10 -> 55241 | E11: =E6-E10 -> 48999 | F11: =F6-F10 -> 52503 | G11: =G6-G10 -> 71230 | H11: =H6-H10 -> 60024 | I11: =I6-I10 -> 61344 | ... Q11: =Q6-Q10 -> 133050
A12: % Growth | B12: =IFERROR(B11/#REF!-1,"") | C12: =IFERROR(C11/B11-1,"") -> 0.83791134 | D12: =IFERROR(D11/C11-1,"") -> 0.63483279 | E12: =IFERROR(E11/D11-1,"") -> -0.11299578 | F12: =IFERROR(F11/E11-1,"") -> 0.071511664 | G12: =IFERROR(G11/F11-1,"") -> 0.35668438 | H12: =IFERROR(H11/G11-1,"") -> -0.15732135 | I12: =IFERROR(I11/H11-1,"") -> 0.021991204 | J12: =IFERROR(J11/I11-1,"") -> 0.15574465 | ... Q12: =IFERROR(Q11/P11-1,"") -> 0.079811063
A14: Other Income/(Expense), Net | B14: 155 | C14: 415 | D14: 522 | E14: 1156 | F14: 980 | G14: 1285 | H14: 1348 | I14: 2745 | J14: 2005 | K14: 1807 | L14: 803 | M14: 258 | N14: -334 | O14: -565 | P14: 269 | Q14: -321
A15: Total Other Income/(Expense) | B15: =B14 -> 155 | C15: =C14 -> 415 | D15: =D14 -> 522 | E15: =E14 -> 1156 | F15: =F14 -> 980 | G15: =G14 -> 1285 | H15: =H14 -> 1348 | I15: =I14 -> 2745 | ... Q15: =Q14 -> -321
A18: Income Before Income Taxes | B18: =B11+B15 -> 18540 | C18: =C11+C15 -> 34205 | D18: =D11+D15 -> 55763 | E18: =E11+E15 -> 50155 | F18: =F11+F15 -> 53483 | G18: =G11+G15 -> 72515 | H18: =H11+H15 -> 61372 | I18: =I11+I15 -> 64089 | ... Q18: =Q11+Q15 -> 132729
A19: Provision for Income Taxes | B19: 4527 | C19: 8283 | D19: 14030 | E19: 13118 | F19: 13973 | G19: 19121 | H19: 15685 | I19: 15738 | J19: 13372 | K19: 10481 | L19: 9680 | M19: 14527 | N19: 19300 | O19: 16741 | P19: 29749 | Q19: 20719
A20: Net Income | B20: =B18-B19 -> 14013 | C20: =C18-C19 -> 25922 | D20: =D18-D19 -> 41733 | E20: =E18-E19 -> 37037 | F20: =F18-F19 -> 39510 | G20: =G18-G19 -> 53394 | H20: =H18-H19 -> 45687 | I20: =I18-I19 -> 48351 | ... Q20: =Q18-Q19 -> 112010
A23: Shares Used - Basic (000s) | B23: 909461 | C23: 924258 | D23: 934818 | E23: 925331 | F23: 6085572 | G23: 5753421 | H23: 5470820 | I23: 5217242 | J23: 4955377 | K23: 4617834 | L23: 17352119 | M23: 16701272 | N23: 16215963 | O23: 15744231 | P23: 15343783 | Q23: 14948500
A24: Shares Used - Diluted (000s) | B24: 924712 | C24: 936645 | D24: 945355 | E24: 931662 | F24: 6122663 | G24: 5793069 | H24: 5500281 | I24: 5251692 | J24: 5000109 | K24: 4648913 | L24: 17528214 | M24: 16864919 | N24: 16325819 | O24: 15812547 | P24: 15408095 | Q24: 15004697
A25: Cash Dividends Declared per Share | B25: 0 | C25: 0 | D25: 0.38 | E25: 1.64 | F25: 1.82 | G25: 1.98 | H25: 2.18 | I25: 2.4 | J25: 0 | K25: 0 | L25: 0 | M25: 0 | N25: 0 | O25: 0 | P25: 0 | Q25: 0
A28: BALANCE SHEET
A29: Cash & Cash Equivalents (FY1992 source reports Cash + ST Investments combined) | B29: 11261 | C29: 9815 | D29: 10746 | E29: 14259 | F29: 13844 | G29: 21120 | H29: 20484 | I29: 20289 | J29: 25913 | K29: 48844 | L29: 38016 | M29: 34940 | N29: 23646 | O29: 29965 | P29: 29943 | Q29: 35934
A30: Short-Term Investments / Marketable Securities | B30: 14359 | C30: 16137 | D30: 18383 | E30: 26287 | F30: 11233 | G30: 20481 | H30: 46671 | I30: 53892 | J30: 40388 | K30: 51713 | L30: 52927 | M30: 27699 | N30: 24658 | O30: 31590 | P30: 35228 | Q30: 18763
A31: Accounts Receivable, Net | B31: 5510 | C31: 5369 | D31: 10930 | E31: 13102 | F31: 17460 | G31: 16849 | H31: 15754 | I31: 17874 | J31: 23186 | K31: 22926 | L31: 16120 | M31: 26278 | N31: 28184 | O31: 29508 | P31: 33410 | Q31: 39777
A32: Inventories | B32: 1051 | C32: 776 | D32: 791 | E32: 1764 | F32: 2111 | G32: 2349 | H32: 2132 | I32: 4855 | J32: 3956 | K32: 4106 | L32: 4061 | M32: 6580 | N32: 4946 | O32: 6331 | P32: 7286 | Q32: 5718
A33: Deferred Tax Assets | B33: 1636 | C33: 2014 | D33: 2583 | E33: 3453 | F33: 4318 | G33: 5546 | H33: 0 | I33: 0 | J33: 0 | K33: 0 | L33: 0 | M33: 0 | N33: 0 | O33: 0 | P33: 0 | Q33: 0
A34: Vendor Non-Trade Receivables | B34: 4414 | C34: 6348 | D34: 7762 | E34: 7539 | F34: 9759 | G34: 13494 | H34: 13545 | I34: 17799 | J34: 25809 | K34: 22878 | L34: 21325 | M34: 25228 | N34: 32748 | O34: 31477 | P34: 32833 | Q34: 33180
A35: Other Current Assets | B35: 3447 | C35: 4529 | D35: 6458 | E35: 6882 | F35: 9806 | G35: 9539 | H35: 8283 | I35: 13936 | J35: 12087 | K35: 12352 | L35: 11264 | M35: 14111 | N35: 21223 | O35: 14695 | P35: 14287 | Q35: 14585
A36: Total Current Assets | B36: =B29+B30+B31+B32+B33+B34+B35 -> 41678 | C36: =C29+C30+C31+C32+C33+C34+C35 -> 44988 | D36: =D29+D30+D31+D32+D33+D34+D35 -> 57653 | E36: =E29+E30+E31+E32+E33+E34+E35 -> 73286 | F36: =F29+F30+F31+F32+F33+F34+F35 -> 68531 | G36: =G29+G30+G31+G32+G33+G34+G35 -> 89378 | H36: =H29+H30+H31+H32+H33+H34+H35 -> 106869 | I36: =I29+I30+I31+I32+I33+I34+I35 -> 128645 | ... Q36: =Q29+Q30+Q31+Q32+Q33+Q34+Q35 -> 147957
A38: Property, Plant & Equipment, Net | B38: 4768 | C38: 7777 | D38: 15452 | E38: 16597 | F38: 20624 | G38: 22471 | H38: 27010 | I38: 33783 | J38: 41304 | K38: 37378 | L38: 36766 | M38: 39440 | N38: 42117 | O38: 43715 | P38: 45680 | Q38: 49834
A39: Long-Term Marketable Securities | B39: 25391 | C39: 55618 | D39: 92122 | E39: 106215 | F39: 130162 | G39: 164065 | H39: 170430 | I39: 194714 | J39: 170799 | K39: 105341 | L39: 100887 | M39: 127877 | N39: 120805 | O39: 100544 | P39: 91479 | Q39: 77723
A40: Goodwill | B40: 741 | C40: 896 | D40: 1135 | E40: 1577 | F40: 4616 | G40: 5116 | H40: 5414 | I40: 5717 | J40: 0 | K40: 0 | L40: 0 | M40: 0 | N40: 0 | O40: 0 | P40: 0 | Q40: 0
A41: Acquired Intangible Assets, Net | B41: 342 | C41: 3536 | D41: 4224 | E41: 4179 | F41: 4142 | G41: 3893 | H41: 3206 | I41: 2298 | J41: 0 | K41: 0 | L41: 0 | M41: 0 | N41: 0 | O41: 0 | P41: 0 | Q41: 0
A42: Other Assets (legacy) | B42: 2263 | C42: 3556 | D42: 5478 | E42: 5146 | F42: 3764 | G42: 5556 | H42: 8757 | I42: 10162 | J42: 0 | K42: 0 | L42: 0 | M42: 0 | N42: 0 | O42: 0 | P42: 0 | Q42: 0
A43: Other Non-Current Assets | B43: 0 | C43: 0 | D43: 0 | E43: 0 | F43: 0 | G43: 0 | H43: 0 | I43: 0 | J43: 22283 | K43: 32978 | L43: 42522 | M43: 48849 | N43: 54428 | O43: 64758 | P43: 74834 | Q43: 83727
A44: Total Non-Current Assets | B44: =B38+B39+B40+B41+B42+B43 -> 33505 | C44: =C38+C39+C40+C41+C42+C43 -> 71383 | D44: =D38+D39+D40+D41+D42+D43 -> 118411 | E44: =E38+E39+E40+E41+E42+E43 -> 133714 | F44: =F38+F39+F40+F41+F42+F43 -> 163308 | G44: =G38+G39+G40+G41+G42+G43 -> 201101 | H44: =H38+H39+H40+H41+H42+H43 -> 214817 | I44: =I38+I39+I40+I41+I42+I43 -> 246674 | ... Q44: =Q38+Q39+Q40+Q41+Q42+Q43 -> 211284
A45: Total Assets | B45: =B36+B44 -> 75183 | C45: =C36+C44 -> 116371 | D45: =D36+D44 -> 176064 | E45: =E36+E44 -> 207000 | F45: =F36+F44 -> 231839 | G45: =G36+G44 -> 290479 | H45: =H36+H44 -> 321686 | I45: =I36+I44 -> 375319 | ... Q45: =Q36+Q44 -> 359241
A47: Short-Term Borrowings / Notes Payable | B47: 0 | C47: 0 | D47: 0 | E47: 0 | F47: 0 | G47: 0 | H47: 0 | I47: 0 | J47: 0 | K47: 0 | L47: 0 | M47: 0 | N47: 0 | O47: 0 | P47: 0 | Q47: 0
A48: Accounts Payable | B48: 12015 | C48: 14632 | D48: 21175 | E48: 22367 | F48: 30196 | G48: 35490 | H48: 37294 | I48: 49049 | J48: 55888 | K48: 46236 | L48: 42296 | M48: 54763 | N48: 64115 | O48: 62611 | P48: 68960 | Q48: 69860
A49: Accrued Expenses | B49: 5723 | C49: 9247 | D49: 11414 | E49: 13856 | F49: 18453 | G49: 25181 | H49: 22027 | I49: 25744 | J49: 0 | K49: 0 | L49: 0 | M49: 0 | N49: 0 | O49: 0 | P49: 0 | Q49: 0
A50: Deferred Revenue - Current | B50: 2984 | C50: 4091 | D50: 5953 | E50: 7435 | F50: 8491 | G50: 8940 | H50: 8080 | I50: 7548 | J50: 7543 | K50: 5522 | L50: 6643 | M50: 7612 | N50: 7912 | O50: 8061 | P50: 8249 | Q50: 9055
A51: Other Current Liabilities | B51: 0 | C51: 0 | D51: 0 | E51: 0 | F51: 0 | G51: 0 | H51: 0 | I51: 0 | J51: 32687 | K51: 37720 | L51: 42684 | M51: 47493 | N51: 60845 | O51: 58829 | P51: 78304 | Q51: 66387
A52: Commercial Paper | B52: 0 | C52: 0 | D52: 0 | E52: 0 | F52: 6308 | G52: 8499 | H52: 8105 | I52: 11977 | J52: 11964 | K52: 5980 | L52: 4996 | M52: 6000 | N52: 9982 | O52: 5985 | P52: 9967 | Q52: 7979
A53: Current Debt / Term Debt | B53: 0 | C53: 0 | D53: 0 | E53: 0 | F53: 0 | G53: 2500 | H53: 3500 | I53: 6496 | J53: 8784 | K53: 10260 | L53: 8773 | M53: 9613 | N53: 11128 | O53: 9822 | P53: 10912 | Q53: 12350
A54: Total Current Liabilities | B54: =SUM(B47:B53) -> 20722 | C54: =SUM(C47:C53) -> 27970 | D54: =SUM(D47:D53) -> 38542 | E54: =SUM(E47:E53) -> 43658 | F54: =SUM(F47:F53) -> 63448 | G54: =SUM(G47:G53) -> 80610 | H54: =SUM(H47:H53) -> 79006 | I54: =SUM(I47:I53) -> 100814 | ... Q54: =SUM(Q47:Q53) -> 165631
A56: Long-Term Debt / Term Debt | B56: 0 | C56: 0 | D56: 0 | E56: 16960 | F56: 28987 | G56: 53463 | H56: 75427 | I56: 97207 | J56: 93735 | K56: 91807 | L56: 98667 | M56: 109106 | N56: 98959 | O56: 95281 | P56: 85750 | Q56: 78328
A57: Deferred Revenue - Non-Current | B57: 1139 | C57: 1686 | D57: 2648 | E57: 2625 | F57: 3031 | G57: 3624 | H57: 2930 | I57: 2836 | J57: 2797 | K57: 0 | L57: 0 | M57: 0 | N57: 0 | O57: 0 | P57: 0 | Q57: 0
A58: Other Non-Current Liabilities | B58: 5531 | C58: 10100 | D58: 16664 | E58: 20208 | F58: 24826 | G58: 33427 | H58: 36074 | I58: 40415 | J58: 45180 | K58: 50503 | L58: 54490 | M58: 53325 | N58: 49142 | O58: 49848 | P58: 45888 | Q58: 41549
A59: Total Non-Current Liabilities | B59: =SUM(B56:B58) -> 6670 | C59: =SUM(C56:C58) -> 11786 | D59: =SUM(D56:D58) -> 19312 | E59: =SUM(E56:E58) -> 39793 | F59: =SUM(F56:F58) -> 56844 | G59: =SUM(G56:G58) -> 90514 | H59: =SUM(H56:H58) -> 114431 | I59: =SUM(I56:I58) -> 140458 | ... Q59: =SUM(Q56:Q58) -> 119877
A60: Total Liabilities | B60: =B54+B59 -> 27392 | C60: =C54+C59 -> 39756 | D60: =D54+D59 -> 57854 | E60: =E54+E59 -> 83451 | F60: =F54+F59 -> 120292 | G60: =G54+G59 -> 171124 | H60: =H54+H59 -> 193437 | I60: =I54+I59 -> 241272 | ... Q60: =Q54+Q59 -> 285508
A62: Common Stock & Additional Paid-In Capital | B62: 10668 | C62: 13331 | D62: 16422 | E62: 19764 | F62: 23313 | G62: 27416 | H62: 31251 | I62: 35867 | J62: 40201 | K62: 45174 | L62: 50779 | M62: 57365 | N62: 64849 | O62: 73812 | P62: 83276 | Q62: 93568
A63: Retained Earnings | B63: 37169 | C63: 62841 | D63: 101289 | E63: 104256 | F63: 87152 | G63: 92284 | H63: 96364 | I63: 98330 | J63: 70400 | K63: 45898 | L63: 14966 | M63: 5562 | N63: 0 | O63: 0 | P63: 0 | Q63: 0
A64: Accumulated Deficit | B64: 0 | C64: 0 | D64: 0 | E64: 0 | F64: 0 | G64: 0 | H64: 0 | I64: 0 | J64: 0 | K64: 0 | L64: 0 | M64: 0 | N64: -3068 | O64: -214 | P64: -19154 | Q64: -14264
A65: Accumulated Other Comprehensive Income/(Loss) | B65: -46 | C65: 443 | D65: 499 | E65: -471 | F65: 1082 | G65: -345 | H65: 634 | I65: -150 | J65: -3454 | K65: -584 | L65: -406 | M65: 163 | N65: -11109 | O65: -11452 | P65: -7172 | Q65: -5571
A66: Total Shareholders' Equity | B66: =SUM(B62:B65) -> 47791 | C66: =SUM(C62:C65) -> 76615 | D66: =SUM(D62:D65) -> 118210 | E66: =SUM(E62:E65) -> 123549 | F66: =SUM(F62:F65) -> 111547 | G66: =SUM(G62:G65) -> 119355 | H66: =SUM(H62:H65) -> 128249 | I66: =SUM(I62:I65) -> 134047 | ... Q66: =SUM(Q62:Q65) -> 73733
A67: Total Liabilities & Shareholders' Equity | B67: =B60+B66 -> 75183 | C67: =C60+C66 -> 116371 | D67: =D60+D66 -> 176064 | E67: =E60+E66 -> 207000 | F67: =F60+F66 -> 231839 | G67: =G60+G66 -> 290479 | H67: =H60+H66 -> 321686 | I67: =I60+I66 -> 375319 | ... Q67: =Q60+Q66 -> 359241
A70: Share price October 2026 | B70: 10.75 | C70: 14.46 | D70: 21.26 | E70: 18.67 | F70: 27 | G70: 29.88 | H70: 28.39 | I70: 42.26 | J70: 54.72 | K70: 62.19 | L70: 108.86 | M70: 149.8 | N70: 153.34 | O70: 170.77 | P70: 225.91 | Q70: 332.27
A74: INVESTMENT RATIOS — SHARE PRICE INPUT FROM ROW 70
A75: Market price per share (USD; linked to source row 70) | B75: =IFERROR(B70,"") -> 10.75 | C75: =IFERROR(C70,"") -> 14.46 | D75: =IFERROR(D70,"") -> 21.26 | E75: =IFERROR(E70,"") -> 18.67 | F75: =IFERROR(F70,"") -> 27 | G75: =IFERROR(G70,"") -> 29.88 | H75: =IFERROR(H70,"") -> 28.39 | I75: =IFERROR(I70,"") -> 42.26 | ... Q75: =IFERROR(Q70,"") -> 332.27
A76: Basic EPS (USD per share) | B76: =IFERROR(B20*1000/B23,"") -> 15.408027 | C76: =IFERROR(C20*1000/C23,"") -> 28.046281 | D76: =IFERROR(D20*1000/D23,"") -> 44.642914 | E76: =IFERROR(E20*1000/E23,"") -> 40.025677 | F76: =IFERROR(F20*1000/F23,"") -> 6.4924053 | G76: =IFERROR(G20*1000/G23,"") -> 9.2803916 | H76: =IFERROR(H20*1000/H23,"") -> 8.3510333 | I76: =IFERROR(I20*1000/I23,"") -> 9.2675402 | ... Q76: =IFERROR(Q20*1000/Q23,"") -> 7.4930595
A77: Diluted EPS (USD per share) | B77: =IFERROR(B20*1000/B24,"") -> 15.153907 | C77: =IFERROR(C20*1000/C24,"") -> 27.675373 | D77: =IFERROR(D20*1000/D24,"") -> 44.145321 | E77: =IFERROR(E20*1000/E24,"") -> 39.753687 | F77: =IFERROR(F20*1000/F24,"") -> 6.4530744 | G77: =IFERROR(G20*1000/G24,"") -> 9.2168762 | H77: =IFERROR(H20*1000/H24,"") -> 8.3063029 | I77: =IFERROR(I20*1000/I24,"") -> 9.2067471 | ... Q77: =IFERROR(Q20*1000/Q24,"") -> 7.4649958
A78: Price / earnings (diluted) | B78: =IFERROR(B70/(B20*1000/B24),"") -> 0.709388 | C78: =IFERROR(C70/(C20*1000/C24),"") -> 0.52248618 | D78: =IFERROR(D70/(D20*1000/D24),"") -> 0.48159124 | E78: =IFERROR(E70/(E20*1000/E24),"") -> 0.46964197 | F78: =IFERROR(F70/(F20*1000/F24),"") -> 4.1840522 | G78: =IFERROR(G70/(G20*1000/G24),"") -> 3.2418793 | H78: =IFERROR(H70/(H20*1000/H24),"") -> 3.4178864 | I78: =IFERROR(I70/(I20*1000/I24),"") -> 4.590112 | ... Q78: =IFERROR(Q70/(Q20*1000/Q24),"") -> 44.510407
A79: Earnings yield (diluted) | B79: =IFERROR((B20*1000/B24)/B70,"") -> 1.4096658 | C79: =IFERROR((C20*1000/C24)/C70,"") -> 1.9139262 | D79: =IFERROR((D20*1000/D24)/D70,"") -> 2.0764497 | E79: =IFERROR((E20*1000/E24)/E70,"") -> 2.1292816 | F79: =IFERROR((F20*1000/F24)/F70,"") -> 0.23900276 | G79: =IFERROR((G20*1000/G24)/G70,"") -> 0.30846306 | H79: =IFERROR((H20*1000/H24)/H70,"") -> 0.29257847 | I79: =IFERROR((I20*1000/I24)/I70,"") -> 0.21785961 | ... Q79: =IFERROR((Q20*1000/Q24)/Q70,"") -> 0.022466656
A80: Dividend yield | B80: =IFERROR(B25/B70,"") -> 0 | C80: =IFERROR(C25/C70,"") -> 0 | D80: =IFERROR(D25/D70,"") -> 0.017873942 | E80: =IFERROR(E25/E70,"") -> 0.087841457 | F80: =IFERROR(F25/F70,"") -> 0.067407407 | G80: =IFERROR(G25/G70,"") -> 0.06626506 | H80: =IFERROR(H25/H70,"") -> 0.076787601 | I80: =IFERROR(I25/I70,"") -> 0.056791292 | ... Q80: =IFERROR(Q25/Q70,"") -> 0
A81: Dividend payout ratio (diluted EPS) | B81: =IFERROR(B25/(B20*1000/B24),"") -> 0 | C81: =IFERROR(C25/(C20*1000/C24),"") -> 0 | D81: =IFERROR(D25/(D20*1000/D24),"") -> 0.0086079338 | E81: =IFERROR(E25/(E20*1000/E24),"") -> 0.041254035 | F81: =IFERROR(F25/(F20*1000/F24),"") -> 0.28203611 | G81: =IFERROR(G25/(G20*1000/G24),"") -> 0.21482333 | H81: =IFERROR(H25/(H20*1000/H24),"") -> 0.2624513 | I81: =IFERROR(I25/(I20*1000/I24),"") -> 0.26067839 | ... Q81: =IFERROR(Q25/(Q20*1000/Q24),"") -> 0
A82: Retention ratio | B82: =IFERROR(1-B25/(B20*1000/B24),"") -> 1 | C82: =IFERROR(1-C25/(C20*1000/C24),"") -> 1 | D82: =IFERROR(1-D25/(D20*1000/D24),"") -> 0.99139207 | E82: =IFERROR(1-E25/(E20*1000/E24),"") -> 0.95874597 | F82: =IFERROR(1-F25/(F20*1000/F24),"") -> 0.71796389 | G82: =IFERROR(1-G25/(G20*1000/G24),"") -> 0.78517667 | H82: =IFERROR(1-H25/(H20*1000/H24),"") -> 0.7375487 | I82: =IFERROR(1-I25/(I20*1000/I24),"") -> 0.73932161 | ... Q82: =IFERROR(1-Q25/(Q20*1000/Q24),"") -> 1
A83: Book value per diluted share (USD) | B83: =IFERROR(B66*1000/B24,"") -> 51.682037 | C83: =IFERROR(C66*1000/C24,"") -> 81.797266 | D83: =IFERROR(D66*1000/D24,"") -> 125.04297 | E83: =IFERROR(E66*1000/E24,"") -> 132.6114 | F83: =IFERROR(F66*1000/F24,"") -> 18.218706 | G83: =IFERROR(G66*1000/G24,"") -> 20.603069 | H83: =IFERROR(H66*1000/H24,"") -> 23.316809 | I83: =IFERROR(I66*1000/I24,"") -> 25.524536 | ... Q83: =IFERROR(Q66*1000/Q24,"") -> 4.9139946
A84: Price / book value | B84: =IFERROR(B70/(B66*1000/B24),"") -> 0.20800264 | C84: =IFERROR(C70/(C66*1000/C24),"") -> 0.17677853 | D84: =IFERROR(D70/(D66*1000/D24),"") -> 0.17002155 | E84: =IFERROR(E70/(E66*1000/E24),"") -> 0.1407873 | F84: =IFERROR(F70/(F66*1000/F24),"") -> 1.4819932 | G84: =IFERROR(G70/(G66*1000/G24),"") -> 1.4502694 | H84: =IFERROR(H70/(H66*1000/H24),"") -> 1.2175766 | I84: =IFERROR(I70/(I66*1000/I24),"") -> 1.6556618 | ... Q84: =IFERROR(Q70/(Q66*1000/Q24),"") -> 67.617087
A85: Price / sales | B85: =IFERROR(B70/(B4*1000/B24),"") -> 0.15240558 | C85: =IFERROR(C70/(C4*1000/C24),"") -> 0.12511789 | D85: =IFERROR(D70/(D4*1000/D24),"") -> 0.12841674 | E85: =IFERROR(E70/(E4*1000/E24),"") -> 0.10177362 | F85: =IFERROR(F70/(F4*1000/F24),"") -> 0.9043568 | G85: =IFERROR(G70/(G4*1000/G24),"") -> 0.7406324 | H85: =IFERROR(H70/(H4*1000/H24),"") -> 0.72414071 | I85: =IFERROR(I70/(I4*1000/I24),"") -> 0.96816573 | ... Q85: =IFERROR(Q70/(Q4*1000/Q24),"") -> 11.980005
A86: Market capitalization (USD millions; diluted shares proxy) | B86: =IFERROR(B70*B24/1000,"") -> 9940.654 | C86: =IFERROR(C70*C24/1000,"") -> 13543.887 | D86: =IFERROR(D70*D24/1000,"") -> 20098.247 | E86: =IFERROR(E70*E24/1000,"") -> 17394.13 | F86: =IFERROR(F70*F24/1000,"") -> 165311.9 | G86: =IFERROR(G70*G24/1000,"") -> 173096.9 | H86: =IFERROR(H70*H24/1000,"") -> 156152.98 | I86: =IFERROR(I70*I24/1000,"") -> 221936.5 | ... Q86: =IFERROR(Q70*Q24/1000,"") -> 4985610.7
A87: Market value / total assets | B87: =IFERROR((B70*B24/1000)/B45,"") -> 0.13221944 | C87: =IFERROR((C70*C24/1000)/C45,"") -> 0.11638541 | D87: =IFERROR((D70*D24/1000)/D45,"") -> 0.11415308 | E87: =IFERROR((E70*E24/1000)/E45,"") -> 0.084029611 | F87: =IFERROR((F70*F24/1000)/F45,"") -> 0.71304613 | G87: =IFERROR((G70*G24/1000)/G45,"") -> 0.5959016 | H87: =IFERROR((H70*H24/1000)/H45,"") -> 0.4854205 | I87: =IFERROR((I70*I24/1000)/I45,"") -> 0.59132765 | ... Q87: =IFERROR((Q70*Q24/1000)/Q45,"") -> 13.878178
A88: Sustainable growth rate (ROE × retention) | B88: ="" | C88: =IFERROR((C20/AVERAGE(B66:C66))*(1-C25/(C20*1000/C24)),"") -> 0.41673231 | D88: =IFERROR((D20/AVERAGE(C66:D66))*(1-D25/(D20*1000/D24)),"") -> 0.42472747 | E88: =IFERROR((E20/AVERAGE(D66:E66))*(1-E25/(E20*1000/E24)),"") -> 0.29375597 | F88: =IFERROR((F20/AVERAGE(E66:F66))*(1-F25/(F20*1000/F24)),"") -> 0.2413206 | G88: =IFERROR((G20/AVERAGE(F66:G66))*(1-G25/(G20*1000/G24)),"") -> 0.36313002 | H88: =IFERROR((H20/AVERAGE(G66:H66))*(1-H25/(H20*1000/H24)),"") -> 0.27217967 | I88: =IFERROR((I20/AVERAGE(H66:I66))*(1-I25/(I20*1000/I24)),"") -> 0.27256946 | J88: =IFERROR((J20/AVERAGE(I66:J66))*(1-J25/(J20*1000/J24)),"") -> 0.49363583 | ... Q88: =IFERROR((Q20/AVERAGE(P66:Q66))*(1-Q25/(Q20*1000/Q24)),"") -> 1.7142245
A89: Revenue growth rate | B89: ="" | C89: =IFERROR(C4/B4-1,"") -> 0.65962438 | D89: =IFERROR(D4/C4-1,"") -> 0.44581474 | E89: =IFERROR(E4/D4-1,"") -> 0.092020855 | F89: =IFERROR(F4/E4-1,"") -> 0.069539524 | G89: =IFERROR(G4/F4-1,"") -> 0.27856342 | H89: =IFERROR(H4/G4-1,"") -> -0.077342062 | I89: =IFERROR(I4/H4-1,"") -> 0.063045182 | J89: =IFERROR(J4/I4-1,"") -> 0.15861958 | ... Q89: =IFERROR(Q4/P4-1,"") -> 0.064255118
A90: Net income growth rate | B90: ="" | C90: =IFERROR(C20/B20-1,"") -> 0.84985371 | D90: =IFERROR(D20/C20-1,"") -> 0.60994522 | E90: =IFERROR(E20/D20-1,"") -> -0.11252486 | F90: =IFERROR(F20/E20-1,"") -> 0.066771067 | G90: =IFERROR(G20/F20-1,"") -> 0.35140471 | H90: =IFERROR(H20/G20-1,"") -> -0.14434206 | I90: =IFERROR(I20/H20-1,"") -> 0.058309804 | J90: =IFERROR(J20/I20-1,"") -> 0.23122583 | ... Q90: =IFERROR(Q20/P20-1,"") -> 0.19495178
A91: Diluted EPS growth rate | B91: ="" | C91: =IFERROR((C20/C24)/(B20/B24)-1,"") -> 0.82628629 | D91: =IFERROR((D20/D24)/(C20/C24)-1,"") -> 0.59511204 | E91: =IFERROR((E20/E24)/(D20/D24)-1,"") -> -0.099481292 | F91: =IFERROR((F20/F24)/(E20/E24)-1,"") -> -0.83767356 | G91: =IFERROR((G20/G24)/(F20/F24)-1,"") -> 0.42829226 | H91: =IFERROR((H20/H24)/(G20/G24)-1,"") -> -0.098794138 | I91: =IFERROR((I20/I24)/(H20/H24)-1,"") -> 0.10840493 | J91: =IFERROR((J20/J24)/(I20/I24)-1,"") -> 0.29317557 | ... Q91: =IFERROR((Q20/Q24)/(P20/P24)-1,"") -> 0.2270778
A100: Caution: Row 70 is labeled “Share price October 2026” although it contains different annual prices; verify the input prices and split basis before relying on investment ratios.
